Workbook

Sheet NOW
A1: ▸ | B1: Run 1 | C1: hickman-ff | E1: ▸ | F1: Run 2 | G1: simonson-thor
A2: {=IFERROR(_xlfn.XLOOKUP($C$1, Runs[Run ID], Runs[Title]), "— pick a run —") & " (" & IFERROR(_xlfn.XLOOKUP($C$1, Runs[Run ID], Runs[Track]), "— pick a run —") & ")"} -> Hickman's Fantastic Four / FF (Hickman Saga) | E2: {=IFERROR(_xlfn.XLOOKUP($G$1, Runs[Run ID], Runs[Title]), "— pick a run —") & " (" & IFERROR(_xlfn.XLOOKUP($G$1, Runs[Run ID], Runs[Track]), "— pick a run —") & ")"} -> Simonson's Thor (Thor)
A4: Progress | C4: =IF(COUNTIF(Reading_Order[Run ID],$C$1)=0,"",REPT("▰",ROUND((1-$C$5/COUNTIF(Reading_Order[Run ID],$C$1))*10,0))&REPT("▱",10-ROUND((1-$C$5/COUNTIF(Reading_Order[Run ID],$C$1))*10,0))&" "&TEXT(1-$C$5/COUNTIF(Reading_Order[Run ID],$C$1),"0%")) -> ▰▰▰▰▰▱▱▱▱▱ 46% | E4: Progress | G4: =IF(COUNTIF(Reading_Order[Run ID],$G$1)=0,"",REPT("▰",ROUND((1-$G$5/COUNTIF(Reading_Order[Run ID],$G$1))*10,0))&REPT("▱",10-ROUND((1-$G$5/COUNTIF(Reading_Order[Run ID],$G$1))*10,0))&" "&TEXT(1-$G$5/COUNTIF(Reading_Order[Run ID],$G$1),"0%")) -> ▰▰▰▱▱▱▱▱▱▱ 34%
A5: Left | C5: =COUNTIFS(Reading_Order[Run ID],$C$1,Reading_Order[Completed],FALSE) -> 33 | E5: Left | G5: =COUNTIFS(Reading_Order[Run ID],$G$1,Reading_Order[Completed],FALSE) -> 33
A6: Est. done | C6: =IF($C$5=0, "✓ complete", TEXT(TODAY()+$C$5, "d mmm yyyy")) -> 31 Oct 2026 | E6: Est. done | G6: =IF($G$5=0, "✓ complete", TEXT(TODAY()+$G$5, "d mmm yyyy")) -> 31 Oct 2026
A7: Next up | C7: =IFERROR(__xludf.DUMMYFUNCTION("IFERROR(INDEX(SORT(FILTER(Reading_Order[Issue],Reading_Order[Run ID]=$C$1,Reading_Order[Completed]=FALSE),FILTER(Reading_Order[Sequence],Reading_Order[Run ID]=$C$1,Reading_Order[Completed]=FALSE),TRUE),1),""✓ run complete"")"),"FF (2011) #4") -> FF (2011) #4 | E7: Next up | G7: =IFERROR(__xludf.DUMMYFUNCTION("IFERROR(INDEX(SORT(FILTER(Reading_Order[Issue],Reading_Order[Run ID]=$G$1,Reading_Order[Completed]=FALSE),FILTER(Reading_Order[Sequence],Reading_Order[Run ID]=$G$1,Reading_Order[Completed]=FALSE),TRUE),1),""✓ run complete"")"),"Thor #354") -> Thor #354
A9: =IFERROR(__xludf.DUMMYFUNCTION("LET(r, $C$1, t, XLOOKUP(r, Runs[Run ID], Runs[Track]), b, XLOOKUP(r, Runs[Run ID], Runs[Block]), rows, SORT(FILTER(CHOOSECOLS(Runs, 16, 2, 1, 7, 11), (Runs[Track]=t)*(Runs[Block]=b)), 1, 1), HSTACK( MAP(CH"&"OOSECOLS(rows,2), CHOOSECOLS(rows,5), LAMBDA(id, st, IF(id=r, ""▶"", IF(st=""read"", ""✓"", ""·"")))), CHOOSECOLS(rows, 3, 4, 5)))"),"✓") -> ✓ | B9: =IFERROR(__xludf.DUMMYFUNCTION("""COMPUTED_VALUE"""),"Secret Warriors") -> Secret Warriors | C9: =IFERROR(__xludf.DUMMYFUNCTION("""COMPUTED_VALUE"""),31.0) -> 31 | D9: =IFERROR(__xludf.DUMMYFUNCTION("""COMPUTED_VALUE"""),"read") -> read | E9: =IFERROR(__xludf.DUMMYFUNCTION("LET(r, $G$1, t, XLOOKUP(r, Runs[Run ID], Runs[Track]), b, XLOOKUP(r, Runs[Run ID], Runs[Block]), rows, SORT(FILTER(CHOOSECOLS(Runs, 16, 2, 1, 7, 11), (Runs[Track]=t)*(Runs[Block]=b)), 1, 1), HSTACK( MAP(CH"&"OOSECOLS(rows,2), CHOOSECOLS(rows,5), LAMBDA(id, st, IF(id=r, ""▶"", IF(st=""read"", ""✓"", ""·"")))), CHOOSECOLS(rows, 3, 4, 5)))"),"▶") -> ▶ | F9: =IFERROR(__xludf.DUMMYFUNCTION("""COMPUTED_VALUE"""),"Simonson's Thor") -> Simonson's Thor | G9: =IFERROR(__xludf.DUMMYFUNCTION("""COMPUTED_VALUE"""),50.0) -> 50 | H9: =IFERROR(__xludf.DUMMYFUNCTION("""COMPUTED_VALUE"""),"reading") -> reading
A10: =IFERROR(__xludf.DUMMYFUNCTION("""COMPUTED_VALUE"""),"▶") -> ▶ | B10: =IFERROR(__xludf.DUMMYFUNCTION("""COMPUTED_VALUE"""),"Hickman's Fantastic Four / FF") -> Hickman's Fantastic Four / FF | C10: =IFERROR(__xludf.DUMMYFUNCTION("""COMPUTED_VALUE"""),61.0) -> 61 | D10: =IFERROR(__xludf.DUMMYFUNCTION("""COMPUTED_VALUE"""),"reading") -> reading | E10: =IFERROR(__xludf.DUMMYFUNCTION("""COMPUTED_VALUE"""),"·") -> · | F10: =IFERROR(__xludf.DUMMYFUNCTION("""COMPUTED_VALUE"""),"Thor: God of Thunder") -> Thor: God of Thunder | G10: =IFERROR(__xludf.DUMMYFUNCTION("""COMPUTED_VALUE"""),34.0) -> 34 | H10: =IFERROR(__xludf.DUMMYFUNCTION("""COMPUTED_VALUE"""),"unread") -> unread
A11: =IFERROR(__xludf.DUMMYFUNCTION("""COMPUTED_VALUE"""),"·") -> · | B11: =IFERROR(__xludf.DUMMYFUNCTION("""COMPUTED_VALUE"""),"S.H.I.E.L.D.") -> S.H.I.E.L.D. | C11: =IFERROR(__xludf.DUMMYFUNCTION("""COMPUTED_VALUE"""),13.0) -> 13 | D11: =IFERROR(__xludf.DUMMYFUNCTION("""COMPUTED_VALUE"""),"unread") -> unread | E11: =IFERROR(__xludf.DUMMYFUNCTION("""COMPUTED_VALUE"""),"·") -> · | F11: =IFERROR(__xludf.DUMMYFUNCTION("""COMPUTED_VALUE"""),"Original Sin") -> Original Sin | G11: =IFERROR(__xludf.DUMMYFUNCTION("""COMPUTED_VALUE"""),5.0) -> 5 | H11: =IFERROR(__xludf.DUMMYFUNCTION("""COMPUTED_VALUE"""),"unread") -> unread
A12: =IFERROR(__xludf.DUMMYFUNCTION("""COMPUTED_VALUE"""),"·") -> · | B12: =IFERROR(__xludf.DUMMYFUNCTION("""COMPUTED_VALUE"""),"Illuminati Prelude") -> Illuminati Prelude | C12: =IFERROR(__xludf.DUMMYFUNCTION("""COMPUTED_VALUE"""),6.0) -> 6 | D12: =IFERROR(__xludf.DUMMYFUNCTION("""COMPUTED_VALUE"""),"unread") -> unread | E12: =IFERROR(__xludf.DUMMYFUNCTION("""COMPUTED_VALUE"""),"·") -> · | F12: =IFERROR(__xludf.DUMMYFUNCTION("""COMPUTED_VALUE"""),"Aaron's Thor / Mighty Thor") -> Aaron's Thor / Mighty Thor | G12: =IFERROR(__xludf.DUMMYFUNCTION("""COMPUTED_VALUE"""),52.0) -> 52 | H12: =IFERROR(__xludf.DUMMYFUNCTION("""COMPUTED_VALUE"""),"unread") -> unread
A13: =IFERROR(__xludf.DUMMYFUNCTION("""COMPUTED_VALUE"""),"·") -> · | B13: =IFERROR(__xludf.DUMMYFUNCTION("""COMPUTED_VALUE"""),"Ultimate Doomsday") -> Ultimate Doomsday | C13: =IFERROR(__xludf.DUMMYFUNCTION("""COMPUTED_VALUE"""),12.0) -> 12 | D13: =IFERROR(__xludf.DUMMYFUNCTION("""COMPUTED_VALUE"""),"unread") -> unread | E13: =IFERROR(__xludf.DUMMYFUNCTION("""COMPUTED_VALUE"""),"·") -> · | F13: =IFERROR(__xludf.DUMMYFUNCTION("""COMPUTED_VALUE"""),"War of the Realms") -> War of the Realms | G13: =IFERROR(__xludf.DUMMYFUNCTION("""COMPUTED_VALUE"""),36.0) -> 36 | H13: =IFERROR(__xludf.DUMMYFUNCTION("""COMPUTED_VALUE"""),"unread") -> unread
A14: =IFERROR(__xludf.DUMMYFUNCTION("""COMPUTED_VALUE"""),"·") -> · | B14: =IFERROR(__xludf.DUMMYFUNCTION("""COMPUTED_VALUE"""),"Ultimate Comics: Ultimates") -> Ultimate Comics: Ultimates | C14: =IFERROR(__xludf.DUMMYFUNCTION("""COMPUTED_VALUE"""),26.0) -> 26 | D14: =IFERROR(__xludf.DUMMYFUNCTION("""COMPUTED_VALUE"""),"unread") -> unread | E14: =IFERROR(__xludf.DUMMYFUNCTION("""COMPUTED_VALUE"""),"·") -> · | F14: =IFERROR(__xludf.DUMMYFUNCTION("""COMPUTED_VALUE"""),"King Thor") -> King Thor | G14: =IFERROR(__xludf.DUMMYFUNCTION("""COMPUTED_VALUE"""),14.0) -> 14 | H14: =IFERROR(__xludf.DUMMYFUNCTION("""COMPUTED_VALUE"""),"unread") -> unread
A15: =IFERROR(__xludf.DUMMYFUNCTION("""COMPUTED_VALUE"""),"·") -> · | B15: =IFERROR(__xludf.DUMMYFUNCTION("""COMPUTED_VALUE"""),"Hickman's Avengers World") -> Hickman's Avengers World | C15: =IFERROR(__xludf.DUMMYFUNCTION("""COMPUTED_VALUE"""),27.0) -> 27 | D15: =IFERROR(__xludf.DUMMYFUNCTION("""COMPUTED_VALUE"""),"unread") -> unread | E15: =IFERROR(__xludf.DUMMYFUNCTION("""COMPUTED_VALUE"""),"·") -> · | F15: =IFERROR(__xludf.DUMMYFUNCTION("""COMPUTED_VALUE"""),"Cates' Thor") -> Cates' Thor | G15: =IFERROR(__xludf.DUMMYFUNCTION("""COMPUTED_VALUE"""),42.0) -> 42 | H15: =IFERROR(__xludf.DUMMYFUNCTION("""COMPUTED_VALUE"""),"unread") -> unread
A16: =IFERROR(__xludf.DUMMYFUNCTION("""COMPUTED_VALUE"""),"·") -> · | B16: =IFERROR(__xludf.DUMMYFUNCTION("""COMPUTED_VALUE"""),"Infinity") -> Infinity | C16: =IFERROR(__xludf.DUMMYFUNCTION("""COMPUTED_VALUE"""),22.0) -> 22 | D16: =IFERROR(__xludf.DUMMYFUNCTION("""COMPUTED_VALUE"""),"unread") -> unread | E16: =IFERROR(__xludf.DUMMYFUNCTION("""COMPUTED_VALUE"""),"·") -> · | F16: =IFERROR(__xludf.DUMMYFUNCTION("""COMPUTED_VALUE"""),"Immortal Thor") -> Immortal Thor | G16: =IFERROR(__xludf.DUMMYFUNCTION("""COMPUTED_VALUE"""),41.0) -> 41 | H16: =IFERROR(__xludf.DUMMYFUNCTION("""COMPUTED_VALUE"""),"unread") -> unread
A17: =IFERROR(__xludf.DUMMYFUNCTION("""COMPUTED_VALUE"""),"·") -> · | B17: =IFERROR(__xludf.DUMMYFUNCTION("""COMPUTED_VALUE"""),"Hickman's Avengers / New Avengers") -> Hickman's Avengers / New Avengers | C17: =IFERROR(__xludf.DUMMYFUNCTION("""COMPUTED_VALUE"""),57.0) -> 57 | D17: =IFERROR(__xludf.DUMMYFUNCTION("""COMPUTED_VALUE"""),"unread") -> unread
A18: =IFERROR(__xludf.DUMMYFUNCTION("""COMPUTED_VALUE"""),"·") -> · | B18: =IFERROR(__xludf.DUMMYFUNCTION("""COMPUTED_VALUE"""),"Secret Wars (2015)") -> Secret Wars (2015) | C18: =IFERROR(__xludf.DUMMYFUNCTION("""COMPUTED_VALUE"""),16.0) -> 16 | D18: =IFERROR(__xludf.DUMMYFUNCTION("""COMPUTED_VALUE"""),"unread") -> unread
A27: ✓ | B27: ISSUE | E27: ✓ | F27: ISSUE
A28: =IFERROR(__xludf.DUMMYFUNCTION("IFERROR(SORT({FILTER(Reading_Order[Completed],Reading_Order[Run ID]=$C$1),FILTER(Reading_Order[Issue],Reading_Order[Run ID]=$C$1)},FILTER(Reading_Order[Sequence],Reading_Order[Run ID]=$C$1),TRUE),""No issues found for this Run ID"")"),TRUE) -> TRUE | B28: =IFERROR(__xludf.DUMMYFUNCTION("""COMPUTED_VALUE"""),"Dark Reign: Fantastic Four #1") -> Dark Reign: Fantastic Four #1 | E28: =IFERROR(__xludf.DUMMYFUNCTION("IFERROR(SORT({FILTER(Reading_Order[Completed],Reading_Order[Run ID]=$G$1),FILTER(Reading_Order[Issue],Reading_Order[Run ID]=$G$1)},FILTER(Reading_Order[Sequence],Reading_Order[Run ID]=$G$1),TRUE),""No issues found for this Run ID"")"),TRUE) -> TRUE | F28: =IFERROR(__xludf.DUMMYFUNCTION("""COMPUTED_VALUE"""),"Thor #337") -> Thor #337
A29: =IFERROR(__xludf.DUMMYFUNCTION("""COMPUTED_VALUE"""),TRUE) -> TRUE | B29: =IFERROR(__xludf.DUMMYFUNCTION("""COMPUTED_VALUE"""),"Dark Reign: Fantastic Four #2") -> Dark Reign: Fantastic Four #2 | E29: =IFERROR(__xludf.DUMMYFUNCTION("""COMPUTED_VALUE"""),TRUE) -> TRUE | F29: =IFERROR(__xludf.DUMMYFUNCTION("""COMPUTED_VALUE"""),"Thor #338") -> Thor #338
A30: =IFERROR(__xludf.DUMMYFUNCTION("""COMPUTED_VALUE"""),TRUE) -> TRUE | B30: =IFERROR(__xludf.DUMMYFUNCTION("""COMPUTED_VALUE"""),"Dark Reign: Fantastic Four #3") -> Dark Reign: Fantastic Four #3 | E30: =IFERROR(__xludf.DUMMYFUNCTION("""COMPUTED_VALUE"""),TRUE) -> TRUE | F30: =IFERROR(__xludf.DUMMYFUNCTION("""COMPUTED_VALUE"""),"Thor #339") -> Thor #339
A31: =IFERROR(__xludf.DUMMYFUNCTION("""COMPUTED_VALUE"""),TRUE) -> TRUE | B31: =IFERROR(__xludf.DUMMYFUNCTION("""COMPUTED_VALUE"""),"Dark Reign: Fantastic Four #4") -> Dark Reign: Fantastic Four #4 | E31: =IFERROR(__xludf.DUMMYFUNCTION("""COMPUTED_VALUE"""),TRUE) -> TRUE | F31: =IFERROR(__xludf.DUMMYFUNCTION("""COMPUTED_VALUE"""),"Thor #340") -> Thor #340
A32: =IFERROR(__xludf.DUMMYFUNCTION("""COMPUTED_VALUE"""),TRUE) -> TRUE | B32: =IFERROR(__xludf.DUMMYFUNCTION("""COMPUTED_VALUE"""),"Dark Reign: Fantastic Four #5") -> Dark Reign: Fantastic Four #5 | E32: =IFERROR(__xludf.DUMMYFUNCTION("""COMPUTED_VALUE"""),TRUE) -> TRUE | F32: =IFERROR(__xludf.DUMMYFUNCTION("""COMPUTED_VALUE"""),"Thor #341") -> Thor #341
A33: =IFERROR(__xludf.DUMMYFUNCTION("""COMPUTED_VALUE"""),TRUE) -> TRUE | B33: =IFERROR(__xludf.DUMMYFUNCTION("""COMPUTED_VALUE"""),"Dark Reign: The Cabal") -> Dark Reign: The Cabal | E33: =IFERROR(__xludf.DUMMYFUNCTION("""COMPUTED_VALUE"""),TRUE) -> TRUE | F33: =IFERROR(__xludf.DUMMYFUNCTION("""COMPUTED_VALUE"""),"Thor #342") -> Thor #342
A34: =IFERROR(__xludf.DUMMYFUNCTION("""COMPUTED_VALUE"""),TRUE) -> TRUE | B34: =IFERROR(__xludf.DUMMYFUNCTION("""COMPUTED_VALUE"""),"Fantastic Four (1998) #570") -> Fantastic Four (1998) #570 | E34: =IFERROR(__xludf.DUMMYFUNCTION("""COMPUTED_VALUE"""),TRUE) -> TRUE | F34: =IFERROR(__xludf.DUMMYFUNCTION("""COMPUTED_VALUE"""),"Thor #343") -> Thor #343
A35: =IFERROR(__xludf.DUMMYFUNCTION("""COMPUTED_VALUE"""),TRUE) -> TRUE | B35: =IFERROR(__xludf.DUMMYFUNCTION("""COMPUTED_VALUE"""),"Fantastic Four (1998) #571") -> Fantastic Four (1998) #571 | E35: =IFERROR(__xludf.DUMMYFUNCTION("""COMPUTED_VALUE"""),TRUE) -> TRUE | F35: =IFERROR(__xludf.DUMMYFUNCTION("""COMPUTED_VALUE"""),"Thor #344") -> Thor #344
A36: =IFERROR(__xludf.DUMMYFUNCTION("""COMPUTED_VALUE"""),TRUE) -> TRUE | B36: =IFERROR(__xludf.DUMMYFUNCTION("""COMPUTED_VALUE"""),"Fantastic Four (1998) #572") -> Fantastic Four (1998) #572 | E36: =IFERROR(__xludf.DUMMYFUNCTION("""COMPUTED_VALUE"""),TRUE) -> TRUE | F36: =IFERROR(__xludf.DUMMYFUNCTION("""COMPUTED_VALUE"""),"Thor #345") -> Thor #345
A37: =IFERROR(__xludf.DUMMYFUNCTION("""COMPUTED_VALUE"""),TRUE) -> TRUE | B37: =IFERROR(__xludf.DUMMYFUNCTION("""COMPUTED_VALUE"""),"Fantastic Four (1998) #573") -> Fantastic Four (1998) #573 | E37: =IFERROR(__xludf.DUMMYFUNCTION("""COMPUTED_VALUE"""),TRUE) -> TRUE | F37: =IFERROR(__xludf.DUMMYFUNCTION("""COMPUTED_VALUE"""),"Thor #346") -> Thor #346
A38: =IFERROR(__xludf.DUMMYFUNCTION("""COMPUTED_VALUE"""),TRUE) -> TRUE | B38: =IFERROR(__xludf.DUMMYFUNCTION("""COMPUTED_VALUE"""),"Fantastic Four (1998) #574") -> Fantastic Four (1998) #574 | E38: =IFERROR(__xludf.DUMMYFUNCTION("""COMPUTED_VALUE"""),TRUE) -> TRUE | F38: =IFERROR(__xludf.DUMMYFUNCTION("""COMPUTED_VALUE"""),"Thor #347") -> Thor #347
A39: =IFERROR(__xludf.DUMMYFUNCTION("""COMPUTED_VALUE"""),TRUE) -> TRUE | B39: =IFERROR(__xludf.DUMMYFUNCTION("""COMPUTED_VALUE"""),"Fantastic Four (1998) #575") -> Fantastic Four (1998) #575 | E39: =IFERROR(__xludf.DUMMYFUNCTION("""COMPUTED_VALUE"""),TRUE) -> TRUE | F39: =IFERROR(__xludf.DUMMYFUNCTION("""COMPUTED_VALUE"""),"Thor #348") -> Thor #348
A40: =IFERROR(__xludf.DUMMYFUNCTION("""COMPUTED_VALUE"""),TRUE) -> TRUE | B40: =IFERROR(__xludf.DUMMYFUNCTION("""COMPUTED_VALUE"""),"Fantastic Four (1998) #576") -> Fantastic Four (1998) #576 | E40: =IFERROR(__xludf.DUMMYFUNCTION("""COMPUTED_VALUE"""),TRUE) -> TRUE | F40: =IFERROR(__xludf.DUMMYFUNCTION("""COMPUTED_VALUE"""),"Thor #349") -> Thor #349
A41: =IFERROR(__xludf.DUMMYFUNCTION("""COMPUTED_VALUE"""),TRUE) -> TRUE | B41: =IFERROR(__xludf.DUMMYFUNCTION("""COMPUTED_VALUE"""),"Fantastic Four (1998) #577") -> Fantastic Four (1998) #577 | E41: =IFERROR(__xludf.DUMMYFUNCTION("""COMPUTED_VALUE"""),TRUE) -> TRUE | F41: =IFERROR(__xludf.DUMMYFUNCTION("""COMPUTED_VALUE"""),"Thor #350") -> Thor #350
A42: =IFERROR(__xludf.DUMMYFUNCTION("""COMPUTED_VALUE"""),TRUE) -> TRUE | B42: =IFERROR(__xludf.DUMMYFUNCTION("""COMPUTED_VALUE"""),"Fantastic Four (1998) #578") -> Fantastic Four (1998) #578 | E42: =IFERROR(__xludf.DUMMYFUNCTION("""COMPUTED_VALUE"""),TRUE) -> TRUE | F42: =IFERROR(__xludf.DUMMYFUNCTION("""COMPUTED_VALUE"""),"Thor #351") -> Thor #351
A43: =IFERROR(__xludf.DUMMYFUNCTION("""COMPUTED_VALUE"""),TRUE) -> TRUE | B43: =IFERROR(__xludf.DUMMYFUNCTION("""COMPUTED_VALUE"""),"Fantastic Four (1998) #579") -> Fantastic Four (1998) #579 | E43: =IFERROR(__xludf.DUMMYFUNCTION("""COMPUTED_VALUE"""),TRUE) -> TRUE | F43: =IFERROR(__xludf.DUMMYFUNCTION("""COMPUTED_VALUE"""),"Thor #352") -> Thor #352
A44: =IFERROR(__xludf.DUMMYFUNCTION("""COMPUTED_VALUE"""),TRUE) -> TRUE | B44: =IFERROR(__xludf.DUMMYFUNCTION("""COMPUTED_VALUE"""),"Fantastic Four (1998) #580") -> Fantastic Four (1998) #580 | E44: =IFERROR(__xludf.DUMMYFUNCTION("""COMPUTED_VALUE"""),TRUE) -> TRUE | F44: =IFERROR(__xludf.DUMMYFUNCTION("""COMPUTED_VALUE"""),"Thor #353") -> Thor #353
A45: =IFERROR(__xludf.DUMMYFUNCTION("""COMPUTED_VALUE"""),TRUE) -> TRUE | B45: =IFERROR(__xludf.DUMMYFUNCTION("""COMPUTED_VALUE"""),"Fantastic Four (1998) #581") -> Fantastic Four (1998) #581 | E45: =IFERROR(__xludf.DUMMYFUNCTION("""COMPUTED_VALUE"""),FALSE) -> FALSE | F45: =IFERROR(__xludf.DUMMYFUNCTION("""COMPUTED_VALUE"""),"Thor #354") -> Thor #354
A46: =IFERROR(__xludf.DUMMYFUNCTION("""COMPUTED_VALUE"""),TRUE) -> TRUE | B46: =IFERROR(__xludf.DUMMYFUNCTION("""COMPUTED_VALUE"""),"Fantastic Four (1998) #582") -> Fantastic Four (1998) #582 | E46: =IFERROR(__xludf.DUMMYFUNCTION("""COMPUTED_VALUE"""),FALSE) -> FALSE | F46: =IFERROR(__xludf.DUMMYFUNCTION("""COMPUTED_VALUE"""),"Thor #355") -> Thor #355
A47: =IFERROR(__xludf.DUMMYFUNCTION("""COMPUTED_VALUE"""),TRUE) -> TRUE | B47: =IFERROR(__xludf.DUMMYFUNCTION("""COMPUTED_VALUE"""),"Fantastic Four (1998) #583") -> Fantastic Four (1998) #583 | E47: =IFERROR(__xludf.DUMMYFUNCTION("""COMPUTED_VALUE"""),FALSE) -> FALSE | F47: =IFERROR(__xludf.DUMMYFUNCTION("""COMPUTED_VALUE"""),"Thor #356") -> Thor #356
A48: =IFERROR(__xludf.DUMMYFUNCTION("""COMPUTED_VALUE"""),TRUE) -> TRUE | B48: =IFERROR(__xludf.DUMMYFUNCTION("""COMPUTED_VALUE"""),"Fantastic Four (1998) #584") -> Fantastic Four (1998) #584 | E48: =IFERROR(__xludf.DUMMYFUNCTION("""COMPUTED_VALUE"""),FALSE) -> FALSE | F48: =IFERROR(__xludf.DUMMYFUNCTION("""COMPUTED_VALUE"""),"Thor #357") -> Thor #357
A49: =IFERROR(__xludf.DUMMYFUNCTION("""COMPUTED_VALUE"""),TRUE) -> TRUE | B49: =IFERROR(__xludf.DUMMYFUNCTION("""COMPUTED_VALUE"""),"Fantastic Four (1998) #585") -> Fantastic Four (1998) #585 | E49: =IFERROR(__xludf.DUMMYFUNCTION("""COMPUTED_VALUE"""),FALSE) -> FALSE | F49: =IFERROR(__xludf.DUMMYFUNCTION("""COMPUTED_VALUE"""),"Thor #358") -> Thor #358
A50: =IFERROR(__xludf.DUMMYFUNCTION("""COMPUTED_VALUE"""),TRUE) -> TRUE | B50: =IFERROR(__xludf.DUMMYFUNCTION("""COMPUTED_VALUE"""),"Fantastic Four (1998) #586") -> Fantastic Four (1998) #586 | E50: =IFERROR(__xludf.DUMMYFUNCTION("""COMPUTED_VALUE"""),FALSE) -> FALSE | F50: =IFERROR(__xludf.DUMMYFUNCTION("""COMPUTED_VALUE"""),"Thor #359") -> Thor #359
A51: =IFERROR(__xludf.DUMMYFUNCTION("""COMPUTED_VALUE"""),TRUE) -> TRUE | B51: =IFERROR(__xludf.DUMMYFUNCTION("""COMPUTED_VALUE"""),"Fantastic Four (1998) #587") -> Fantastic Four (1998) #587 | E51: =IFERROR(__xludf.DUMMYFUNCTION("""COMPUTED_VALUE"""),FALSE) -> FALSE | F51: =IFERROR(__xludf.DUMMYFUNCTION("""COMPUTED_VALUE"""),"Thor #360") -> Thor #360
A52: =IFERROR(__xludf.DUMMYFUNCTION("""COMPUTED_VALUE"""),TRUE) -> TRUE | B52: =IFERROR(__xludf.DUMMYFUNCTION("""COMPUTED_VALUE"""),"Fantastic Four (1998) #588") -> Fantastic Four (1998) #588 | E52: =IFERROR(__xludf.DUMMYFUNCTION("""COMPUTED_VALUE"""),FALSE) -> FALSE | F52: =IFERROR(__xludf.DUMMYFUNCTION("""COMPUTED_VALUE"""),"Balder the Brave #1") -> Balder the Brave #1
A53: =IFERROR(__xludf.DUMMYFUNCTION("""COMPUTED_VALUE"""),TRUE) -> TRUE | B53: =IFERROR(__xludf.DUMMYFUNCTION("""COMPUTED_VALUE"""),"FF (2011) #1") -> FF (2011) #1 | E53: =IFERROR(__xludf.DUMMYFUNCTION("""COMPUTED_VALUE"""),FALSE) -> FALSE | F53: =IFERROR(__xludf.DUMMYFUNCTION("""COMPUTED_VALUE"""),"Thor #361") -> Thor #361
A54: =IFERROR(__xludf.DUMMYFUNCTION("""COMPUTED_VALUE"""),TRUE) -> TRUE | B54: =IFERROR(__xludf.DUMMYFUNCTION("""COMPUTED_VALUE"""),"FF (2011) #2") -> FF (2011) #2 | E54: =IFERROR(__xludf.DUMMYFUNCTION("""COMPUTED_VALUE"""),FALSE) -> FALSE | F54: =IFERROR(__xludf.DUMMYFUNCTION("""COMPUTED_VALUE"""),"Thor #362") -> Thor #362
A55: =IFERROR(__xludf.DUMMYFUNCTION("""COMPUTED_VALUE"""),TRUE) -> TRUE | B55: =IFERROR(__xludf.DUMMYFUNCTION("""COMPUTED_VALUE"""),"FF (2011) #3") -> FF (2011) #3 | E55: =IFERROR(__xludf.DUMMYFUNCTION("""COMPUTED_VALUE"""),FALSE) -> FALSE | F55: =IFERROR(__xludf.DUMMYFUNCTION("""COMPUTED_VALUE"""),"Balder the Brave #2") -> Balder the Brave #2
A56: =IFERROR(__xludf.DUMMYFUNCTION("""COMPUTED_VALUE"""),FALSE) -> FALSE | B56: =IFERROR(__xludf.DUMMYFUNCTION("""COMPUTED_VALUE"""),"FF (2011) #4") -> FF (2011) #4 | E56: =IFERROR(__xludf.DUMMYFUNCTION("""COMPUTED_VALUE"""),FALSE) -> FALSE | F56: =IFERROR(__xludf.DUMMYFUNCTION("""COMPUTED_VALUE"""),"Balder the Brave #3") -> Balder the Brave #3
A57: =IFERROR(__xludf.DUMMYFUNCTION("""COMPUTED_VALUE"""),FALSE) -> FALSE | B57: =IFERROR(__xludf.DUMMYFUNCTION("""COMPUTED_VALUE"""),"FF (2011) #5") -> FF (2011) #5 | E57: =IFERROR(__xludf.DUMMYFUNCTION("""COMPUTED_VALUE"""),FALSE) -> FALSE | F57: =IFERROR(__xludf.DUMMYFUNCTION("""COMPUTED_VALUE"""),"Balder the Brave #4") -> Balder the Brave #4
A58: =IFERROR(__xludf.DUMMYFUNCTION("""COMPUTED_VALUE"""),FALSE) -> FALSE | B58: =IFERROR(__xludf.DUMMYFUNCTION("""COMPUTED_VALUE"""),"FF (2011) #6") -> FF (2011) #6 | E58: =IFERROR(__xludf.DUMMYFUNCTION("""COMPUTED_VALUE"""),FALSE) -> FALSE | F58: =IFERROR(__xludf.DUMMYFUNCTION("""COMPUTED_VALUE"""),"Thor #363") -> Thor #363
A59: =IFERROR(__xludf.DUMMYFUNCTION("""COMPUTED_VALUE"""),FALSE) -> FALSE | B59: =IFERROR(__xludf.DUMMYFUNCTION("""COMPUTED_VALUE"""),"FF (2011) #7") -> FF (2011) #7 | E59: =IFERROR(__xludf.DUMMYFUNCTION("""COMPUTED_VALUE"""),FALSE) -> FALSE | F59: =IFERROR(__xludf.DUMMYFUNCTION("""COMPUTED_VALUE"""),"Thor #364") -> Thor #364
A60: =IFERROR(__xludf.DUMMYFUNCTION("""COMPUTED_VALUE"""),FALSE) -> FALSE | B60: =IFERROR(__xludf.DUMMYFUNCTION("""COMPUTED_VALUE"""),"FF (2011) #8") -> FF (2011) #8 | E60: =IFERROR(__xludf.DUMMYFUNCTION("""COMPUTED_VALUE"""),FALSE) -> FALSE | F60: =IFERROR(__xludf.DUMMYFUNCTION("""COMPUTED_VALUE"""),"Thor #365") -> Thor #365
A61: =IFERROR(__xludf.DUMMYFUNCTION("""COMPUTED_VALUE"""),FALSE) -> FALSE | B61: =IFERROR(__xludf.DUMMYFUNCTION("""COMPUTED_VALUE"""),"FF (2011) #9") -> FF (2011) #9 | E61: =IFERROR(__xludf.DUMMYFUNCTION("""COMPUTED_VALUE"""),FALSE) -> FALSE | F61: =IFERROR(__xludf.DUMMYFUNCTION("""COMPUTED_VALUE"""),"Thor #366") -> Thor #366
A62: =IFERROR(__xludf.DUMMYFUNCTION("""COMPUTED_VALUE"""),FALSE) -> FALSE | B62: =IFERROR(__xludf.DUMMYFUNCTION("""COMPUTED_VALUE"""),"FF (2011) #10") -> FF (2011) #10 | E62: =IFERROR(__xludf.DUMMYFUNCTION("""COMPUTED_VALUE"""),FALSE) -> FALSE | F62: =IFERROR(__xludf.DUMMYFUNCTION("""COMPUTED_VALUE"""),"Thor #367") -> Thor #367
A63: =IFERROR(__xludf.DUMMYFUNCTION("""COMPUTED_VALUE"""),FALSE) -> FALSE | B63: =IFERROR(__xludf.DUMMYFUNCTION("""COMPUTED_VALUE"""),"FF (2011) #11") -> FF (2011) #11 | E63: =IFERROR(__xludf.DUMMYFUNCTION("""COMPUTED_VALUE"""),FALSE) -> FALSE | F63: =IFERROR(__xludf.DUMMYFUNCTION("""COMPUTED_VALUE"""),"Thor #368") -> Thor #368
A64: =IFERROR(__xludf.DUMMYFUNCTION("""COMPUTED_VALUE"""),FALSE) -> FALSE | B64: =IFERROR(__xludf.DUMMYFUNCTION("""COMPUTED_VALUE"""),"Fantastic Four (2012) #600") -> Fantastic Four (2012) #600 | E64: =IFERROR(__xludf.DUMMYFUNCTION("""COMPUTED_VALUE"""),FALSE) -> FALSE | F64: =IFERROR(__xludf.DUMMYFUNCTION("""COMPUTED_VALUE"""),"Thor #369") -> Thor #369
A65: =IFERROR(__xludf.DUMMYFUNCTION("""COMPUTED_VALUE"""),FALSE) -> FALSE | B65: =IFERROR(__xludf.DUMMYFUNCTION("""COMPUTED_VALUE"""),"FF (2011) #12") -> FF (2011) #12 | E65: =IFERROR(__xludf.DUMMYFUNCTION("""COMPUTED_VALUE"""),FALSE) -> FALSE | F65: =IFERROR(__xludf.DUMMYFUNCTION("""COMPUTED_VALUE"""),"Thor #370") -> Thor #370
A66: =IFERROR(__xludf.DUMMYFUNCTION("""COMPUTED_VALUE"""),FALSE) -> FALSE | B66: =IFERROR(__xludf.DUMMYFUNCTION("""COMPUTED_VALUE"""),"Fantastic Four (2012) #601") -> Fantastic Four (2012) #601 | E66: =IFERROR(__xludf.DUMMYFUNCTION("""COMPUTED_VALUE"""),FALSE) -> FALSE | F66: =IFERROR(__xludf.DUMMYFUNCTION("""COMPUTED_VALUE"""),"Thor #371") -> Thor #371
A67: =IFERROR(__xludf.DUMMYFUNCTION("""COMPUTED_VALUE"""),FALSE) -> FALSE | B67: =IFERROR(__xludf.DUMMYFUNCTION("""COMPUTED_VALUE"""),"FF (2011) #13") -> FF (2011) #13 | E67: =IFERROR(__xludf.DUMMYFUNCTION("""COMPUTED_VALUE"""),FALSE) -> FALSE | F67: =IFERROR(__xludf.DUMMYFUNCTION("""COMPUTED_VALUE"""),"Thor #372") -> Thor #372
A68: =IFERROR(__xludf.DUMMYFUNCTION("""COMPUTED_VALUE"""),FALSE) -> FALSE | B68: =IFERROR(__xludf.DUMMYFUNCTION("""COMPUTED_VALUE"""),"Fantastic Four (2012) #602") -> Fantastic Four (2012) #602 | E68: =IFERROR(__xludf.DUMMYFUNCTION("""COMPUTED_VALUE"""),FALSE) -> FALSE | F68: =IFERROR(__xludf.DUMMYFUNCTION("""COMPUTED_VALUE"""),"Thor #373") -> Thor #373
A69: =IFERROR(__xludf.DUMMYFUNCTION("""COMPUTED_VALUE"""),FALSE) -> FALSE | B69: =IFERROR(__xludf.DUMMYFUNCTION("""COMPUTED_VALUE"""),"FF (2011) #14") -> FF (2011) #14 | E69: =IFERROR(__xludf.DUMMYFUNCTION("""COMPUTED_VALUE"""),FALSE) -> FALSE | F69: =IFERROR(__xludf.DUMMYFUNCTION("""COMPUTED_VALUE"""),"Thor #374") -> Thor #374
A70: =IFERROR(__xludf.DUMMYFUNCTION("""COMPUTED_VALUE"""),FALSE) -> FALSE | B70: =IFERROR(__xludf.DUMMYFUNCTION("""COMPUTED_VALUE"""),"Fantastic Four (2012) #603") -> Fantastic Four (2012) #603 | E70: =IFERROR(__xludf.DUMMYFUNCTION("""COMPUTED_VALUE"""),FALSE) -> FALSE | F70: =IFERROR(__xludf.DUMMYFUNCTION("""COMPUTED_VALUE"""),"Thor #375") -> Thor #375
A71: =IFERROR(__xludf.DUMMYFUNCTION("""COMPUTED_VALUE"""),FALSE) -> FALSE | B71: =IFERROR(__xludf.DUMMYFUNCTION("""COMPUTED_VALUE"""),"FF (2011) #15") -> FF (2011) #15 | E71: =IFERROR(__xludf.DUMMYFUNCTION("""COMPUTED_VALUE"""),FALSE) -> FALSE | F71: =IFERROR(__xludf.DUMMYFUNCTION("""COMPUTED_VALUE"""),"Thor #376") -> Thor #376
A72: =IFERROR(__xludf.DUMMYFUNCTION("""COMPUTED_VALUE"""),FALSE) -> FALSE | B72: =IFERROR(__xludf.DUMMYFUNCTION("""COMPUTED_VALUE"""),"Fantastic Four (2012) #604") -> Fantastic Four (2012) #604 | E72: =IFERROR(__xludf.DUMMYFUNCTION("""COMPUTED_VALUE"""),FALSE) -> FALSE | F72: =IFERROR(__xludf.DUMMYFUNCTION("""COMPUTED_VALUE"""),"Thor #377") -> Thor #377
A73: =IFERROR(__xludf.DUMMYFUNCTION("""COMPUTED_VALUE"""),FALSE) -> FALSE | B73: =IFERROR(__xludf.DUMMYFUNCTION("""COMPUTED_VALUE"""),"FF (2011) #16") -> FF (2011) #16 | E73: =IFERROR(__xludf.DUMMYFUNCTION("""COMPUTED_VALUE"""),FALSE) -> FALSE | F73: =IFERROR(__xludf.DUMMYFUNCTION("""COMPUTED_VALUE"""),"Thor #378") -> Thor #378
A74: =IFERROR(__xludf.DUMMYFUNCTION("""COMPUTED_VALUE"""),FALSE) -> FALSE | B74: =IFERROR(__xludf.DUMMYFUNCTION("""COMPUTED_VALUE"""),"Fantastic Four (2012) #605") -> Fantastic Four (2012) #605 | E74: =IFERROR(__xludf.DUMMYFUNCTION("""COMPUTED_VALUE"""),FALSE) -> FALSE | F74: =IFERROR(__xludf.DUMMYFUNCTION("""COMPUTED_VALUE"""),"Thor #379") -> Thor #379
A75: =IFERROR(__xludf.DUMMYFUNCTION("""COMPUTED_VALUE"""),FALSE) -> FALSE | B75: =IFERROR(__xludf.DUMMYFUNCTION("""COMPUTED_VALUE"""),"Fantastic Four (2012) #605.1") -> Fantastic Four (2012) #605.1 | E75: =IFERROR(__xludf.DUMMYFUNCTION("""COMPUTED_VALUE"""),FALSE) -> FALSE | F75: =IFERROR(__xludf.DUMMYFUNCTION("""COMPUTED_VALUE"""),"Thor #380") -> Thor #380
A76: =IFERROR(__xludf.DUMMYFUNCTION("""COMPUTED_VALUE"""),FALSE) -> FALSE | B76: =IFERROR(__xludf.DUMMYFUNCTION("""COMPUTED_VALUE"""),"Fantastic Four (2012) #606") -> Fantastic Four (2012) #606 | E76: =IFERROR(__xludf.DUMMYFUNCTION("""COMPUTED_VALUE"""),FALSE) -> FALSE | F76: =IFERROR(__xludf.DUMMYFUNCTION("""COMPUTED_VALUE"""),"Thor #381") -> Thor #381
A77: =IFERROR(__xludf.DUMMYFUNCTION("""COMPUTED_VALUE"""),FALSE) -> FALSE | B77: =IFERROR(__xludf.DUMMYFUNCTION("""COMPUTED_VALUE"""),"FF (2011) #17") -> FF (2011) #17 | E77: =IFERROR(__xludf.DUMMYFUNCTION("""COMPUTED_VALUE"""),FALSE) -> FALSE | F77: =IFERROR(__xludf.DUMMYFUNCTION("""COMPUTED_VALUE"""),"Thor #382") -> Thor #382
A78: =IFERROR(__xludf.DUMMYFUNCTION("""COMPUTED_VALUE"""),FALSE) -> FALSE | B78: =IFERROR(__xludf.DUMMYFUNCTION("""COMPUTED_VALUE"""),"FF (2011) #18") -> FF (2011) #18
A79: =IFERROR(__xludf.DUMMYFUNCTION("""COMPUTED_VALUE"""),FALSE) -> FALSE | B79: =IFERROR(__xludf.DUMMYFUNCTION("""COMPUTED_VALUE"""),"Fantastic Four (2012) #607") -> Fantastic Four (2012) #607
A80: =IFERROR(__xludf.DUMMYFUNCTION("""COMPUTED_VALUE"""),FALSE) -> FALSE | B80: =IFERROR(__xludf.DUMMYFUNCTION("""COMPUTED_VALUE"""),"Fantastic Four (2012) #608") -> Fantastic Four (2012) #608
A81: =IFERROR(__xludf.DUMMYFUNCTION("""COMPUTED_VALUE"""),FALSE) -> FALSE | B81: =IFERROR(__xludf.DUMMYFUNCTION("""COMPUTED_VALUE"""),"FF (2011) #19") -> FF (2011) #19
A82: =IFERROR(__xludf.DUMMYFUNCTION("""COMPUTED_VALUE"""),FALSE) -> FALSE | B82: =IFERROR(__xludf.DUMMYFUNCTION("""COMPUTED_VALUE"""),"FF (2011) #20") -> FF (2011) #20
A83: =IFERROR(__xludf.DUMMYFUNCTION("""COMPUTED_VALUE"""),FALSE) -> FALSE | B83: =IFERROR(__xludf.DUMMYFUNCTION("""COMPUTED_VALUE"""),"FF (2011) #21") -> FF (2011) #21
A84: =IFERROR(__xludf.DUMMYFUNCTION("""COMPUTED_VALUE"""),FALSE) -> FALSE | B84: =IFERROR(__xludf.DUMMYFUNCTION("""COMPUTED_VALUE"""),"Fantastic Four (2012) #609") -> Fantastic Four (2012) #609
A85: =IFERROR(__xludf.DUMMYFUNCTION("""COMPUTED_VALUE"""),FALSE) -> FALSE | B85: =IFERROR(__xludf.DUMMYFUNCTION("""COMPUTED_VALUE"""),"Fantastic Four (2012) #610") -> Fantastic Four (2012) #610
A86: =IFERROR(__xludf.DUMMYFUNCTION("""COMPUTED_VALUE"""),FALSE) -> FALSE | B86: =IFERROR(__xludf.DUMMYFUNCTION("""COMPUTED_VALUE"""),"FF (2011) #22") -> FF (2011) #22
A87: =IFERROR(__xludf.DUMMYFUNCTION("""COMPUTED_VALUE"""),FALSE) -> FALSE | B87: =IFERROR(__xludf.DUMMYFUNCTION("""COMPUTED_VALUE"""),"Fantastic Four (2012) #611") -> Fantastic Four (2012) #611
A88: =IFERROR(__xludf.DUMMYFUNCTION("""COMPUTED_VALUE"""),FALSE) -> FALSE | B88: =IFERROR(__xludf.DUMMYFUNCTION("""COMPUTED_VALUE"""),"FF (2011) #23") -> FF (2011) #23

Sheet RUNS
A1: Title | B1: Run ID | C1: Track | D1: Writer | E1: Artists | F1: Series (and Issues) | G1: Issue Count | H1: Start Year | I1: End Year | J1: In Sheet | K1: Status | L1: Tier | M1: Why | N1: Notes | O1: Block | P1: Sequence | Q1: Spine | R1: Rating | S1: Readiness | T1: Hard Prereqs | U1: Hard Read | V1: Hard Left | W1: Soft Prereqs | X1: Soft Read | Y1: Soft Left | Z1: Unlocks | AA1: Completed | AB1: Left | AC1: % Done | AD1: Standalone
A2: Avengers Origin | B2: avengers-origin | C2: Avengers | D2: Stan Lee | F2: Avengers #1, 4, 16 | G2: =COUNTIF(Reading_Order[Run ID], B2) -> 3 | H2: 1963 | I2: 1965 | J2: =$G2>0 -> TRUE | K2: =IF($G2=0,"—",IF($AA2=$G2,"read",IF($AA2>0,"reading","unread"))) -> unread | L2: 4 | M2: Formation and the Kooky Quartet roster | O2: 1 | P2: 1 | Q2: FALSE | S2: =IF($V2>0, "blocked", IF($Y2=0, "ready-all", "ready-hard")) -> ready-all | T2: =COUNTIFS(Prerequisites[Run ID], $B2, Prerequisites[Type], "hard") -> 0 | U2: =COUNTIFS(Prerequisites[Run ID], $B2, Prerequisites[Type], "hard", Prerequisites[Satisfied], TRUE) -> 0 | V2: =T2-U2 -> 0 | W2: =COUNTIFS(Prerequisites[Run ID], $B2, Prerequisites[Type], "soft") -> 0 | X2: =COUNTIFS(Prerequisites[Run ID], $B2, Prerequisites[Type], "soft", Prerequisites[Satisfied], TRUE) -> 0 | Y2: =W2-X2 -> 0 | Z2: =COUNTIFS(Prerequisites[Prereq Run ID],$B2,Prerequisites[Type], "hard") -> 1 | AA2: =COUNTIFS(Reading_Order[Run ID], $B2, Reading_Order[Completed], TRUE) -> 0 | AB2: =$G2-$AA2 -> 3 | AC2: =AA2/(AB2+AA2) -> 0 | AD2: =IF(T2<1, TRUE, FALSE) -> TRUE
A3: The Kree-Skrull War | B3: kree-skrull-war | C3: Avengers | D3: Roy Thomas | E3: Neal Adams | F3: Avengers #89-97 | G3: =COUNTIF(Reading_Order[Run ID], B3) -> 9 | H3: 1971 | I3: 1972 | J3: =$G3>0 -> TRUE | K3: =IF($G3=0,"—",IF($AA3=$G3,"read",IF($AA3>0,"reading","unread"))) -> unread | L3: 2 | M3: The first Marvel event, and still readable | O3: 1 | P3: 2 | Q3: FALSE | S3: =IF($V3>0, "blocked", IF($Y3=0, "ready-all", "ready-hard")) -> blocked | T3: =COUNTIFS(Prerequisites[Run ID], $B3, Prerequisites[Type], "hard") -> 1 | U3: =COUNTIFS(Prerequisites[Run ID], $B3, Prerequisites[Type], "hard", Prerequisites[Satisfied], TRUE) -> 0 | V3: =T3-U3 -> 1 | W3: =COUNTIFS(Prerequisites[Run ID], $B3, Prerequisites[Type], "soft") -> 0 | X3: =COUNTIFS(Prerequisites[Run ID], $B3, Prerequisites[Type], "soft", Prerequisites[Satisfied], TRUE) -> 0 | Y3: =W3-X3 -> 0 | Z3: =COUNTIFS(Prerequisites[Prereq Run ID],$B3,Prerequisites[Type], "hard") -> 1 | AA3: =COUNTIFS(Reading_Order[Run ID], $B3, Reading_Order[Completed], TRUE) -> 0 | AB3: =$G3-$AA3 -> 9 | AC3: =AA3/(AB3+AA3) -> 0 | AD3: =IF(T3<1, TRUE, FALSE) -> FALSE
A4: Stern's Avengers | B4: stern-avengers | C4: Avengers | D4: Roger Stern | E4: John Buscema | F4: Avengers #227-285 | G4: =COUNTIF(Reading_Order[Run ID], B4) -> 131 | H4: 1983 | I4: 1987 | J4: =$G4>0 -> TRUE | K4: =IF($G4=0,"—",IF($AA4=$G4,"read",IF($AA4>0,"reading","unread"))) -> unread | L4: 4 | M4: Under Siege, and the best Monica Rambeau material anywhere | O4: 1 | P4: 3 | Q4: FALSE | S4: =IF($V4>0, "blocked", IF($Y4=0, "ready-all", "ready-hard")) -> blocked | T4: =COUNTIFS(Prerequisites[Run ID], $B4, Prerequisites[Type], "hard") -> 1 | U4: =COUNTIFS(Prerequisites[Run ID], $B4, Prerequisites[Type], "hard", Prerequisites[Satisfied], TRUE) -> 0 | V4: =T4-U4 -> 1 | W4: =COUNTIFS(Prerequisites[Run ID], $B4, Prerequisites[Type], "soft") -> 3 | X4: =COUNTIFS(Prerequisites[Run ID], $B4, Prerequisites[Type], "soft", Prerequisites[Satisfied], TRUE) -> 0 | Y4: =W4-X4 -> 3 | Z4: =COUNTIFS(Prerequisites[Prereq Run ID],$B4,Prerequisites[Type], "hard") -> 0 | AA4: =COUNTIFS(Reading_Order[Run ID], $B4, Reading_Order[Completed], TRUE) -> 0 | AB4: =$G4-$AA4 -> 131 | AC4: =AA4/(AB4+AA4) -> 0 | AD4: =IF(T4<1, TRUE, FALSE) -> FALSE
A5: Busiek's Avengers + Thunderbolts | B5: busiek-avengers | C5: Avengers | D5: Kurt Busiek | E5: George Perez | F5: Thunderbolts (1997) #0-44; Avengers (1998) #0-56; Iron Man (1998) #7; Captain America (1998) #8; Quicksilver (1997) #10; Avengers: Forever (1998) #1-12; Avengers Annual (1999); Avengers Annual (2000); Maximum Security #1-3; Avengers: The Ultron Imperative; Avengers Annual (2001) | G5: =COUNTIF(Reading_Order[Run ID], B5) -> 154 | H5: 1997 | I5: 2002 | J5: =$G5>0 -> TRUE | K5: =IF($G5=0,"—",IF($AA5=$G5,"read",IF($AA5>0,"reading","unread"))) -> unread | L5: 2 | M5: The best 'how the Marvel Universe works' run ever written | O5: 2 | P5: 1 | Q5: TRUE | S5: =IF($V5>0, "blocked", IF($Y5=0, "ready-all", "ready-hard")) -> ready-hard | T5: =COUNTIFS(Prerequisites[Run ID], $B5, Prerequisites[Type], "hard") -> 0 | U5: =COUNTIFS(Prerequisites[Run ID], $B5, Prerequisites[Type], "hard", Prerequisites[Satisfied], TRUE) -> 0 | V5: =T5-U5 -> 0 | W5: =COUNTIFS(Prerequisites[Run ID], $B5, Prerequisites[Type], "soft") -> 4 | X5: =COUNTIFS(Prerequisites[Run ID], $B5, Prerequisites[Type], "soft", Prerequisites[Satisfied], TRUE) -> 0 | Y5: =W5-X5 -> 4 | Z5: =COUNTIFS(Prerequisites[Prereq Run ID],$B5,Prerequisites[Type], "hard") -> 1 | AA5: =COUNTIFS(Reading_Order[Run ID], $B5, Reading_Order[Completed], TRUE) -> 0 | AB5: =$G5-$AA5 -> 154 | AC5: =AA5/(AB5+AA5) -> 0 | AD5: =IF(T5<1, TRUE, FALSE) -> TRUE
A6: Avengers: Disassembled | B6: bendis-disassembled | C6: Avengers | D6: Brian Michael Bendis | F6: Avengers (1999) #500-503; Avengers Finale | G6: =COUNTIF(Reading_Order[Run ID], B6) -> 5 | H6: 2004 | I6: 2005 | J6: =$G6>0 -> TRUE | K6: =IF($G6=0,"—",IF($AA6=$G6,"read",IF($AA6>0,"reading","unread"))) -> unread | L6: 2 | M6: The break that starts the modern era | O6: 2 | P6: 2 | Q6: TRUE | S6: =IF($V6>0, "blocked", IF($Y6=0, "ready-all", "ready-hard")) -> blocked | T6: =COUNTIFS(Prerequisites[Run ID], $B6, Prerequisites[Type], "hard") -> 1 | U6: =COUNTIFS(Prerequisites[Run ID], $B6, Prerequisites[Type], "hard", Prerequisites[Satisfied], TRUE) -> 0 | V6: =T6-U6 -> 1 | W6: =COUNTIFS(Prerequisites[Run ID], $B6, Prerequisites[Type], "soft") -> 2 | X6: =COUNTIFS(Prerequisites[Run ID], $B6, Prerequisites[Type], "soft", Prerequisites[Satisfied], TRUE) -> 0 | Y6: =W6-X6 -> 2 | Z6: =COUNTIFS(Prerequisites[Prereq Run ID],$B6,Prerequisites[Type], "hard") -> 4 | AA6: =COUNTIFS(Reading_Order[Run ID], $B6, Reading_Order[Completed], TRUE) -> 0 | AB6: =$G6-$AA6 -> 5 | AC6: =AA6/(AB6+AA6) -> 0 | AD6: =IF(T6<1, TRUE, FALSE) -> FALSE
A7: New Avengers Breakout | B7: bendis-breakout | C7: Avengers | D7: Brian Michael Bendis | F7: The Pulse #1-9; Secret War #1-5; New Avengers #1-10; Young Avengers #1-8; The Sentry #1-5; The Sentry/Fantastic Four; The Sentry/X-Men; The Sentry/Spider-Man; The Sentry/Hulk; The Sentry vs. The Void | G7: =COUNTIF(Reading_Order[Run ID], B7) -> 48 | H7: 2004 | I7: 2005 | J7: =$G7>0 -> TRUE | K7: =IF($G7=0,"—",IF($AA7=$G7,"read",IF($AA7>0,"reading","unread"))) -> unread | L7: 2 | M7: The New Avengers launch; the status quo for a decade | O7: 2 | P7: 3 | Q7: TRUE | S7: =IF($V7>0, "blocked", IF($Y7=0, "ready-all", "ready-hard")) -> blocked | T7: =COUNTIFS(Prerequisites[Run ID], $B7, Prerequisites[Type], "hard") -> 1 | U7: =COUNTIFS(Prerequisites[Run ID], $B7, Prerequisites[Type], "hard", Prerequisites[Satisfied], TRUE) -> 0 | V7: =T7-U7 -> 1 | W7: =COUNTIFS(Prerequisites[Run ID], $B7, Prerequisites[Type], "soft") -> 1 | X7: =COUNTIFS(Prerequisites[Run ID], $B7, Prerequisites[Type], "soft", Prerequisites[Satisfied], TRUE) -> 0 | Y7: =W7-X7 -> 1 | Z7: =COUNTIFS(Prerequisites[Prereq Run ID],$B7,Prerequisites[Type], "hard") -> 2 | AA7: =COUNTIFS(Reading_Order[Run ID], $B7, Reading_Order[Completed], TRUE) -> 0 | AB7: =$G7-$AA7 -> 48 | AC7: =AA7/(AB7+AA7) -> 0 | AD7: =IF(T7<1, TRUE, FALSE) -> FALSE
A8: House of M | B8: bendis-house-of-m | C8: Avengers | D8: Brian Michael Bendis | F8: Young Avengers Special #1; Excalibur (2004) #8-14; House of M #1-8; Wolverine #33-35; The Pulse #10; Decimation: House of M – The Day After | G8: =COUNTIF(Reading_Order[Run ID], B8) -> 42 | H8: 2005 | I8: 2006 | J8: =$G8>0 -> TRUE | K8: =IF($G8=0,"—",IF($AA8=$G8,"read",IF($AA8>0,"reading","unread"))) -> unread | L8: 2 | M8: Hard prereq for Decimation, AvX and the whole X-Men bridge | O8: 2 | P8: 4 | Q8: TRUE | S8: =IF($V8>0, "blocked", IF($Y8=0, "ready-all", "ready-hard")) -> blocked | T8: =COUNTIFS(Prerequisites[Run ID], $B8, Prerequisites[Type], "hard") -> 2 | U8: =COUNTIFS(Prerequisites[Run ID], $B8, Prerequisites[Type], "hard", Prerequisites[Satisfied], TRUE) -> 0 | V8: =T8-U8 -> 2 | W8: =COUNTIFS(Prerequisites[Run ID], $B8, Prerequisites[Type], "soft") -> 2 | X8: =COUNTIFS(Prerequisites[Run ID], $B8, Prerequisites[Type], "soft", Prerequisites[Satisfied], TRUE) -> 0 | Y8: =W8-X8 -> 2 | Z8: =COUNTIFS(Prerequisites[Prereq Run ID],$B8,Prerequisites[Type], "hard") -> 4 | AA8: =COUNTIFS(Reading_Order[Run ID], $B8, Reading_Order[Completed], TRUE) -> 0 | AB8: =$G8-$AA8 -> 42 | AC8: =AA8/(AB8+AA8) -> 0 | AD8: =IF(T8<1, TRUE, FALSE) -> FALSE
A9: Civil War | B9: bendis-civil-war | C9: Avengers | D9: Brian Michael Bendis | F9: New Avengers #11-25; New Avengers Annual #1; New Avengers: Illuminati (2006 one-shot); Spider-Woman: Origin #1-5; The Pulse #11-14; Young Avengers #9-12; Civil War: Young Avengers & Runaways #1-4; Fantastic Four (1998) #536-543; Amazing Spider-Man (1999) #529-538; Civil War #1-7; Civil War: Casualties of War; Civil War: Front Line #1-11; Sensational Spider-Man Annual #1; Captain America (2004) #25; Civil War: The Confession; Civil War: The Initiative; Fallen Son #1-5 | G9: =COUNTIF(Reading_Order[Run ID], B9) -> 60 | H9: 2005 | I9: 2007 | J9: =$G9>0 -> TRUE | K9: =IF($G9=0,"—",IF($AA9=$G9,"read",IF($AA9>0,"reading","unread"))) -> unread | L9: 3 | M9: The line-wide fracture everything after refers back to | O9: 3 | P9: 1 | Q9: FALSE | S9: =IF($V9>0, "blocked", IF($Y9=0, "ready-all", "ready-hard")) -> blocked | T9: =COUNTIFS(Prerequisites[Run ID], $B9, Prerequisites[Type], "hard") -> 1 | U9: =COUNTIFS(Prerequisites[Run ID], $B9, Prerequisites[Type], "hard", Prerequisites[Satisfied], TRUE) -> 0 | V9: =T9-U9 -> 1 | W9: =COUNTIFS(Prerequisites[Run ID], $B9, Prerequisites[Type], "soft") -> 3 | X9: =COUNTIFS(Prerequisites[Run ID], $B9, Prerequisites[Type], "soft", Prerequisites[Satisfied], TRUE) -> 0 | Y9: =W9-X9 -> 3 | Z9: =COUNTIFS(Prerequisites[Prereq Run ID],$B9,Prerequisites[Type], "hard") -> 1 | AA9: =COUNTIFS(Reading_Order[Run ID], $B9, Reading_Order[Completed], TRUE) -> 0 | AB9: =$G9-$AA9 -> 60 | AC9: =AA9/(AB9+AA9) -> 0 | AD9: =IF(T9<1, TRUE, FALSE) -> FALSE
A10: Heinberg's Young Avengers | B10: heinberg-young-avengers | C10: Young Avengers | D10: Allan Heinberg | G10: =COUNTIF(Reading_Order[Run ID], B10) -> 18 | J10: =$G10>0 -> TRUE | K10: =IF($G10=0,"—",IF($AA10=$G10,"read",IF($AA10>0,"reading","unread"))) -> unread | L10: 3 | O10: 1 | P10: 1 | Q10: TRUE | S10: =IF($V10>0, "blocked", IF($Y10=0, "ready-all", "ready-hard")) -> ready-all | T10: =COUNTIFS(Prerequisites[Run ID], $B10, Prerequisites[Type], "hard") -> 0 | U10: =COUNTIFS(Prerequisites[Run ID], $B10, Prerequisites[Type], "hard", Prerequisites[Satisfied], TRUE) -> 0 | V10: =T10-U10 -> 0 | W10: =COUNTIFS(Prerequisites[Run ID], $B10, Prerequisites[Type], "soft") -> 0 | X10: =COUNTIFS(Prerequisites[Run ID], $B10, Prerequisites[Type], "soft", Prerequisites[Satisfied], TRUE) -> 0 | Y10: =W10-X10 -> 0 | Z10: =COUNTIFS(Prerequisites[Prereq Run ID],$B10,Prerequisites[Type], "hard") -> 1 | AA10: =COUNTIFS(Reading_Order[Run ID], $B10, Reading_Order[Completed], TRUE) -> 0 | AB10: =$G10-$AA10 -> 18 | AC10: =AA10/(AB10+AA10) -> 0 | AD10: =IF(T10<1, TRUE, FALSE) -> TRUE
A11: childrens-crusade | B11: childrens-crusade | C11: Young Avengers | D11: Allan Heinberg | G11: =COUNTIF(Reading_Order[Run ID], B11) -> 11 | J11: =$G11>0 -> TRUE | K11: =IF($G11=0,"—",IF($AA11=$G11,"read",IF($AA11>0,"reading","unread"))) -> unread | O11: 1 | P11: 2 | Q11: FALSE | S11: =IF($V11>0, "blocked", IF($Y11=0, "ready-all", "ready-hard")) -> blocked | T11: =COUNTIFS(Prerequisites[Run ID], $B11, Prerequisites[Type], "hard") -> 3 | U11: =COUNTIFS(Prerequisites[Run ID], $B11, Prerequisites[Type], "hard", Prerequisites[Satisfied], TRUE) -> 0 | V11: =T11-U11 -> 3 | W11: =COUNTIFS(Prerequisites[Run ID], $B11, Prerequisites[Type], "soft") -> 1 | X11: =COUNTIFS(Prerequisites[Run ID], $B11, Prerequisites[Type], "soft", Prerequisites[Satisfied], TRUE) -> 0 | Y11: =W11-X11 -> 1 | Z11: =COUNTIFS(Prerequisites[Prereq Run ID],$B11,Prerequisites[Type], "hard") -> 2 | AA11: =COUNTIFS(Reading_Order[Run ID], $B11, Reading_Order[Completed], TRUE) -> 0 | AB11: =$G11-$AA11 -> 11 | AC11: =AA11/(AB11+AA11) -> 0 | AD11: =IF(T11<1, TRUE, FALSE) -> FALSE
A12: Gillen's Loki | B12: gillen-loki | C12: Young Avengers | D12: Kieron Gillen | G12: =COUNTIF(Reading_Order[Run ID], B12) -> 32 | J12: =$G12>0 -> TRUE | K12: =IF($G12=0,"—",IF($AA12=$G12,"read",IF($AA12>0,"reading","unread"))) -> unread | O12: 1 | P12: 3 | Q12: FALSE | S12: =IF($V12>0, "blocked", IF($Y12=0, "ready-all", "ready-hard")) -> blocked | T12: =COUNTIFS(Prerequisites[Run ID], $B12, Prerequisites[Type], "hard") -> 2 | U12: =COUNTIFS(Prerequisites[Run ID], $B12, Prerequisites[Type], "hard", Prerequisites[Satisfied], TRUE) -> 0 | V12: =T12-U12 -> 2 | W12: =COUNTIFS(Prerequisites[Run ID], $B12, Prerequisites[Type], "soft") -> 1 | X12: =COUNTIFS(Prerequisites[Run ID], $B12, Prerequisites[Type], "soft", Prerequisites[Satisfied], TRUE) -> 0 | Y12: =W12-X12 -> 1 | Z12: =COUNTIFS(Prerequisites[Prereq Run ID],$B12,Prerequisites[Type], "hard") -> 1 | AA12: =COUNTIFS(Reading_Order[Run ID], $B12, Reading_Order[Completed], TRUE) -> 0 | AB12: =$G12-$AA12 -> 32 | AC12: =AA12/(AB12+AA12) -> 0 | AD12: =IF(T12<1, TRUE, FALSE) -> FALSE
A13: Gillen's Young Avengers | B13: gillen-young-avengers | C13: Young Avengers | D13: Kieron Gillen | F13: Young Avengers (2005) #1-12; Young Avengers (2013) #1-15; Uncanny X-Men (1981) #526; Avengers: The Children's Crusade #1-9; Avengers: The Children's Crusade - Young Avengers #1; Journey into Mystery (2011) #622-645; Exiled #1; New Mutants (2009) #42-43; The Mighty Thor (2011) #18-21; Marvel NOW! Point One #1 | G13: =COUNTIF(Reading_Order[Run ID], B13) -> 22 | H13: 2005 | I13: 2014 | J13: =$G13>0 -> TRUE | K13: =IF($G13=0,"—",IF($AA13=$G13,"read",IF($AA13>0,"reading","unread"))) -> unread | L13: 3 | M13: The most stylish superhero book of its decade | O13: 1 | P13: 4 | Q13: FALSE | S13: =IF($V13>0, "blocked", IF($Y13=0, "ready-all", "ready-hard")) -> blocked | T13: =COUNTIFS(Prerequisites[Run ID], $B13, Prerequisites[Type], "hard") -> 4 | U13: =COUNTIFS(Prerequisites[Run ID], $B13, Prerequisites[Type], "hard", Prerequisites[Satisfied], TRUE) -> 0 | V13: =T13-U13 -> 4 | W13: =COUNTIFS(Prerequisites[Run ID], $B13, Prerequisites[Type], "soft") -> 1 | X13: =COUNTIFS(Prerequisites[Run ID], $B13, Prerequisites[Type], "soft", Prerequisites[Satisfied], TRUE) -> 0 | Y13: =W13-X13 -> 1 | Z13: =COUNTIFS(Prerequisites[Prereq Run ID],$B13,Prerequisites[Type], "hard") -> 1 | AA13: =COUNTIFS(Reading_Order[Run ID], $B13, Reading_Order[Completed], TRUE) -> 0 | AB13: =$G13-$AA13 -> 22 | AC13: =AA13/(AB13+AA13) -> 0 | AD13: =IF(T13<1, TRUE, FALSE) -> FALSE
A14: The Initiative | B14: bendis-initiative | C14: Avengers | D14: Brian Michael Bendis | F14: New Avengers #26-37; New Avengers Annual #2; The Mighty Avengers #1-11; Avengers: The Initiative #1-13; Avengers: The Initiative Annual #1; World War Hulk #1-5; Thunderbolts #110-121; New Avengers: Illuminati #1-5 | G14: =COUNTIF(Reading_Order[Run ID], B14) -> 70 | H14: 2007 | I14: 2008 | J14: =$G14>0 -> TRUE | K14: =IF($G14=0,"—",IF($AA14=$G14,"read",IF($AA14>0,"reading","unread"))) -> unread | L14: 3 | M14: Hard prereq via World War Hulk | O14: 3 | P14: 2 | Q14: FALSE | S14: =IF($V14>0, "blocked", IF($Y14=0, "ready-all", "ready-hard")) -> blocked | T14: =COUNTIFS(Prerequisites[Run ID], $B14, Prerequisites[Type], "hard") -> 1 | U14: =COUNTIFS(Prerequisites[Run ID], $B14, Prerequisites[Type], "hard", Prerequisites[Satisfied], TRUE) -> 0 | V14: =T14-U14 -> 1 | W14: =COUNTIFS(Prerequisites[Run ID], $B14, Prerequisites[Type], "soft") -> 1 | X14: =COUNTIFS(Prerequisites[Run ID], $B14, Prerequisites[Type], "soft", Prerequisites[Satisfied], TRUE) -> 0 | Y14: =W14-X14 -> 1 | Z14: =COUNTIFS(Prerequisites[Prereq Run ID],$B14,Prerequisites[Type], "hard") -> 1 | AA14: =COUNTIFS(Reading_Order[Run ID], $B14, Reading_Order[Completed], TRUE) -> 0 | AB14: =$G14-$AA14 -> 70 | AC14: =AA14/(AB14+AA14) -> 0 | AD14: =IF(T14<1, TRUE, FALSE) -> FALSE
A15: Secret Invasion | B15: bendis-secret-invasion | C15: Avengers | D15: Brian Michael Bendis | F15: New Avengers #38-47; The Mighty Avengers #12-19; Avengers: The Initiative #14-19; Secret Invasion Prologue; Secret Invasion #1-8; Secret Invasion: Requiem #1; Secret Invasion: Dark Reign #1; Thunderbolts #122-125 | G15: =COUNTIF(Reading_Order[Run ID], B15) -> 46 | H15: 2008 | I15: 2009 | J15: =$G15>0 -> TRUE | K15: =IF($G15=0,"—",IF($AA15=$G15,"read",IF($AA15>0,"reading","unread"))) -> unread | L15: 3 | M15: Direct prequel to Secret Warriors, which you've read | O15: 3 | P15: 3 | Q15: FALSE | S15: =IF($V15>0, "blocked", IF($Y15=0, "ready-all", "ready-hard")) -> blocked | T15: =COUNTIFS(Prerequisites[Run ID], $B15, Prerequisites[Type], "hard") -> 1 | U15: =COUNTIFS(Prerequisites[Run ID], $B15, Prerequisites[Type], "hard", Prerequisites[Satisfied], TRUE) -> 0 | V15: =T15-U15 -> 1 | W15: =COUNTIFS(Prerequisites[Run ID], $B15, Prerequisites[Type], "soft") -> 2 | X15: =COUNTIFS(Prerequisites[Run ID], $B15, Prerequisites[Type], "soft", Prerequisites[Satisfied], TRUE) -> 0 | Y15: =W15-X15 -> 2 | Z15: =COUNTIFS(Prerequisites[Prereq Run ID],$B15,Prerequisites[Type], "hard") -> 1 | AA15: =COUNTIFS(Reading_Order[Run ID], $B15, Reading_Order[Completed], TRUE) -> 0 | AB15: =$G15-$AA15 -> 46 | AC15: =AA15/(AB15+AA15) -> 0 | AD15: =IF(T15<1, TRUE, FALSE) -> FALSE
A16: Dark Reign | B16: bendis-dark-reign | C16: Avengers | D16: Brian Michael Bendis | F16: New Avengers #48-60; New Avengers Annual #3; The Mighty Avengers #20-31; Dark Avengers #1-12; Avengers: The Initiative #20-30; Avengers: The Initiative Special #1; New Avengers: The Reunion #1-4; Dark Reign: The Hood #1-5; Dark Reign: The Cabal; Free Comic Book Day 2009: Avengers; Dark Avengers/Uncanny X-Men: Utopia #1; Uncanny X-Men #513-514; Dark Avengers/Uncanny X-Men: Exodus #1 | G16: =COUNTIF(Reading_Order[Run ID], B16) -> 65 | H16: 2009 | I16: 2010 | J16: =$G16>0 -> TRUE | K16: =IF($G16=0,"—",IF($AA16=$G16,"read",IF($AA16>0,"reading","unread"))) -> unread | L16: 3 | M16: Osborn in charge; the setup for Siege | O16: 3 | P16: 4 | Q16: FALSE | S16: =IF($V16>0, "blocked", IF($Y16=0, "ready-all", "ready-hard")) -> blocked | T16: =COUNTIFS(Prerequisites[Run ID], $B16, Prerequisites[Type], "hard") -> 1 | U16: =COUNTIFS(Prerequisites[Run ID], $B16, Prerequisites[Type], "hard", Prerequisites[Satisfied], TRUE) -> 0 | V16: =T16-U16 -> 1 | W16: =COUNTIFS(Prerequisites[Run ID], $B16, Prerequisites[Type], "soft") -> 0 | X16: =COUNTIFS(Prerequisites[Run ID], $B16, Prerequisites[Type], "soft", Prerequisites[Satisfied], TRUE) -> 0 | Y16: =W16-X16 -> 0 | Z16: =COUNTIFS(Prerequisites[Prereq Run ID],$B16,Prerequisites[Type], "hard") -> 1 | AA16: =COUNTIFS(Reading_Order[Run ID], $B16, Reading_Order[Completed], TRUE) -> 0 | AB16: =$G16-$AA16 -> 65 | AC16: =AA16/(AB16+AA16) -> 0 | AD16: =IF(T16<1, TRUE, FALSE) -> FALSE
A17: Siege | B17: bendis-siege | C17: Avengers | D17: Brian Michael Bendis | F17: Dark Reign: The List – Avengers; Dark Avengers #13-16; Dark Avengers Annual #1; The Mighty Avengers #32-36; New Avengers #61-64; New Avengers Finale #1; Avengers: The Initiative #31-35; Siege: The Cabal #1; Origins of Siege #1; Siege Prologue; Siege #1-4; Siege: Embedded #1-4 | G17: =COUNTIF(Reading_Order[Run ID], B17) -> 35 | H17: 2009 | I17: 2010 | J17: =$G17>0 -> TRUE | K17: =IF($G17=0,"—",IF($AA17=$G17,"read",IF($AA17>0,"reading","unread"))) -> unread | L17: 3 | M17: Asgard falls; leads directly into Hickman | O17: 3 | P17: 5 | Q17: FALSE | S17: =IF($V17>0, "blocked", IF($Y17=0, "ready-all", "ready-hard")) -> blocked | T17: =COUNTIFS(Prerequisites[Run ID], $B17, Prerequisites[Type], "hard") -> 1 | U17: =COUNTIFS(Prerequisites[Run ID], $B17, Prerequisites[Type], "hard", Prerequisites[Satisfied], TRUE) -> 0 | V17: =T17-U17 -> 1 | W17: =COUNTIFS(Prerequisites[Run ID], $B17, Prerequisites[Type], "soft") -> 1 | X17: =COUNTIFS(Prerequisites[Run ID], $B17, Prerequisites[Type], "soft", Prerequisites[Satisfied], TRUE) -> 0 | Y17: =W17-X17 -> 1 | Z17: =COUNTIFS(Prerequisites[Prereq Run ID],$B17,Prerequisites[Type], "hard") -> 1 | AA17: =COUNTIFS(Reading_Order[Run ID], $B17, Reading_Order[Completed], TRUE) -> 0 | AB17: =$G17-$AA17 -> 35 | AC17: =AA17/(AB17+AA17) -> 0 | AD17: =IF(T17<1, TRUE, FALSE) -> FALSE
A18: Heroric Age | B18: bendis-heroic-age | C18: Avengers | D18: Brian Michael Bendis | F18: Enter the Heroic Age #1; Avengers: Prime #1-5; Avengers (2010) #1-12, #12.1; New Avengers (2010) #1-13; Secret Avengers #1-12, #12.1; Avengers Academy #1-14.1; Amazing Spider-Man (1999) #661-662; Avengers: The Children's Crusade #1-9; Children's Crusade: Young Avengers #1 | G18: =COUNTIF(Reading_Order[Run ID], B18) -> 71 | H18: 2010 | I18: 2012 | J18: =$G18>0 -> TRUE | K18: =IF($G18=0,"—",IF($AA18=$G18,"read",IF($AA18>0,"reading","unread"))) -> unread | L18: 4 | M18: The reset, and where Children's Crusade lives | O18: 4 | P18: 1 | Q18: FALSE | S18: =IF($V18>0, "blocked", IF($Y18=0, "ready-all", "ready-hard")) -> blocked | T18: =COUNTIFS(Prerequisites[Run ID], $B18, Prerequisites[Type], "hard") -> 1 | U18: =COUNTIFS(Prerequisites[Run ID], $B18, Prerequisites[Type], "hard", Prerequisites[Satisfied], TRUE) -> 0 | V18: =T18-U18 -> 1 | W18: =COUNTIFS(Prerequisites[Run ID], $B18, Prerequisites[Type], "soft") -> 2 | X18: =COUNTIFS(Prerequisites[Run ID], $B18, Prerequisites[Type], "soft", Prerequisites[Satisfied], TRUE) -> 0 | Y18: =W18-X18 -> 2 | Z18: =COUNTIFS(Prerequisites[Prereq Run ID],$B18,Prerequisites[Type], "hard") -> 1 | AA18: =COUNTIFS(Reading_Order[Run ID], $B18, Reading_Order[Completed], TRUE) -> 0 | AB18: =$G18-$AA18 -> 71 | AC18: =AA18/(AB18+AA18) -> 0 | AD18: =IF(T18<1, TRUE, FALSE) -> FALSE
A19: Fear Itself | B19: bendis-fear-itself | C19: Avengers | D19: Brian Michael Bendis | F19: Fear Itself: The Book of the Skull #1; Fear Itself #1-7, #7.1-7.3; Fear Itself: The Home Front #1-7; Avengers (2010) #13-24; Avengers (2010) Annual #1; New Avengers (2010) #14-23, #16.1; New Avengers (1996) Annual #1; Secret Avengers #13-25; Avengers Academy #15-20; Avengers Assemble #1-8 | G19: =COUNTIF(Reading_Order[Run ID], B19) -> 88 | H19: 2011 | I19: 2012 | J19: =$G19>0 -> TRUE | K19: =IF($G19=0,"—",IF($AA19=$G19,"read",IF($AA19>0,"reading","unread"))) -> unread | L19: 4 | M19: A Thor event more than an Avengers one | O19: 4 | P19: 2 | Q19: FALSE | S19: =IF($V19>0, "blocked", IF($Y19=0, "ready-all", "ready-hard")) -> blocked | T19: =COUNTIFS(Prerequisites[Run ID], $B19, Prerequisites[Type], "hard") -> 1 | U19: =COUNTIFS(Prerequisites[Run ID], $B19, Prerequisites[Type], "hard", Prerequisites[Satisfied], TRUE) -> 0 | V19: =T19-U19 -> 1 | W19: =COUNTIFS(Prerequisites[Run ID], $B19, Prerequisites[Type], "soft") -> 2 | X19: =COUNTIFS(Prerequisites[Run ID], $B19, Prerequisites[Type], "soft", Prerequisites[Satisfied], TRUE) -> 0 | Y19: =W19-X19 -> 2 | Z19: =COUNTIFS(Prerequisites[Prereq Run ID],$B19,Prerequisites[Type], "hard") -> 1 | AA19: =COUNTIFS(Reading_Order[Run ID], $B19, Reading_Order[Completed], TRUE) -> 0 | AB19: =$G19-$AA19 -> 88 | AC19: =AA19/(AB19+AA19) -> 0 | AD19: =IF(T19<1, TRUE, FALSE) -> FALSE
A20: Avengers vs. X-Men | B20: bendis-avx | C20: Avengers | D20: Brian Michael Bendis | F20: Avengers: X-Sanction #1-4; Avengers (2010) #24.1, #25-30; Avengers vs. X-Men #0, #1-12; New Avengers (2010) #24-30; Secret Avengers #26-28; Uncanny X-Men (2012) #11-20; Wolverine and the X-Men #9-15, #18; AvX: Consequences #1-5 | G20: =COUNTIF(Reading_Order[Run ID], B20) -> 68 | H20: 2011 | I20: 2012 | J20: =$G20>0 -> TRUE | K20: =IF($G20=0,"—",IF($AA20=$G20,"read",IF($AA20>0,"reading","unread"))) -> unread | L20: 4 | M20: Hope Summers is the plot — needs the Messiah Trilogy to land | O20: 4 | P20: 3 | Q20: FALSE | S20: =IF($V20>0, "blocked", IF($Y20=0, "ready-all", "ready-hard")) -> blocked | T20: =COUNTIFS(Prerequisites[Run ID], $B20, Prerequisites[Type], "hard") -> 4 | U20: =COUNTIFS(Prerequisites[Run ID], $B20, Prerequisites[Type], "hard", Prerequisites[Satisfied], TRUE) -> 0 | V20: =T20-U20 -> 4 | W20: =COUNTIFS(Prerequisites[Run ID], $B20, Prerequisites[Type], "soft") -> 1 | X20: =COUNTIFS(Prerequisites[Run ID], $B20, Prerequisites[Type], "soft", Prerequisites[Satisfied], TRUE) -> 0 | Y20: =W20-X20 -> 1 | Z20: =COUNTIFS(Prerequisites[Prereq Run ID],$B20,Prerequisites[Type], "hard") -> 2 | AA20: =COUNTIFS(Reading_Order[Run ID], $B20, Reading_Order[Completed], TRUE) -> 0 | AB20: =$G20-$AA20 -> 68 | AC20: =AA20/(AB20+AA20) -> 0 | AD20: =IF(T20<1, TRUE, FALSE) -> FALSE
A21: Age of Ultron | B21: bendis-ultron | C21: Avengers | D21: Brian Michael Bendis | F21: Avengers (2010) #31-34; New Avengers (2010) #31-34; Secret Avengers #29-37; Marvel NOW! Point One #1; Age of Ultron #1-10, #10AI | G21: =COUNTIF(Reading_Order[Run ID], B21) -> 35 | H21: 2012 | I21: 2013 | J21: =$G21>0 -> TRUE | K21: =IF($G21=0,"—",IF($AA21=$G21,"read",IF($AA21>0,"reading","unread"))) -> unread | L21: 4 | M21: Its ending leads into Hickman's Secret Wars | O21: 4 | P21: 4 | Q21: FALSE | S21: =IF($V21>0, "blocked", IF($Y21=0, "ready-all", "ready-hard")) -> blocked | T21: =COUNTIFS(Prerequisites[Run ID], $B21, Prerequisites[Type], "hard") -> 1 | U21: =COUNTIFS(Prerequisites[Run ID], $B21, Prerequisites[Type], "hard", Prerequisites[Satisfied], TRUE) -> 0 | V21: =T21-U21 -> 1 | W21: =COUNTIFS(Prerequisites[Run ID], $B21, Prerequisites[Type], "soft") -> 0 | X21: =COUNTIFS(Prerequisites[Run ID], $B21, Prerequisites[Type], "soft", Prerequisites[Satisfied], TRUE) -> 0 | Y21: =W21-X21 -> 0 | Z21: =COUNTIFS(Prerequisites[Prereq Run ID],$B21,Prerequisites[Type], "hard") -> 1 | AA21: =COUNTIFS(Reading_Order[Run ID], $B21, Reading_Order[Completed], TRUE) -> 0 | AB21: =$G21-$AA21 -> 35 | AC21: =AA21/(AB21+AA21) -> 0 | AD21: =IF(T21<1, TRUE, FALSE) -> FALSE
A22: Ewing Mighty Avengers | B22: ewing-mighty-avengers | C22: Avengers | D22: Al Ewing | F22: Avengers Assemble (2012) #14-15; The Mighty Avengers (2013) #1-14; Avengers: Ultron Forever; New Avengers: Ultron Forever; Uncanny Avengers: Ultron Forever; Captain America and the Mighty Avengers #1-9; Captain Britain and the Mighty Defenders #1-2 | G22: =COUNTIF(Reading_Order[Run ID], B22) -> 31 | H22: 2012 | I22: 2015 | J22: =$G22>0 -> TRUE | K22: =IF($G22=0,"—",IF($AA22=$G22,"read",IF($AA22>0,"reading","unread"))) -> unread | L22: 3 | M22: Blue Marvel, Monica Rambeau, the street-level Avengers nobody else writes | O22: 5 | P22: 1 | Q22: TRUE | S22: =IF($V22>0, "blocked", IF($Y22=0, "ready-all", "ready-hard")) -> blocked | T22: =COUNTIFS(Prerequisites[Run ID], $B22, Prerequisites[Type], "hard") -> 1 | U22: =COUNTIFS(Prerequisites[Run ID], $B22, Prerequisites[Type], "hard", Prerequisites[Satisfied], TRUE) -> 0 | V22: =T22-U22 -> 1 | W22: =COUNTIFS(Prerequisites[Run ID], $B22, Prerequisites[Type], "soft") -> 5 | X22: =COUNTIFS(Prerequisites[Run ID], $B22, Prerequisites[Type], "soft", Prerequisites[Satisfied], TRUE) -> 0 | Y22: =W22-X22 -> 5 | Z22: =COUNTIFS(Prerequisites[Prereq Run ID],$B22,Prerequisites[Type], "hard") -> 1 | AA22: =COUNTIFS(Reading_Order[Run ID], $B22, Reading_Order[Completed], TRUE) -> 0 | AB22: =$G22-$AA22 -> 31 | AC22: =AA22/(AB22+AA22) -> 0 | AD22: =IF(T22<1, TRUE, FALSE) -> FALSE
A23: Ewing Ultimates | B23: ewing-ultimates | C23: Avengers | D23: Al Ewing | F23: Contest of Champions #1-10; All New, All-Different Avengers #0; The Ultimates (2015) #1-12; The Ultimates (2017) 2 #1-9, 100 | G23: =COUNTIF(Reading_Order[Run ID], B23) -> 33 | H23: 2015 | I23: 2017 | J23: =$G23>0 -> TRUE | K23: =IF($G23=0,"—",IF($AA23=$G23,"read",IF($AA23>0,"reading","unread"))) -> unread | L23: 2 | M23: TARGET — direct sequel to Hickman's Secret Wars, and READY the moment you finish it | O23: 5 | P23: 2 | Q23: TRUE | S23: =IF($V23>0, "blocked", IF($Y23=0, "ready-all", "ready-hard")) -> blocked | T23: =COUNTIFS(Prerequisites[Run ID], $B23, Prerequisites[Type], "hard") -> 2 | U23: =COUNTIFS(Prerequisites[Run ID], $B23, Prerequisites[Type], "hard", Prerequisites[Satisfied], TRUE) -> 0 | V23: =T23-U23 -> 2 | W23: =COUNTIFS(Prerequisites[Run ID], $B23, Prerequisites[Type], "soft") -> 1 | X23: =COUNTIFS(Prerequisites[Run ID], $B23, Prerequisites[Type], "soft", Prerequisites[Satisfied], TRUE) -> 0 | Y23: =W23-X23 -> 1 | Z23: =COUNTIFS(Prerequisites[Prereq Run ID],$B23,Prerequisites[Type], "hard") -> 1 | AA23: =COUNTIFS(Reading_Order[Run ID], $B23, Reading_Order[Completed], TRUE) -> 0 | AB23: =$G23-$AA23 -> 33 | AC23: =AA23/(AB23+AA23) -> 0 | AD23: =IF(T23<1, TRUE, FALSE) -> FALSE
A24: Ewing New Avengers | B24: ewing-new-avengers | C24: Avengers | D24: Al Ewing | F24: New Avengers (2015) #1-18; U.S. Avengers #1-12 | G24: =COUNTIF(Reading_Order[Run ID], B24) -> 33 | H24: 2015 | I24: 2017 | J24: =$G24>0 -> TRUE | K24: =IF($G24=0,"—",IF($AA24=$G24,"read",IF($AA24>0,"reading","unread"))) -> unread | L24: 3 | M24: U.S.Avengers; Ewing at his most playful | O24: 5 | P24: 3 | Q24: TRUE | S24: =IF($V24>0, "blocked", IF($Y24=0, "ready-all", "ready-hard")) -> blocked | T24: =COUNTIFS(Prerequisites[Run ID], $B24, Prerequisites[Type], "hard") -> 2 | U24: =COUNTIFS(Prerequisites[Run ID], $B24, Prerequisites[Type], "hard", Prerequisites[Satisfied], TRUE) -> 0 | V24: =T24-U24 -> 2 | W24: =COUNTIFS(Prerequisites[Run ID], $B24, Prerequisites[Type], "soft") -> 1 | X24: =COUNTIFS(Prerequisites[Run ID], $B24, Prerequisites[Type], "soft", Prerequisites[Satisfied], TRUE) -> 0 | Y24: =W24-X24 -> 1 | Z24: =COUNTIFS(Prerequisites[Prereq Run ID],$B24,Prerequisites[Type], "hard") -> 1 | AA24: =COUNTIFS(Reading_Order[Run ID], $B24, Reading_Order[Completed], TRUE) -> 0 | AB24: =$G24-$AA24 -> 33 | AC24: =AA24/(AB24+AA24) -> 0 | AD24: =IF(T24<1, TRUE, FALSE) -> FALSE
... A33: Black Panther Origin | B33: black-panther-origin | C33: Black Panther | D33: Stan Lee | F33: Fantastic Four #52-53 | G33: =COUNTIF(Reading_Order[Run ID], B33) -> 10 | H33: 1966 | I33: 1966 | J33: =$G33>0 -> TRUE | K33: =IF($G33=0,"—",IF($AA33=$G33,"read",IF($AA33>0,"reading","unread"))) -> unread | L33: 4 | M33: Two issues of peak Kirby | O33: 1 | P33: 1 | Q33: TRUE | S33: =IF($V33>0, "blocked", IF($Y33=0, "ready-all", "ready-hard")) -> ready-hard | T33: =COUNTIFS(Prerequisites[Run ID], $B33, Prerequisites[Type], "hard") -> 0 | U33: =COUNTIFS(Prerequisites[Run ID], $B33, Prerequisites[Type], "hard", Prerequisites[Satisfied], TRUE) -> 0 | V33: =T33-U33 -> 0 | W33: =COUNTIFS(Prerequisites[Run ID], $B33, Prerequisites[Type], "soft") -> 1 | X33: =COUNTIFS(Prerequisites[Run ID], $B33, Prerequisites[Type], "soft", Prerequisites[Satisfied], TRUE) -> 0 | Y33: =W33-X33 -> 1 | Z33: =COUNTIFS(Prerequisites[Prereq Run ID],$B33,Prerequisites[Type], "hard") -> 1 | AA33: =COUNTIFS(Reading_Order[Run ID], $B33, Reading_Order[Completed], TRUE) -> 0 | AB33: =$G33-$AA33 -> 10 | AC33: =AA33/(AB33+AA33) -> 0 | AD33: =IF(T33<1, TRUE, FALSE) -> TRUE
A34: Panther's Rage | B34: mcgregor-panthers-rage | C34: Black Panther | D34: Don McGregor | E34: Rich Buckler, Billy Graham | F34: Jungle Action (1972) #6-22, #24 | G34: =COUNTIF(Reading_Order[Run ID], B34) -> 19 | H34: 1973 | I34: 1976 | J34: =$G34>0 -> TRUE | K34: =IF($G34=0,"—",IF($AA34=$G34,"read",IF($AA34>0,"reading","unread"))) -> unread | L34: 3 | M34: Arguably Marvel's first graphic novel, serialised 13 issues at a time | O34: 1 | P34: 2 | Q34: TRUE | S34: =IF($V34>0, "blocked", IF($Y34=0, "ready-all", "ready-hard")) -> ready-hard | T34: =COUNTIFS(Prerequisites[Run ID], $B34, Prerequisites[Type], "hard") -> 0 | U34: =COUNTIFS(Prerequisites[Run ID], $B34, Prerequisites[Type], "hard", Prerequisites[Satisfied], TRUE) -> 0 | V34: =T34-U34 -> 0 | W34: =COUNTIFS(Prerequisites[Run ID], $B34, Prerequisites[Type], "soft") -> 1 | X34: =COUNTIFS(Prerequisites[Run ID], $B34, Prerequisites[Type], "soft", Prerequisites[Satisfied], TRUE) -> 0 | Y34: =W34-X34 -> 1 | Z34: =COUNTIFS(Prerequisites[Prereq Run ID],$B34,Prerequisites[Type], "hard") -> 2 | AA34: =COUNTIFS(Reading_Order[Run ID], $B34, Reading_Order[Completed], TRUE) -> 0 | AB34: =$G34-$AA34 -> 19 | AC34: =AA34/(AB34+AA34) -> 0 | AD34: =IF(T34<1, TRUE, FALSE) -> TRUE
A35: Panther's Quest | B35: mcgregor-panthers-quest | C35: Black Panther | D35: Don McGregor | F35: Marvel Comics Presents #13-37 | G35: =COUNTIF(Reading_Order[Run ID], B35) -> 25 | J35: =$G35>0 -> TRUE | K35: =IF($G35=0,"—",IF($AA35=$G35,"read",IF($AA35>0,"reading","unread"))) -> unread | O35: 1 | P35: 3 | Q35: FALSE | S35: =IF($V35>0, "blocked", IF($Y35=0, "ready-all", "ready-hard")) -> blocked | T35: =COUNTIFS(Prerequisites[Run ID], $B35, Prerequisites[Type], "hard") -> 2 | U35: =COUNTIFS(Prerequisites[Run ID], $B35, Prerequisites[Type], "hard", Prerequisites[Satisfied], TRUE) -> 0 | V35: =T35-U35 -> 2 | W35: =COUNTIFS(Prerequisites[Run ID], $B35, Prerequisites[Type], "soft") -> 0 | X35: =COUNTIFS(Prerequisites[Run ID], $B35, Prerequisites[Type], "soft", Prerequisites[Satisfied], TRUE) -> 0 | Y35: =W35-X35 -> 0 | Z35: =COUNTIFS(Prerequisites[Prereq Run ID],$B35,Prerequisites[Type], "hard") -> 0 | AA35: =COUNTIFS(Reading_Order[Run ID], $B35, Reading_Order[Completed], TRUE) -> 0 | AB35: =$G35-$AA35 -> 25 | AC35: =AA35/(AB35+AA35) -> 0 | AD35: =IF(T35<1, TRUE, FALSE) -> FALSE
A36: Kirby's Black Panther | B36: kirby-black-panther | C36: Black Panther | D36: Jack Kirby | F36: Black Panther (1977) #1-15; Marvel Premiere (1972) #51-53 | G36: =COUNTIF(Reading_Order[Run ID], B36) -> 18 | H36: 1977 | I36: 1979 | J36: =$G36>0 -> TRUE | K36: =IF($G36=0,"—",IF($AA36=$G36,"read",IF($AA36>0,"reading","unread"))) -> unread | L36: 4 | M36: Kirby doing pulp adventure, unrelated to McGregor | O36: 1 | P36: 4 | Q36: FALSE | S36: =IF($V36>0, "blocked", IF($Y36=0, "ready-all", "ready-hard")) -> blocked | T36: =COUNTIFS(Prerequisites[Run ID], $B36, Prerequisites[Type], "hard") -> 1 | U36: =COUNTIFS(Prerequisites[Run ID], $B36, Prerequisites[Type], "hard", Prerequisites[Satisfied], TRUE) -> 0 | V36: =T36-U36 -> 1 | W36: =COUNTIFS(Prerequisites[Run ID], $B36, Prerequisites[Type], "soft") -> 0 | X36: =COUNTIFS(Prerequisites[Run ID], $B36, Prerequisites[Type], "soft", Prerequisites[Satisfied], TRUE) -> 0 | Y36: =W36-X36 -> 0 | Z36: =COUNTIFS(Prerequisites[Prereq Run ID],$B36,Prerequisites[Type], "hard") -> 1 | AA36: =COUNTIFS(Reading_Order[Run ID], $B36, Reading_Order[Completed], TRUE) -> 0 | AB36: =$G36-$AA36 -> 18 | AC36: =AA36/(AB36+AA36) -> 0 | AD36: =IF(T36<1, TRUE, FALSE) -> FALSE
A37: Priest's Black Panther | B37: priest-black-panther | C37: Black Panther | D37: Christopher Priest | E37: Mark Texeira | F37: Black Panther (1998) #1-62; Avengers (1998) #19-23, #57-61, #65-70, #76; Deadpool (1997) #44; Incredible Hulk (2000) #33; Crew #1-7 | G37: =COUNTIF(Reading_Order[Run ID], B37) -> 93 | H37: 1998 | I37: 2003 | J37: =$G37>0 -> TRUE | K37: =IF($G37=0,"—",IF($AA37=$G37,"read",IF($AA37>0,"reading","unread"))) -> unread | L37: 3 | M37: #5 is the best sampling point in the run | O37: 1 | P37: 5 | Q37: TRUE | S37: =IF($V37>0, "blocked", IF($Y37=0, "ready-all", "ready-hard")) -> blocked | T37: =COUNTIFS(Prerequisites[Run ID], $B37, Prerequisites[Type], "hard") -> 1 | U37: =COUNTIFS(Prerequisites[Run ID], $B37, Prerequisites[Type], "hard", Prerequisites[Satisfied], TRUE) -> 0 | V37: =T37-U37 -> 1 | W37: =COUNTIFS(Prerequisites[Run ID], $B37, Prerequisites[Type], "soft") -> 2 | X37: =COUNTIFS(Prerequisites[Run ID], $B37, Prerequisites[Type], "soft", Prerequisites[Satisfied], TRUE) -> 0 | Y37: =W37-X37 -> 2 | Z37: =COUNTIFS(Prerequisites[Prereq Run ID],$B37,Prerequisites[Type], "hard") -> 1 | AA37: =COUNTIFS(Reading_Order[Run ID], $B37, Reading_Order[Completed], TRUE) -> 0 | AB37: =$G37-$AA37 -> 93 | AC37: =AA37/(AB37+AA37) -> 0 | AD37: =IF(T37<1, TRUE, FALSE) -> FALSE
A38: Hudlin's Black Panther | B38: hudlin-black-panther | C38: Black Panther | D38: Reginald Hudlin | F38: Black Panther (2005) #1-41; X-Men (1991) #175-176; Storm #1-6; Fantastic Four (1961) #544-550; Black Panther (2005) Annual #1; Black Panther (2009) #1-12; Doomwar #1-6; Klaws of the Panther #1-4 | G38: =COUNTIF(Reading_Order[Run ID], B38) -> 87 | H38: 2005 | I38: 2010 | J38: =$G38>0 -> TRUE | K38: =IF($G38=0,"—",IF($AA38=$G38,"read",IF($AA38>0,"reading","unread"))) -> unread | L38: 4 | M38: The Storm marriage and Doomwar | O38: 1 | P38: 6 | Q38: FALSE | S38: =IF($V38>0, "blocked", IF($Y38=0, "ready-all", "ready-hard")) -> blocked | T38: =COUNTIFS(Prerequisites[Run ID], $B38, Prerequisites[Type], "hard") -> 1 | U38: =COUNTIFS(Prerequisites[Run ID], $B38, Prerequisites[Type], "hard", Prerequisites[Satisfied], TRUE) -> 0 | V38: =T38-U38 -> 1 | W38: =COUNTIFS(Prerequisites[Run ID], $B38, Prerequisites[Type], "soft") -> 1 | X38: =COUNTIFS(Prerequisites[Run ID], $B38, Prerequisites[Type], "soft", Prerequisites[Satisfied], TRUE) -> 0 | Y38: =W38-X38 -> 1 | Z38: =COUNTIFS(Prerequisites[Prereq Run ID],$B38,Prerequisites[Type], "hard") -> 2 | AA38: =COUNTIFS(Reading_Order[Run ID], $B38, Reading_Order[Completed], TRUE) -> 0 | AB38: =$G38-$AA38 -> 87 | AC38: =AA38/(AB38+AA38) -> 0 | AD38: =IF(T38<1, TRUE, FALSE) -> FALSE
A39: Coates' Black Panther | B39: coates-black-panther | C39: Black Panther | D39: Ta-Nehisi Coates | E39: Brian Stelfreeze | F39: Black Panther (2016) #1-18; Black Panther (2018) #1-25 | G39: =COUNTIF(Reading_Order[Run ID], B39) -> 76 | H39: 2016 | I39: 2021 | J39: =$G39>0 -> TRUE | K39: =IF($G39=0,"—",IF($AA39=$G39,"read",IF($AA39>0,"reading","unread"))) -> unread | L39: 3 | M39: Starts, really, in Hickman's New Avengers — which you'll have read | O39: 1 | P39: 7 | Q39: TRUE | S39: =IF($V39>0, "blocked", IF($Y39=0, "ready-all", "ready-hard")) -> blocked | T39: =COUNTIFS(Prerequisites[Run ID], $B39, Prerequisites[Type], "hard") -> 1 | U39: =COUNTIFS(Prerequisites[Run ID], $B39, Prerequisites[Type], "hard", Prerequisites[Satisfied], TRUE) -> 0 | V39: =T39-U39 -> 1 | W39: =COUNTIFS(Prerequisites[Run ID], $B39, Prerequisites[Type], "soft") -> 2 | X39: =COUNTIFS(Prerequisites[Run ID], $B39, Prerequisites[Type], "soft", Prerequisites[Satisfied], TRUE) -> 0 | Y39: =W39-X39 -> 2 | Z39: =COUNTIFS(Prerequisites[Prereq Run ID],$B39,Prerequisites[Type], "hard") -> 0 | AA39: =COUNTIFS(Reading_Order[Run ID], $B39, Reading_Order[Completed], TRUE) -> 0 | AB39: =$G39-$AA39 -> 76 | AC39: =AA39/(AB39+AA39) -> 0 | AD39: =IF(T39<1, TRUE, FALSE) -> FALSE
A40: Captain America Origin | B40: cap-origin | C40: Captain America | D40: Joe Simon, Stan Lee, Jack Kirby | F40: Captain America Comics #1; Avengers #4; Tales of Suspense #63, 72-81; Sgt. Fury #13; Captain America #110-111, 113 | G40: =COUNTIF(Reading_Order[Run ID], B40) -> 41 | H40: 1941 | I40: 1965 | J40: =$G40>0 -> TRUE | K40: =IF($G40=0,"—",IF($AA40=$G40,"read",IF($AA40>0,"reading","unread"))) -> unread | L40: 4 | M40: Avengers #4 is the real start of modern Cap | O40: 1 | P40: 1 | Q40: FALSE | S40: =IF($V40>0, "blocked", IF($Y40=0, "ready-all", "ready-hard")) -> ready-all | T40: =COUNTIFS(Prerequisites[Run ID], $B40, Prerequisites[Type], "hard") -> 0 | U40: =COUNTIFS(Prerequisites[Run ID], $B40, Prerequisites[Type], "hard", Prerequisites[Satisfied], TRUE) -> 0 | V40: =T40-U40 -> 0 | W40: =COUNTIFS(Prerequisites[Run ID], $B40, Prerequisites[Type], "soft") -> 0 | X40: =COUNTIFS(Prerequisites[Run ID], $B40, Prerequisites[Type], "soft", Prerequisites[Satisfied], TRUE) -> 0 | Y40: =W40-X40 -> 0 | Z40: =COUNTIFS(Prerequisites[Prereq Run ID],$B40,Prerequisites[Type], "hard") -> 2 | AA40: =COUNTIFS(Reading_Order[Run ID], $B40, Reading_Order[Completed], TRUE) -> 0 | AB40: =$G40-$AA40 -> 41 | AC40: =AA40/(AB40+AA40) -> 0 | AD40: =IF(T40<1, TRUE, FALSE) -> TRUE
A41: Englehart's Captain America | B41: englehart-cap | C41: Captain America | D41: Steve Englehart | E41: Sal Buscema | F41: Captain America #153-186 | G41: =COUNTIF(Reading_Order[Run ID], B41) -> 39 | H41: 1972 | I41: 1975 | J41: =$G41>0 -> TRUE | K41: =IF($G41=0,"—",IF($AA41=$G41,"read",IF($AA41>0,"reading","unread"))) -> unread | L41: 4 | M41: Cap quits over Watergate. Still startling | O41: 1 | P41: 2 | Q41: FALSE | S41: =IF($V41>0, "blocked", IF($Y41=0, "ready-all", "ready-hard")) -> blocked | T41: =COUNTIFS(Prerequisites[Run ID], $B41, Prerequisites[Type], "hard") -> 1 | U41: =COUNTIFS(Prerequisites[Run ID], $B41, Prerequisites[Type], "hard", Prerequisites[Satisfied], TRUE) -> 0 | V41: =T41-U41 -> 1 | W41: =COUNTIFS(Prerequisites[Run ID], $B41, Prerequisites[Type], "soft") -> 1 | X41: =COUNTIFS(Prerequisites[Run ID], $B41, Prerequisites[Type], "soft", Prerequisites[Satisfied], TRUE) -> 0 | Y41: =W41-X41 -> 1 | Z41: =COUNTIFS(Prerequisites[Prereq Run ID],$B41,Prerequisites[Type], "hard") -> 1 | AA41: =COUNTIFS(Reading_Order[Run ID], $B41, Reading_Order[Completed], TRUE) -> 0 | AB41: =$G41-$AA41 -> 39 | AC41: =AA41/(AB41+AA41) -> 0 | AD41: =IF(T41<1, TRUE, FALSE) -> FALSE
A42: Kirby's Captain America | B42: kirby-cap | C42: Captain America | D42: Jack Kirby | F42: Captain America (1968) #193-214 | G42: =COUNTIF(Reading_Order[Run ID], B42) -> 25 | H42: 1976 | I42: 1977 | J42: =$G42>0 -> TRUE | K42: =IF($G42=0,"—",IF($AA42=$G42,"read",IF($AA42>0,"reading","unread"))) -> unread | L42: 4 | M42: Deranged in the best way — the Madbomb | O42: 1 | P42: 3 | Q42: FALSE | S42: =IF($V42>0, "blocked", IF($Y42=0, "ready-all", "ready-hard")) -> blocked | T42: =COUNTIFS(Prerequisites[Run ID], $B42, Prerequisites[Type], "hard") -> 1 | U42: =COUNTIFS(Prerequisites[Run ID], $B42, Prerequisites[Type], "hard", Prerequisites[Satisfied], TRUE) -> 0 | V42: =T42-U42 -> 1 | W42: =COUNTIFS(Prerequisites[Run ID], $B42, Prerequisites[Type], "soft") -> 0 | X42: =COUNTIFS(Prerequisites[Run ID], $B42, Prerequisites[Type], "soft", Prerequisites[Satisfied], TRUE) -> 0 | Y42: =W42-X42 -> 0 | Z42: =COUNTIFS(Prerequisites[Prereq Run ID],$B42,Prerequisites[Type], "hard") -> 1 | AA42: =COUNTIFS(Reading_Order[Run ID], $B42, Reading_Order[Completed], TRUE) -> 0 | AB42: =$G42-$AA42 -> 25 | AC42: =AA42/(AB42+AA42) -> 0 | AD42: =IF(T42<1, TRUE, FALSE) -> FALSE
A43: Stern/Byrne's Captain America | B43: stern-byrne-cap | C43: Captain America | D43: John Byrne, Roger Stern | F43: Captain America #247-255 | G43: =COUNTIF(Reading_Order[Run ID], B43) -> 9 | H43: 1980 | I43: 1981 | J43: =$G43>0 -> TRUE | K43: =IF($G43=0,"—",IF($AA43=$G43,"read",IF($AA43>0,"reading","unread"))) -> unread | L43: 4 | M43: Nine issues, and the template for every modern Cap run | O43: 1 | P43: 4 | Q43: FALSE | S43: =IF($V43>0, "blocked", IF($Y43=0, "ready-all", "ready-hard")) -> blocked | T43: =COUNTIFS(Prerequisites[Run ID], $B43, Prerequisites[Type], "hard") -> 1 | U43: =COUNTIFS(Prerequisites[Run ID], $B43, Prerequisites[Type], "hard", Prerequisites[Satisfied], TRUE) -> 0 | V43: =T43-U43 -> 1 | W43: =COUNTIFS(Prerequisites[Run ID], $B43, Prerequisites[Type], "soft") -> 1 | X43: =COUNTIFS(Prerequisites[Run ID], $B43, Prerequisites[Type], "soft", Prerequisites[Satisfied], TRUE) -> 0 | Y43: =W43-X43 -> 1 | Z43: =COUNTIFS(Prerequisites[Prereq Run ID],$B43,Prerequisites[Type], "hard") -> 1 | AA43: =COUNTIFS(Reading_Order[Run ID], $B43, Reading_Order[Completed], TRUE) -> 0 | AB43: =$G43-$AA43 -> 9 | AC43: =AA43/(AB43+AA43) -> 0 | AD43: =IF(T43<1, TRUE, FALSE) -> FALSE
A44: Dematteis's Captain America | B44: dematteis-cap | C44: Captain America | D44: J.M. Dematteis | F44: Captain America #261-278, 290-300 | G44: =COUNTIF(Reading_Order[Run ID], B44) -> 43 | H44: 1981 | I44: 1984 | J44: =$G44>0 -> TRUE | K44: =IF($G44=0,"—",IF($AA44=$G44,"read",IF($AA44>0,"reading","unread"))) -> unread | L44: 4 | M44: The Red Skull material; Cap's most explicitly moral era | O44: 1 | P44: 5 | Q44: FALSE | S44: =IF($V44>0, "blocked", IF($Y44=0, "ready-all", "ready-hard")) -> blocked | T44: =COUNTIFS(Prerequisites[Run ID], $B44, Prerequisites[Type], "hard") -> 1 | U44: =COUNTIFS(Prerequisites[Run ID], $B44, Prerequisites[Type], "hard", Prerequisites[Satisfied], TRUE) -> 0 | V44: =T44-U44 -> 1 | W44: =COUNTIFS(Prerequisites[Run ID], $B44, Prerequisites[Type], "soft") -> 0 | X44: =COUNTIFS(Prerequisites[Run ID], $B44, Prerequisites[Type], "soft", Prerequisites[Satisfied], TRUE) -> 0 | Y44: =W44-X44 -> 0 | Z44: =COUNTIFS(Prerequisites[Prereq Run ID],$B44,Prerequisites[Type], "hard") -> 1 | AA44: =COUNTIFS(Reading_Order[Run ID], $B44, Reading_Order[Completed], TRUE) -> 0 | AB44: =$G44-$AA44 -> 43 | AC44: =AA44/(AB44+AA44) -> 0 | AD44: =IF(T44<1, TRUE, FALSE) -> FALSE
A45: Gruenwald's Captain America | B45: gruenwald-cap | C45: Captain America | D45: Mark Gruenwald | E45: Various | F45: Captain America #307-312, 318-323, 332-350, 354, 367, 401-408 | G45: =COUNTIF(Reading_Order[Run ID], B45) -> 80 | H45: 1985 | I45: 1995 | J45: =$G45>0 -> TRUE | K45: =IF($G45=0,"—",IF($AA45=$G45,"read",IF($AA45>0,"reading","unread"))) -> unread | L45: 4 | M45: Captain America No More' and the Cap-Wolf era | O45: 1 | P45: 6 | Q45: FALSE | S45: =IF($V45>0, "blocked", IF($Y45=0, "ready-all", "ready-hard")) -> blocked | T45: =COUNTIFS(Prerequisites[Run ID], $B45, Prerequisites[Type], "hard") -> 1 | U45: =COUNTIFS(Prerequisites[Run ID], $B45, Prerequisites[Type], "hard", Prerequisites[Satisfied], TRUE) -> 0 | V45: =T45-U45 -> 1 | W45: =COUNTIFS(Prerequisites[Run ID], $B45, Prerequisites[Type], "soft") -> 0 | X45: =COUNTIFS(Prerequisites[Run ID], $B45, Prerequisites[Type], "soft", Prerequisites[Satisfied], TRUE) -> 0 | Y45: =W45-X45 -> 0 | Z45: =COUNTIFS(Prerequisites[Prereq Run ID],$B45,Prerequisites[Type], "hard") -> 1 | AA45: =COUNTIFS(Reading_Order[Run ID], $B45, Reading_Order[Completed], TRUE) -> 0 | AB45: =$G45-$AA45 -> 80 | AC45: =AA45/(AB45+AA45) -> 0 | AD45: =IF(T45<1, TRUE, FALSE) -> FALSE
A46: Waid's Captain America | B46: waid-cap | C46: Captain America | D46: Mark Waid | E46: Ron Garney | F46: Captain America #444-454; Captain America (1997) #1-23 | G46: =COUNTIF(Reading_Order[Run ID], B46) -> 47 | H46: 1995 | I46: 2000 | J46: =$G46>0 -> TRUE | K46: =IF($G46=0,"—",IF($AA46=$G46,"read",IF($AA46>0,"reading","unread"))) -> unread | L46: 4 | M46: The sincere Cap that Brubaker then complicates | O46: 1 | P46: 7 | Q46: FALSE | S46: =IF($V46>0, "blocked", IF($Y46=0, "ready-all", "ready-hard")) -> blocked | T46: =COUNTIFS(Prerequisites[Run ID], $B46, Prerequisites[Type], "hard") -> 1 | U46: =COUNTIFS(Prerequisites[Run ID], $B46, Prerequisites[Type], "hard", Prerequisites[Satisfied], TRUE) -> 0 | V46: =T46-U46 -> 1 | W46: =COUNTIFS(Prerequisites[Run ID], $B46, Prerequisites[Type], "soft") -> 0 | X46: =COUNTIFS(Prerequisites[Run ID], $B46, Prerequisites[Type], "soft", Prerequisites[Satisfied], TRUE) -> 0 | Y46: =W46-X46 -> 0 | Z46: =COUNTIFS(Prerequisites[Prereq Run ID],$B46,Prerequisites[Type], "hard") -> 0 | AA46: =COUNTIFS(Reading_Order[Run ID], $B46, Reading_Order[Completed], TRUE) -> 0 | AB46: =$G46-$AA46 -> 47 | AC46: =AA46/(AB46+AA46) -> 0 | AD46: =IF(T46<1, TRUE, FALSE) -> FALSE
A47: Brubaker's Captain America | B47: brubaker-cap | C47: Captain America | D47: Ed Brubaker | E47: Steve Epting | F47: Captain America (2004) #1-50, 600-619, 615.1; Captain America 65th Anniversary Special; Winter Soldier: Winter Kills; Civil War #1-7; Civil War: The Confession; Fallen Son: Iron Man; Captain America Reborn #1-6, Prologue; Captain America: Who Will Wield the Shield?; Secret Avengerss (2010) #1-12, 16-21; Fear Itself: Book of the Skrull; Fear Itself #1-7, 7.1; Captain America and Bucky #620-624; Captain America (2011) #1-19; Winter Soldier #1-19 | G47: =COUNTIF(Reading_Order[Run ID], B47) -> 139 | H47: 2004 | I47: 2012 | J47: =$G47>0 -> TRUE | K47: =IF($G47=0,"—",IF($AA47=$G47,"read",IF($AA47>0,"reading","unread"))) -> unread | L47: 3 | M47: The Winter Soldier — one of the best superhero runs of the century | O47: 2 | P47: 1 | Q47: TRUE | S47: =IF($V47>0, "blocked", IF($Y47=0, "ready-all", "ready-hard")) -> ready-hard | T47: =COUNTIFS(Prerequisites[Run ID], $B47, Prerequisites[Type], "hard") -> 0 | U47: =COUNTIFS(Prerequisites[Run ID], $B47, Prerequisites[Type], "hard", Prerequisites[Satisfied], TRUE) -> 0 | V47: =T47-U47 -> 0 | W47: =COUNTIFS(Prerequisites[Run ID], $B47, Prerequisites[Type], "soft") -> 2 | X47: =COUNTIFS(Prerequisites[Run ID], $B47, Prerequisites[Type], "soft", Prerequisites[Satisfied], TRUE) -> 0 | Y47: =W47-X47 -> 2 | Z47: =COUNTIFS(Prerequisites[Prereq Run ID],$B47,Prerequisites[Type], "hard") -> 1 | AA47: =COUNTIFS(Reading_Order[Run ID], $B47, Reading_Order[Completed], TRUE) -> 0 | AB47: =$G47-$AA47 -> 139 | AC47: =AA47/(AB47+AA47) -> 0 | AD47: =IF(T47<1, TRUE, FALSE) -> TRUE
A48: Captain America: White | B48: captain-america-white | C48: Captain America | D48: Jeph Loeb | F48: Captain America: White #0-5 | G48: =COUNTIF(Reading_Order[Run ID], B48) -> 6 | H48: 2008 | I48: 2015 | J48: =$G48>0 -> TRUE | K48: =IF($G48=0,"—",IF($AA48=$G48,"read",IF($AA48>0,"reading","unread"))) -> unread | L48: 4 | O48: 2 | P48: 2 | Q48: FALSE | S48: =IF($V48>0, "blocked", IF($Y48=0, "ready-all", "ready-hard")) -> blocked | T48: =COUNTIFS(Prerequisites[Run ID], $B48, Prerequisites[Type], "hard") -> 1 | U48: =COUNTIFS(Prerequisites[Run ID], $B48, Prerequisites[Type], "hard", Prerequisites[Satisfied], TRUE) -> 0 | V48: =T48-U48 -> 1 | W48: =COUNTIFS(Prerequisites[Run ID], $B48, Prerequisites[Type], "soft") -> 0 | X48: =COUNTIFS(Prerequisites[Run ID], $B48, Prerequisites[Type], "soft", Prerequisites[Satisfied], TRUE) -> 0 | Y48: =W48-X48 -> 0 | Z48: =COUNTIFS(Prerequisites[Prereq Run ID],$B48,Prerequisites[Type], "hard") -> 0 | AA48: =COUNTIFS(Reading_Order[Run ID], $B48, Reading_Order[Completed], TRUE) -> 0 | AB48: =$G48-$AA48 -> 6 | AC48: =AA48/(AB48+AA48) -> 0 | AD48: =IF(T48<1, TRUE, FALSE) -> FALSE
A49: Remender's Captain America | B49: remender-cap | C49: Captain America | D49: Rick Remender | F49: Captain America (2012) #1-25 | G49: =COUNTIF(Reading_Order[Run ID], B49) -> 40 | H49: 2012 | I49: 2014 | J49: =$G49>0 -> TRUE | K49: =IF($G49=0,"—",IF($AA49=$G49,"read",IF($AA49>0,"reading","unread"))) -> unread | L49: 4 | M49: Dimension Z. Oddly brutal and unfairly forgotten | O49: 3 | P49: 1 | Q49: FALSE | S49: =IF($V49>0, "blocked", IF($Y49=0, "ready-all", "ready-hard")) -> blocked | T49: =COUNTIFS(Prerequisites[Run ID], $B49, Prerequisites[Type], "hard") -> 1 | U49: =COUNTIFS(Prerequisites[Run ID], $B49, Prerequisites[Type], "hard", Prerequisites[Satisfied], TRUE) -> 0 | V49: =T49-U49 -> 1 | W49: =COUNTIFS(Prerequisites[Run ID], $B49, Prerequisites[Type], "soft") -> 1 | X49: =COUNTIFS(Prerequisites[Run ID], $B49, Prerequisites[Type], "soft", Prerequisites[Satisfied], TRUE) -> 0 | Y49: =W49-X49 -> 1 | Z49: =COUNTIFS(Prerequisites[Prereq Run ID],$B49,Prerequisites[Type], "hard") -> 1 | AA49: =COUNTIFS(Reading_Order[Run ID], $B49, Reading_Order[Completed], TRUE) -> 0 | AB49: =$G49-$AA49 -> 40 | AC49: =AA49/(AB49+AA49) -> 0 | AD49: =IF(T49<1, TRUE, FALSE) -> FALSE
A50: Secret Empire | B50: secret-empire | C50: Captain America | D50: Nick Spencer | F50: Secret Empire #0-10; Secret Empire: Omega; Captain America: Steve Rogers #1-19; Captain America: Sam Wilson #1-24 | G50: =COUNTIF(Reading_Order[Run ID], B50) -> 66 | H50: 2015 | I50: 2017 | J50: =$G50>0 -> TRUE | K50: =IF($G50=0,"—",IF($AA50=$G50,"read",IF($AA50>0,"reading","unread"))) -> unread | L50: 4 | M50: Required setup for Coates, though Coates isn't in your list | O50: 3 | P50: 2 | Q50: TRUE | S50: =IF($V50>0, "blocked", IF($Y50=0, "ready-all", "ready-hard")) -> blocked | T50: =COUNTIFS(Prerequisites[Run ID], $B50, Prerequisites[Type], "hard") -> 1 | U50: =COUNTIFS(Prerequisites[Run ID], $B50, Prerequisites[Type], "hard", Prerequisites[Satisfied], TRUE) -> 0 | V50: =T50-U50 -> 1 | W50: =COUNTIFS(Prerequisites[Run ID], $B50, Prerequisites[Type], "soft") -> 3 | X50: =COUNTIFS(Prerequisites[Run ID], $B50, Prerequisites[Type], "soft", Prerequisites[Satisfied], TRUE) -> 0 | Y50: =W50-X50 -> 3 | Z50: =COUNTIFS(Prerequisites[Prereq Run ID],$B50,Prerequisites[Type], "hard") -> 0 | AA50: =COUNTIFS(Reading_Order[Run ID], $B50, Reading_Order[Completed], TRUE) -> 0 | AB50: =$G50-$AA50 -> 66 | AC50: =AA50/(AB50+AA50) -> 0 | AD50: =IF(T50<1, TRUE, FALSE) -> FALSE
A51: Zdarsky's Captain America | B51: zdarsky-cap | C51: Captain America | D51: Chip Zdarsky | E51: Valerio Schiti | F51: Captain America (2025) #1-15; Wolverine: Weapons of Armageddon #1 | G51: =COUNTIF(Reading_Order[Run ID], B51) -> 19 | H51: 2025 | I51: 2026 | J51: =$G51>0 -> TRUE | K51: =IF($G51=0,"—",IF($AA51=$G51,"read",IF($AA51>0,"reading","unread"))) -> unread | L51: 4 | M51: Current run; One World Under Doom crossover from #6 | O51: 4 | P51: 1 | Q51: TRUE | S51: =IF($V51>0, "blocked", IF($Y51=0, "ready-all", "ready-hard")) -> ready-hard | T51: =COUNTIFS(Prerequisites[Run ID], $B51, Prerequisites[Type], "hard") -> 0 | U51: =COUNTIFS(Prerequisites[Run ID], $B51, Prerequisites[Type], "hard", Prerequisites[Satisfied], TRUE) -> 0 | V51: =T51-U51 -> 0 | W51: =COUNTIFS(Prerequisites[Run ID], $B51, Prerequisites[Type], "soft") -> 2 | X51: =COUNTIFS(Prerequisites[Run ID], $B51, Prerequisites[Type], "soft", Prerequisites[Satisfied], TRUE) -> 0 | Y51: =W51-X51 -> 2 | Z51: =COUNTIFS(Prerequisites[Prereq Run ID],$B51,Prerequisites[Type], "hard") -> 0 | AA51: =COUNTIFS(Reading_Order[Run ID], $B51, Reading_Order[Completed], TRUE) -> 0 | AB51: =$G51-$AA51 -> 19 | AC51: =AA51/(AB51+AA51) -> 0 | AD51: =IF(T51<1, TRUE, FALSE) -> TRUE
A52: Carol Danvers Origin | B52: carol-danvers-origin | C52: Captain Marvel | D52: Gerry Conway, Chris Claremont | F52: Ms. Marvel #1-2; Avengers Annual #10 | G52: =COUNTIF(Reading_Order[Run ID], B52) -> 29 | H52: 1977 | I52: 1981 | J52: =$G52>0 -> TRUE | K52: =IF($G52=0,"—",IF($AA52=$G52,"read",IF($AA52>0,"reading","unread"))) -> unread | L52: 4 | M52: Feeds both DeConnick and Wilson's Ms. Marvel | O52: 1 | P52: 1 | Q52: TRUE | S52: =IF($V52>0, "blocked", IF($Y52=0, "ready-all", "ready-hard")) -> ready-all | T52: =COUNTIFS(Prerequisites[Run ID], $B52, Prerequisites[Type], "hard") -> 0 | U52: =COUNTIFS(Prerequisites[Run ID], $B52, Prerequisites[Type], "hard", Prerequisites[Satisfied], TRUE) -> 0 | V52: =T52-U52 -> 0 | W52: =COUNTIFS(Prerequisites[Run ID], $B52, Prerequisites[Type], "soft") -> 0 | X52: =COUNTIFS(Prerequisites[Run ID], $B52, Prerequisites[Type], "soft", Prerequisites[Satisfied], TRUE) -> 0 | Y52: =W52-X52 -> 0 | Z52: =COUNTIFS(Prerequisites[Prereq Run ID],$B52,Prerequisites[Type], "hard") -> 1 | AA52: =COUNTIFS(Reading_Order[Run ID], $B52, Reading_Order[Completed], TRUE) -> 0 | AB52: =$G52-$AA52 -> 29 | AC52: =AA52/(AB52+AA52) -> 0 | AD52: =IF(T52<1, TRUE, FALSE) -> TRUE
A53: DeConnick's Captain Marvel | B53: deconnick-captain-marvel | C53: Captain Marvel | D53: Kelly Sue DeConnick | E53: Dexter Soy | F53: Captain Marvel (2012) #1-17 | G53: =COUNTIF(Reading_Order[Run ID], B53) -> 43 | H53: 2012 | I53: 2013 | J53: =$G53>0 -> TRUE | K53: =IF($G53=0,"—",IF($AA53=$G53,"read",IF($AA53>0,"reading","unread"))) -> unread | L53: 4 | M53: Carol takes the name | O53: 1 | P53: 2 | Q53: TRUE | S53: =IF($V53>0, "blocked", IF($Y53=0, "ready-all", "ready-hard")) -> blocked | T53: =COUNTIFS(Prerequisites[Run ID], $B53, Prerequisites[Type], "hard") -> 1 | U53: =COUNTIFS(Prerequisites[Run ID], $B53, Prerequisites[Type], "hard", Prerequisites[Satisfied], TRUE) -> 0 | V53: =T53-U53 -> 1 | W53: =COUNTIFS(Prerequisites[Run ID], $B53, Prerequisites[Type], "soft") -> 0 | X53: =COUNTIFS(Prerequisites[Run ID], $B53, Prerequisites[Type], "soft", Prerequisites[Satisfied], TRUE) -> 0 | Y53: =W53-X53 -> 0 | Z53: =COUNTIFS(Prerequisites[Prereq Run ID],$B53,Prerequisites[Type], "hard") -> 0 | AA53: =COUNTIFS(Reading_Order[Run ID], $B53, Reading_Order[Completed], TRUE) -> 0 | AB53: =$G53-$AA53 -> 43 | AC53: =AA53/(AB53+AA53) -> 0 | AD53: =IF(T53<1, TRUE, FALSE) -> FALSE
A54: Kamala Kahn | B54: wilson-ms-marvel | C54: Captain Marvel | D54: G. Willow Wilson | E54: Adrian Alphona | F54: All-New Marvel NOW! Point One #1; Ms. Marvel (2014) #1-19; All-New, All-Different Avengers #1-15; Ms. Marvel (2015) #1-38; Civil War II #1-8; All-New, All-Different Avengers Annual #1; Champions #1-27; Secret Empire #1-10; Secret Warriors (2017) #1-12; Avengers 672; Avengers (1963) #673-674; Champions Annula #1 | G54: =COUNTIF(Reading_Order[Run ID], B54) -> 147 | H54: 2014 | I54: 2019 | J54: =$G54>0 -> TRUE | K54: =IF($G54=0,"—",IF($AA54=$G54,"read",IF($AA54>0,"reading","unread"))) -> unread | L54: 4 | M54: Warm, funny, and the best new character Marvel made this century | O54: 2 | P54: 1 | Q54: TRUE | S54: =IF($V54>0, "blocked", IF($Y54=0, "ready-all", "ready-hard")) -> ready-hard | T54: =COUNTIFS(Prerequisites[Run ID], $B54, Prerequisites[Type], "hard") -> 0 | U54: =COUNTIFS(Prerequisites[Run ID], $B54, Prerequisites[Type], "hard", Prerequisites[Satisfied], TRUE) -> 0 | V54: =T54-U54 -> 0 | W54: =COUNTIFS(Prerequisites[Run ID], $B54, Prerequisites[Type], "soft") -> 1 | X54: =COUNTIFS(Prerequisites[Run ID], $B54, Prerequisites[Type], "soft", Prerequisites[Satisfied], TRUE) -> 0 | Y54: =W54-X54 -> 1 | Z54: =COUNTIFS(Prerequisites[Prereq Run ID],$B54,Prerequisites[Type], "hard") -> 0 | AA54: =COUNTIFS(Reading_Order[Run ID], $B54, Reading_Order[Completed], TRUE) -> 0 | AB54: =$G54-$AA54 -> 147 | AC54: =AA54/(AB54+AA54) -> 0 | AD54: =IF(T54<1, TRUE, FALSE) -> TRUE
A55: Silver Surfer Origin | B55: silver-surfer-origin | C55: Cosmic | D55: Stan Lee | F55: Fantastic Four #48-50; Silver Surfer #1 | G55: =COUNTIF(Reading_Order[Run ID], B55) -> 35 | H55: 1966 | I55: 1968 | J55: =$G55>0 -> TRUE | K55: =IF($G55=0,"—",IF($AA55=$G55,"read",IF($AA55>0,"reading","unread"))) -> unread | L55: 4 | M55: Norrin's bargain with Galactus | O55: 1 | P55: 1 | Q55: FALSE | S55: =IF($V55>0, "blocked", IF($Y55=0, "ready-all", "ready-hard")) -> blocked | T55: =COUNTIFS(Prerequisites[Run ID], $B55, Prerequisites[Type], "hard") -> 1 | U55: =COUNTIFS(Prerequisites[Run ID], $B55, Prerequisites[Type], "hard", Prerequisites[Satisfied], TRUE) -> 0 | V55: =T55-U55 -> 1 | W55: =COUNTIFS(Prerequisites[Run ID], $B55, Prerequisites[Type], "soft") -> 0 | X55: =COUNTIFS(Prerequisites[Run ID], $B55, Prerequisites[Type], "soft", Prerequisites[Satisfied], TRUE) -> 0 | Y55: =W55-X55 -> 0 | Z55: =COUNTIFS(Prerequisites[Prereq Run ID],$B55,Prerequisites[Type], "hard") -> 1 | AA55: =COUNTIFS(Reading_Order[Run ID], $B55, Reading_Order[Completed], TRUE) -> 0 | AB55: =$G55-$AA55 -> 35 | AC55: =AA55/(AB55+AA55) -> 0 | AD55: =IF(T55<1, TRUE, FALSE) -> FALSE
A56: Warlock on Counter Earth | B56: warlock-counter-earth | C56: Cosmic | D56: Roy Thomas | F56: Marvel Premier #1-2; Warlock #1-8; Incredible Hulk #176;178 | G56: =COUNTIF(Reading_Order[Run ID], B56) -> 20 | H56: 1972 | I56: 1974 | J56: =$G56>0 -> TRUE | K56: =IF($G56=0,"—",IF($AA56=$G56,"read",IF($AA56>0,"reading","unread"))) -> unread | L56: 3 | M56: Adam Warlock's origin — hard gate for the Starlin block | O56: 1 | P56: 2 | Q56: TRUE | S56: =IF($V56>0, "blocked", IF($Y56=0, "ready-all", "ready-hard")) -> blocked | T56: =COUNTIFS(Prerequisites[Run ID], $B56, Prerequisites[Type], "hard") -> 1 | U56: =COUNTIFS(Prerequisites[Run ID], $B56, Prerequisites[Type], "hard", Prerequisites[Satisfied], TRUE) -> 0 | V56: =T56-U56 -> 1 | W56: =COUNTIFS(Prerequisites[Run ID], $B56, Prerequisites[Type], "soft") -> 2 | X56: =COUNTIFS(Prerequisites[Run ID], $B56, Prerequisites[Type], "soft", Prerequisites[Satisfied], TRUE) -> 0 | Y56: =W56-X56 -> 2 | Z56: =COUNTIFS(Prerequisites[Prereq Run ID],$B56,Prerequisites[Type], "hard") -> 1 | AA56: =COUNTIFS(Reading_Order[Run ID], $B56, Reading_Order[Completed], TRUE) -> 0 | AB56: =$G56-$AA56 -> 20 | AC56: =AA56/(AB56+AA56) -> 0 | AD56: =IF(T56<1, TRUE, FALSE) -> FALSE
A57: Death of Captain Marvel | B57: death-of-captain-marvel | C57: Cosmic | D57: Jim Starlin | F57: Iron Man #55; Captain Marvel #25-34; Marvel Feature #12; Daredevil #105-107; Avengers #125, Annual 7/1977; Marvel Team-Up #55; Strange Tales #178-181; Warlock #9-15; Marvel Two-in-One Annual 2/1977; Doctor Strange (1974) #24-26; Marvel Graphic Novel #1: The Death of Captain Marvel | G57: =COUNTIF(Reading_Order[Run ID], B57) -> 31 | H57: 1973 | I57: 1982 | J57: =$G57>0 -> TRUE | K57: =IF($G57=0,"—",IF($AA57=$G57,"read",IF($AA57>0,"reading","unread"))) -> unread | L57: 3 | M57: Thanos, Death, Warlock and Drax all established here | O57: 1 | P57: 3 | Q57: TRUE | S57: =IF($V57>0, "blocked", IF($Y57=0, "ready-all", "ready-hard")) -> blocked | T57: =COUNTIFS(Prerequisites[Run ID], $B57, Prerequisites[Type], "hard") -> 1 | U57: =COUNTIFS(Prerequisites[Run ID], $B57, Prerequisites[Type], "hard", Prerequisites[Satisfied], TRUE) -> 0 | V57: =T57-U57 -> 1 | W57: =COUNTIFS(Prerequisites[Run ID], $B57, Prerequisites[Type], "soft") -> 0 | X57: =COUNTIFS(Prerequisites[Run ID], $B57, Prerequisites[Type], "soft", Prerequisites[Satisfied], TRUE) -> 0 | Y57: =W57-X57 -> 0 | Z57: =COUNTIFS(Prerequisites[Prereq Run ID],$B57,Prerequisites[Type], "hard") -> 1 | AA57: =COUNTIFS(Reading_Order[Run ID], $B57, Reading_Order[Completed], TRUE) -> 0 | AB57: =$G57-$AA57 -> 31 | AC57: =AA57/(AB57+AA57) -> 0 | AD57: =IF(T57<1, TRUE, FALSE) -> FALSE
A58: Engleheart's Silver Surfer | B58: englehart-silver-surfer | C58: Cosmic | D58: Steve Englehart | G58: =COUNTIF(Reading_Order[Run ID], B58) -> 31 | J58: =$G58>0 -> TRUE | K58: =IF($G58=0,"—",IF($AA58=$G58,"read",IF($AA58>0,"reading","unread"))) -> unread | O58: 1 | P58: 4 | Q58: FALSE | S58: =IF($V58>0, "blocked", IF($Y58=0, "ready-all", "ready-hard")) -> blocked | T58: =COUNTIFS(Prerequisites[Run ID], $B58, Prerequisites[Type], "hard") -> 1 | U58: =COUNTIFS(Prerequisites[Run ID], $B58, Prerequisites[Type], "hard", Prerequisites[Satisfied], TRUE) -> 0 | V58: =T58-U58 -> 1 | W58: =COUNTIFS(Prerequisites[Run ID], $B58, Prerequisites[Type], "soft") -> 0 | X58: =COUNTIFS(Prerequisites[Run ID], $B58, Prerequisites[Type], "soft", Prerequisites[Satisfied], TRUE) -> 0 | Y58: =W58-X58 -> 0 | Z58: =COUNTIFS(Prerequisites[Prereq Run ID],$B58,Prerequisites[Type], "hard") -> 1 | AA58: =COUNTIFS(Reading_Order[Run ID], $B58, Reading_Order[Completed], TRUE) -> 0 | AB58: =$G58-$AA58 -> 31 | AC58: =AA58/(AB58+AA58) -> 0 | AD58: =IF(T58<1, TRUE, FALSE) -> FALSE
A59: Infinity Gauntlet | B59: infinity-gauntlet | C59: Cosmic | D59: Jim Starlin | F59: Silver Surfer (1987) #34-50; Thanos Quest #1-2; Infinity Gauntlet #1-6; Warlock and the Infinity Watch #1-7 | G59: =COUNTIF(Reading_Order[Run ID], B59) -> 31 | H59: 1990 | I59: 1992 | J59: =$G59>0 -> TRUE | K59: =IF($G59=0,"—",IF($AA59=$G59,"read",IF($AA59>0,"reading","unread"))) -> unread | L59: 3 | M59: The one everyone has heard of, and it holds up | O59: 1 | P59: 5 | Q59: TRUE | S59: =IF($V59>0, "blocked", IF($Y59=0, "ready-all", "ready-hard")) -> blocked | T59: =COUNTIFS(Prerequisites[Run ID], $B59, Prerequisites[Type], "hard") -> 1 | U59: =COUNTIFS(Prerequisites[Run ID], $B59, Prerequisites[Type], "hard", Prerequisites[Satisfied], TRUE) -> 0 | V59: =T59-U59 -> 1 | W59: =COUNTIFS(Prerequisites[Run ID], $B59, Prerequisites[Type], "soft") -> 2 | X59: =COUNTIFS(Prerequisites[Run ID], $B59, Prerequisites[Type], "soft", Prerequisites[Satisfied], TRUE) -> 0 | Y59: =W59-X59 -> 2 | Z59: =COUNTIFS(Prerequisites[Prereq Run ID],$B59,Prerequisites[Type], "hard") -> 2 | AA59: =COUNTIFS(Reading_Order[Run ID], $B59, Reading_Order[Completed], TRUE) -> 0 | AB59: =$G59-$AA59 -> 31 | AC59: =AA59/(AB59+AA59) -> 0 | AD59: =IF(T59<1, TRUE, FALSE) -> FALSE
A60: Infinity War | B60: infinity-war | C60: Cosmic | D60: Jim Starlin | F60: Infinity War #1-6; Warlock and the Infinity Watch #8-17; Silver Surfer/Warlock: Resurrection #1-4 | G60: =COUNTIF(Reading_Order[Run ID], B60) -> 21 | H60: 1992 | I60: 1993 | J60: =$G60>0 -> TRUE | K60: =IF($G60=0,"—",IF($AA60=$G60,"read",IF($AA60>0,"reading","unread"))) -> unread | L60: 4 | M60: Diminishing returns, but the Warlock material stays good | O60: 1 | P60: 6 | Q60: FALSE | S60: =IF($V60>0, "blocked", IF($Y60=0, "ready-all", "ready-hard")) -> blocked | T60: =COUNTIFS(Prerequisites[Run ID], $B60, Prerequisites[Type], "hard") -> 1 | U60: =COUNTIFS(Prerequisites[Run ID], $B60, Prerequisites[Type], "hard", Prerequisites[Satisfied], TRUE) -> 0 | V60: =T60-U60 -> 1 | W60: =COUNTIFS(Prerequisites[Run ID], $B60, Prerequisites[Type], "soft") -> 0 | X60: =COUNTIFS(Prerequisites[Run ID], $B60, Prerequisites[Type], "soft", Prerequisites[Satisfied], TRUE) -> 0 | Y60: =W60-X60 -> 0 | Z60: =COUNTIFS(Prerequisites[Prereq Run ID],$B60,Prerequisites[Type], "hard") -> 1 | AA60: =COUNTIFS(Reading_Order[Run ID], $B60, Reading_Order[Completed], TRUE) -> 0 | AB60: =$G60-$AA60 -> 21 | AC60: =AA60/(AB60+AA60) -> 0 | AD60: =IF(T60<1, TRUE, FALSE) -> FALSE
A61: Infinity Crusade | B61: infinity-crusade | C61: Cosmic | D61: Jim Starlin | F61: Infinity Crusade #1-6; Warlock Chronicles #1-8; Warlock and the Infinity Watch #18-42 | G61: =COUNTIF(Reading_Order[Run ID], B61) -> 39 | H61: 1993 | I61: 1995 | J61: =$G61>0 -> TRUE | K61: =IF($G61=0,"—",IF($AA61=$G61,"read",IF($AA61>0,"reading","unread"))) -> unread | L61: 4 | M61: Completists only | O61: 1 | P61: 7 | Q61: FALSE | S61: =IF($V61>0, "blocked", IF($Y61=0, "ready-all", "ready-hard")) -> blocked | T61: =COUNTIFS(Prerequisites[Run ID], $B61, Prerequisites[Type], "hard") -> 1 | U61: =COUNTIFS(Prerequisites[Run ID], $B61, Prerequisites[Type], "hard", Prerequisites[Satisfied], TRUE) -> 0 | V61: =T61-U61 -> 1 | W61: =COUNTIFS(Prerequisites[Run ID], $B61, Prerequisites[Type], "soft") -> 0 | X61: =COUNTIFS(Prerequisites[Run ID], $B61, Prerequisites[Type], "soft", Prerequisites[Satisfied], TRUE) -> 0 | Y61: =W61-X61 -> 0 | Z61: =COUNTIFS(Prerequisites[Prereq Run ID],$B61,Prerequisites[Type], "hard") -> 1 | AA61: =COUNTIFS(Reading_Order[Run ID], $B61, Reading_Order[Completed], TRUE) -> 0 | AB61: =$G61-$AA61 -> 39 | AC61: =AA61/(AB61+AA61) -> 0 | AD61: =IF(T61<1, TRUE, FALSE) -> FALSE
A62: Infinity Epilogue | B62: infinity-epilogue | C62: Cosmic | D62: Jim Starlin | F62: Infinity Abyss #1-6; Marvel: The End #1-6; Thanos #1-6 | G62: =COUNTIF(Reading_Order[Run ID], B62) -> 18 | H62: 2002 | I62: 2004 | J62: =$G62>0 -> TRUE | K62: =IF($G62=0,"—",IF($AA62=$G62,"read",IF($AA62>0,"reading","unread"))) -> unread | L62: 4 | M62: Starlin's late-period return | O62: 1 | P62: 8 | Q62: FALSE | S62: =IF($V62>0, "blocked", IF($Y62=0, "ready-all", "ready-hard")) -> blocked | T62: =COUNTIFS(Prerequisites[Run ID], $B62, Prerequisites[Type], "hard") -> 1 | U62: =COUNTIFS(Prerequisites[Run ID], $B62, Prerequisites[Type], "hard", Prerequisites[Satisfied], TRUE) -> 0 | V62: =T62-U62 -> 1 | W62: =COUNTIFS(Prerequisites[Run ID], $B62, Prerequisites[Type], "soft") -> 0 | X62: =COUNTIFS(Prerequisites[Run ID], $B62, Prerequisites[Type], "soft", Prerequisites[Satisfied], TRUE) -> 0 | Y62: =W62-X62 -> 0 | Z62: =COUNTIFS(Prerequisites[Prereq Run ID],$B62,Prerequisites[Type], "hard") -> 1 | AA62: =COUNTIFS(Reading_Order[Run ID], $B62, Reading_Order[Completed], TRUE) -> 0 | AB62: =$G62-$AA62 -> 18 | AC62: =AA62/(AB62+AA62) -> 0 | AD62: =IF(T62<1, TRUE, FALSE) -> FALSE
A63: Annihilation | B63: annihilation | C63: Cosmic | D63: Keith Giffen, Dan Abnett, Andy Lanning | E63: Various | F63: Thanos #1-12; Drax the Destroyer #1-4; Annihilation: Prologue; Annihilation: Nova #1-4; Annihilation: Ronan #1-4; Annihilation: Silver Surfer #1-4; Annihilation: Super-Skrull #1-4; Annihilation #1-6; Annihilation: Heralds of Galactus #1-2; What If? Annihilation Reached Earth; Nova (2007) #1-3 | G63: =COUNTIF(Reading_Order[Run ID], B63) -> 38 | H63: 2003 | I63: 2007 | J63: =$G63>0 -> TRUE | K63: =IF($G63=0,"—",IF($AA63=$G63,"read",IF($AA63>0,"reading","unread"))) -> unread | L63: 3 | M63: Where the modern cosmic line actually starts | O63: 2 | P63: 1 | Q63: TRUE | S63: =IF($V63>0, "blocked", IF($Y63=0, "ready-all", "ready-hard")) -> ready-hard | T63: =COUNTIFS(Prerequisites[Run ID], $B63, Prerequisites[Type], "hard") -> 0 | U63: =COUNTIFS(Prerequisites[Run ID], $B63, Prerequisites[Type], "hard", Prerequisites[Satisfied], TRUE) -> 0 | V63: =T63-U63 -> 0 | W63: =COUNTIFS(Prerequisites[Run ID], $B63, Prerequisites[Type], "soft") -> 2 | X63: =COUNTIFS(Prerequisites[Run ID], $B63, Prerequisites[Type], "soft", Prerequisites[Satisfied], TRUE) -> 0 | Y63: =W63-X63 -> 2 | Z63: =COUNTIFS(Prerequisites[Prereq Run ID],$B63,Prerequisites[Type], "hard") -> 2 | AA63: =COUNTIFS(Reading_Order[Run ID], $B63, Reading_Order[Completed], TRUE) -> 0 | AB63: =$G63-$AA63 -> 38 | AC63: =AA63/(AB63+AA63) -> 0 | AD63: =IF(T63<1, TRUE, FALSE) -> TRUE
A64: Pre-Annihilators | B64: pre-annihilators | C64: Cosmic | D64: Michael Avon Oeming, Daniel Berman | F64: Silver Surfer (2003) #1-6; Stormbreaker: The Saga of Beta Ray Bill #1-6; Silver Surfer: Requiem #1-4; Silver Surfer: In Thy Name #1-4; Beta Ray Bill: Godhunter #1-3; Secret Invasion Aftermath: Beta Ray Bill — The Green of Eden; Silver Surfer (2011) #1-3 | G64: =COUNTIF(Reading_Order[Run ID], B64) -> 14 | H64: 2003 | I64: 2007 | J64: =$G64>0 -> TRUE | K64: =IF($G64=0,"—",IF($AA64=$G64,"read",IF($AA64>0,"reading","unread"))) -> unread | L64: 4 | M64: Requiem in particular is a small masterpiece | O64: 2 | P64: 2 | Q64: FALSE | S64: =IF($V64>0, "blocked", IF($Y64=0, "ready-all", "ready-hard")) -> blocked | T64: =COUNTIFS(Prerequisites[Run ID], $B64, Prerequisites[Type], "hard") -> 1 | U64: =COUNTIFS(Prerequisites[Run ID], $B64, Prerequisites[Type], "hard", Prerequisites[Satisfied], TRUE) -> 0 | V64: =T64-U64 -> 1 | W64: =COUNTIFS(Prerequisites[Run ID], $B64, Prerequisites[Type], "soft") -> 3 | X64: =COUNTIFS(Prerequisites[Run ID], $B64, Prerequisites[Type], "soft", Prerequisites[Satisfied], TRUE) -> 0 | Y64: =W64-X64 -> 3 | Z64: =COUNTIFS(Prerequisites[Prereq Run ID],$B64,Prerequisites[Type], "hard") -> 1 | AA64: =COUNTIFS(Reading_Order[Run ID], $B64, Reading_Order[Completed], TRUE) -> 0 | AB64: =$G64-$AA64 -> 14 | AC64: =AA64/(AB64+AA64) -> 0 | AD64: =IF(T64<1, TRUE, FALSE) -> FALSE
A65: Annihilation: Conquest | B65: annihilation-conquest | C65: Cosmic | D65: Dan Abnett, Andy Lanning | E65: Various | F65: Annihilation: Saga; Annihilation: Conquest — Prologue; Annihilation: Conquest — Quasar #1-4; Annihilation: Conquest — Star-Lord #1-4; Annihilation: Conquest — Wraith #1-4; Annihilation: Conquest #1-6; Nova (2007) #4-22, Annual 1/2008; Guardians of the Galaxy (2008) #1-7 | G65: =COUNTIF(Reading_Order[Run ID], B65) -> 47 | H65: 2007 | I65: 2008 | J65: =$G65>0 -> TRUE | K65: =IF($G65=0,"—",IF($AA65=$G65,"read",IF($AA65>0,"reading","unread"))) -> unread | L65: 3 | M65: Assembles the Guardians as we now know them | O65: 2 | P65: 3 | Q65: TRUE | S65: =IF($V65>0, "blocked", IF($Y65=0, "ready-all", "ready-hard")) -> blocked | T65: =COUNTIFS(Prerequisites[Run ID], $B65, Prerequisites[Type], "hard") -> 2 | U65: =COUNTIFS(Prerequisites[Run ID], $B65, Prerequisites[Type], "hard", Prerequisites[Satisfied], TRUE) -> 0 | V65: =T65-U65 -> 2 | W65: =COUNTIFS(Prerequisites[Run ID], $B65, Prerequisites[Type], "soft") -> 0 | X65: =COUNTIFS(Prerequisites[Run ID], $B65, Prerequisites[Type], "soft", Prerequisites[Satisfied], TRUE) -> 0 | Y65: =W65-X65 -> 0 | Z65: =COUNTIFS(Prerequisites[Prereq Run ID],$B65,Prerequisites[Type], "hard") -> 2 | AA65: =COUNTIFS(Reading_Order[Run ID], $B65, Reading_Order[Completed], TRUE) -> 0 | AB65: =$G65-$AA65 -> 47 | AC65: =AA65/(AB65+AA65) -> 0 | AD65: =IF(T65<1, TRUE, FALSE) -> FALSE
A66: War of Kings | B66: war-of-kings | C66: Cosmic | D66: Dan Abnett, Andy Lanning | E66: Paul Pelletier | F66: The Uncanny X-Men #475-478; X-Men: Emperor Vulcan #1-5; Secret Invasion: Inhumans #1-4; Secret Invasion: War of Kings; War of Kings Saga; X-Men: Kingbreaker #1-4; War of Kings #1-6; War of Kings: Darkhawk #1-2; War of Kings: Savage World of Skaar; War of Kings: Warriors #1-2; War of Kings: Ascension #1-4; War of Kings: Who Will Rule?; Guardians of the Galaxy (2008) #8-19; Nova (2007) #23-31 | G66: =COUNTIF(Reading_Order[Run ID], B66) -> 52 | H66: 2009 | I66: 2009 | J66: =$G66>0 -> TRUE | K66: =IF($G66=0,"—",IF($AA66=$G66,"read",IF($AA66>0,"reading","unread"))) -> unread | L66: 3 | M66: Inhumans vs Shi'ar; needs Rise and Fall of the Shi'ar Empire | O66: 2 | P66: 4 | Q66: TRUE | S66: =IF($V66>0, "blocked", IF($Y66=0, "ready-all", "ready-hard")) -> blocked | T66: =COUNTIFS(Prerequisites[Run ID], $B66, Prerequisites[Type], "hard") -> 2 | U66: =COUNTIFS(Prerequisites[Run ID], $B66, Prerequisites[Type], "hard", Prerequisites[Satisfied], TRUE) -> 0 | V66: =T66-U66 -> 2 | W66: =COUNTIFS(Prerequisites[Run ID], $B66, Prerequisites[Type], "soft") -> 2 | X66: =COUNTIFS(Prerequisites[Run ID], $B66, Prerequisites[Type], "soft", Prerequisites[Satisfied], TRUE) -> 0 | Y66: =W66-X66 -> 2 | Z66: =COUNTIFS(Prerequisites[Prereq Run ID],$B66,Prerequisites[Type], "hard") -> 2 | AA66: =COUNTIFS(Reading_Order[Run ID], $B66, Reading_Order[Completed], TRUE) -> 0 | AB66: =$G66-$AA66 -> 52 | AC66: =AA66/(AB66+AA66) -> 0 | AD66: =IF(T66<1, TRUE, FALSE) -> FALSE
A67: Realm of Kings | B67: realm-of-kings | C67: Cosmic | D67: Dan Abnett, Andy Lanning | F67: Realm of Kings; Realm of Kings: Imperial Guard #1-5; Realm of Kings: Inhumans #1-5; Realm of Kings: Son of Hulk #1-4; Guardians of the Galaxy (2008) #20-25; Nova (2007) #32-36 | G67: =COUNTIF(Reading_Order[Run ID], B67) -> 26 | H67: 2009 | I67: 2010 | J67: =$G67>0 -> TRUE | K67: =IF($G67=0,"—",IF($AA67=$G67,"read",IF($AA67>0,"reading","unread"))) -> unread | L67: 3 | M67: The Cancerverse arrives | O67: 2 | P67: 5 | Q67: TRUE | S67: =IF($V67>0, "blocked", IF($Y67=0, "ready-all", "ready-hard")) -> blocked | T67: =COUNTIFS(Prerequisites[Run ID], $B67, Prerequisites[Type], "hard") -> 1 | U67: =COUNTIFS(Prerequisites[Run ID], $B67, Prerequisites[Type], "hard", Prerequisites[Satisfied], TRUE) -> 0 | V67: =T67-U67 -> 1 | W67: =COUNTIFS(Prerequisites[Run ID], $B67, Prerequisites[Type], "soft") -> 0 | X67: =COUNTIFS(Prerequisites[Run ID], $B67, Prerequisites[Type], "soft", Prerequisites[Satisfied], TRUE) -> 0 | Y67: =W67-X67 -> 0 | Z67: =COUNTIFS(Prerequisites[Prereq Run ID],$B67,Prerequisites[Type], "hard") -> 1 | AA67: =COUNTIFS(Reading_Order[Run ID], $B67, Reading_Order[Completed], TRUE) -> 0 | AB67: =$G67-$AA67 -> 26 | AC67: =AA67/(AB67+AA67) -> 0 | AD67: =IF(T67<1, TRUE, FALSE) -> FALSE
A68: The Thanos Imperative | B68: thanos-imperative | C68: Cosmic | D68: Dan Abnett, Andy Lanning | E68: Miguel Sepulveda | F68: The Thanos Imperative: Ignition; The Thanos Imperative #1-6; The Thanos Imperative: Devastation | G68: =COUNTIF(Reading_Order[Run ID], B68) -> 8 | H68: 2010 | I68: 2011 | J68: =$G68>0 -> TRUE | K68: =IF($G68=0,"—",IF($AA68=$G68,"read",IF($AA68>0,"reading","unread"))) -> unread | L68: 3 | M68: The end of the whole DnA saga, and a genuinely earned ending | O68: 2 | P68: 6 | Q68: TRUE | S68: =IF($V68>0, "blocked", IF($Y68=0, "ready-all", "ready-hard")) -> blocked | T68: =COUNTIFS(Prerequisites[Run ID], $B68, Prerequisites[Type], "hard") -> 1 | U68: =COUNTIFS(Prerequisites[Run ID], $B68, Prerequisites[Type], "hard", Prerequisites[Satisfied], TRUE) -> 0 | V68: =T68-U68 -> 1 | W68: =COUNTIFS(Prerequisites[Run ID], $B68, Prerequisites[Type], "soft") -> 1 | X68: =COUNTIFS(Prerequisites[Run ID], $B68, Prerequisites[Type], "soft", Prerequisites[Satisfied], TRUE) -> 0 | Y68: =W68-X68 -> 1 | Z68: =COUNTIFS(Prerequisites[Prereq Run ID],$B68,Prerequisites[Type], "hard") -> 1 | AA68: =COUNTIFS(Reading_Order[Run ID], $B68, Reading_Order[Completed], TRUE) -> 0 | AB68: =$G68-$AA68 -> 8 | AC68: =AA68/(AB68+AA68) -> 0 | AD68: =IF(T68<1, TRUE, FALSE) -> FALSE
A69: The Annihilators | B69: annihilators | C69: Cosmic | D69: Dan Abnett, Andy Lanning | F69: Annihilators #1-4; Annihilators: Earthfall #1-4 | G69: =COUNTIF(Reading_Order[Run ID], B69) -> 8 | H69: 2011 | I69: 2012 | J69: =$G69>0 -> TRUE | K69: =IF($G69=0,"—",IF($AA69=$G69,"read",IF($AA69>0,"reading","unread"))) -> unread | L69: 4 | M69: The coda to the DnA era | O69: 2 | P69: 7 | Q69: FALSE | S69: =IF($V69>0, "blocked", IF($Y69=0, "ready-all", "ready-hard")) -> blocked | T69: =COUNTIFS(Prerequisites[Run ID], $B69, Prerequisites[Type], "hard") -> 1 | U69: =COUNTIFS(Prerequisites[Run ID], $B69, Prerequisites[Type], "hard", Prerequisites[Satisfied], TRUE) -> 0 | V69: =T69-U69 -> 1 | W69: =COUNTIFS(Prerequisites[Run ID], $B69, Prerequisites[Type], "soft") -> 0 | X69: =COUNTIFS(Prerequisites[Run ID], $B69, Prerequisites[Type], "soft", Prerequisites[Satisfied], TRUE) -> 0 | Y69: =W69-X69 -> 0 | Z69: =COUNTIFS(Prerequisites[Prereq Run ID],$B69,Prerequisites[Type], "hard") -> 0 | AA69: =COUNTIFS(Reading_Order[Run ID], $B69, Reading_Order[Completed], TRUE) -> 0 | AB69: =$G69-$AA69 -> 8 | AC69: =AA69/(AB69+AA69) -> 0 | AD69: =IF(T69<1, TRUE, FALSE) -> FALSE
A70: Infinity Finale | B70: infinity-finale | C70: Cosmic | D70: Jim Starlin | F70: Thanos: The Infinity Revelation OGN; Thanos vs. Hulk #1-4; Thanos: The Infinity Relativity OGN; The Infinity Entity #1-4; Thanos: The Infinity Finale OGN; Thanos: The Infinity Siblings OGN; Thanos: The Infinity Conflict OGN; Thanos: The Infinity Ending OGN | G70: =COUNTIF(Reading_Order[Run ID], B70) -> 20 | H70: 2014 | I70: 2019 | J70: =$G70>0 -> TRUE | K70: =IF($G70=0,"—",IF($AA70=$G70,"read",IF($AA70>0,"reading","unread"))) -> unread | L70: 4 | M70: The OGN cycle nobody read | O70: 1 | P70: 9 | Q70: FALSE | S70: =IF($V70>0, "blocked", IF($Y70=0, "ready-all", "ready-hard")) -> blocked | T70: =COUNTIFS(Prerequisites[Run ID], $B70, Prerequisites[Type], "hard") -> 1 | U70: =COUNTIFS(Prerequisites[Run ID], $B70, Prerequisites[Type], "hard", Prerequisites[Satisfied], TRUE) -> 0 | V70: =T70-U70 -> 1 | W70: =COUNTIFS(Prerequisites[Run ID], $B70, Prerequisites[Type], "soft") -> 0 | X70: =COUNTIFS(Prerequisites[Run ID], $B70, Prerequisites[Type], "soft", Prerequisites[Satisfied], TRUE) -> 0 | Y70: =W70-X70 -> 0 | Z70: =COUNTIFS(Prerequisites[Prereq Run ID],$B70,Prerequisites[Type], "hard") -> 0 | AA70: =COUNTIFS(Reading_Order[Run ID], $B70, Reading_Order[Completed], TRUE) -> 0 | AB70: =$G70-$AA70 -> 20 | AC70: =AA70/(AB70+AA70) -> 0 | AD70: =IF(T70<1, TRUE, FALSE) -> FALSE
A71: Slott's Silver Surfer | B71: slott-silver-surfer | C71: Cosmic | D71: Dan Slott | F71: Silver Surfer (2014) #1-15 | G71: =COUNTIF(Reading_Order[Run ID], B71) -> 30 | H71: 2014 | I71: 2017 | J71: =$G71>0 -> TRUE | K71: =IF($G71=0,"—",IF($AA71=$G71,"read",IF($AA71>0,"reading","unread"))) -> unread | L71: 4 | M71: Doctor Who with the Silver Surfer, and it earns its ending | O71: 3 | P71: 1 | Q71: TRUE | S71: =IF($V71>0, "blocked", IF($Y71=0, "ready-all", "ready-hard")) -> ready-hard | T71: =COUNTIFS(Prerequisites[Run ID], $B71, Prerequisites[Type], "hard") -> 0 | U71: =COUNTIFS(Prerequisites[Run ID], $B71, Prerequisites[Type], "hard", Prerequisites[Satisfied], TRUE) -> 0 | V71: =T71-U71 -> 0 | W71: =COUNTIFS(Prerequisites[Run ID], $B71, Prerequisites[Type], "soft") -> 2 | X71: =COUNTIFS(Prerequisites[Run ID], $B71, Prerequisites[Type], "soft", Prerequisites[Satisfied], TRUE) -> 0 | Y71: =W71-X71 -> 2 | Z71: =COUNTIFS(Prerequisites[Prereq Run ID],$B71,Prerequisites[Type], "hard") -> 0 | AA71: =COUNTIFS(Reading_Order[Run ID], $B71, Reading_Order[Completed], TRUE) -> 0 | AB71: =$G71-$AA71 -> 30 | AC71: =AA71/(AB71+AA71) -> 0 | AD71: =IF(T71<1, TRUE, FALSE) -> TRUE
A72: Cates' Thanos/Guardians | B72: cates-thanos | C72: Cosmic | D72: Donny Cates | F72: Thanos (2016) #1-18, Annual 1/2018; Cosmic Ghost Rider #1-5; Thanos Legacy; Guardians of the Galaxy (2019) #1-12, Annual 1/2019; Revenge of the Cosmic Ghost Rider #1-5 | G72: =COUNTIF(Reading_Order[Run ID], B72) -> 44 | H72: 2016 | I72: 2020 | J72: =$G72>0 -> TRUE | K72: =IF($G72=0,"—",IF($AA72=$G72,"read",IF($AA72>0,"reading","unread"))) -> unread | L72: 3 | M72: TARGET — and it has zero hard prerequisites | O72: 4 | P72: 1 | Q72: FALSE | S72: =IF($V72>0, "blocked", IF($Y72=0, "ready-all", "ready-hard")) -> ready-hard | T72: =COUNTIFS(Prerequisites[Run ID], $B72, Prerequisites[Type], "hard") -> 0 | U72: =COUNTIFS(Prerequisites[Run ID], $B72, Prerequisites[Type], "hard", Prerequisites[Satisfied], TRUE) -> 0 | V72: =T72-U72 -> 0 | W72: =COUNTIFS(Prerequisites[Run ID], $B72, Prerequisites[Type], "soft") -> 3 | X72: =COUNTIFS(Prerequisites[Run ID], $B72, Prerequisites[Type], "soft", Prerequisites[Satisfied], TRUE) -> 0 | Y72: =W72-X72 -> 3 | Z72: =COUNTIFS(Prerequisites[Prereq Run ID],$B72,Prerequisites[Type], "hard") -> 1 | AA72: =COUNTIFS(Reading_Order[Run ID], $B72, Reading_Order[Completed], TRUE) -> 0 | AB72: =$G72-$AA72 -> 44 | AC72: =AA72/(AB72+AA72) -> 0 | AD72: =IF(T72<1, TRUE, FALSE) -> TRUE
A73: Miller's Daredevil | B73: miller-daredevil | C73: Daredevil | D73: Frank Miller | E73: Frank Miller | F73: Daredevil #168-191, #219 | G73: =COUNTIF(Reading_Order[Run ID], B73) -> 44 | H73: 1981 | I73: 1983 | J73: =$G73>0 -> TRUE | K73: =IF($G73=0,"—",IF($AA73=$G73,"read",IF($AA73>0,"reading","unread"))) -> unread | L73: 1 | M73: Highest quality-per-issue in the entire sheet | O73: 1 | P73: 1 | Q73: TRUE | S73: =IF($V73>0, "blocked", IF($Y73=0, "ready-all", "ready-hard")) -> ready-all | T73: =COUNTIFS(Prerequisites[Run ID], $B73, Prerequisites[Type], "hard") -> 0 | U73: =COUNTIFS(Prerequisites[Run ID], $B73, Prerequisites[Type], "hard", Prerequisites[Satisfied], TRUE) -> 0 | V73: =T73-U73 -> 0 | W73: =COUNTIFS(Prerequisites[Run ID], $B73, Prerequisites[Type], "soft") -> 0 | X73: =COUNTIFS(Prerequisites[Run ID], $B73, Prerequisites[Type], "soft", Prerequisites[Satisfied], TRUE) -> 0 | Y73: =W73-X73 -> 0 | Z73: =COUNTIFS(Prerequisites[Prereq Run ID],$B73,Prerequisites[Type], "hard") -> 1 | AA73: =COUNTIFS(Reading_Order[Run ID], $B73, Reading_Order[Completed], TRUE) -> 0 | AB73: =$G73-$AA73 -> 44 | AC73: =AA73/(AB73+AA73) -> 0 | AD73: =IF(T73<1, TRUE, FALSE) -> TRUE
A74: Born Again | B74: born-again | C74: Daredevil | D74: Frank Miller | E74: David Mazzucchelli | F74: Daredevil #226-233 | G74: =COUNTIF(Reading_Order[Run ID], B74) -> 9 | H74: 1986 | I74: 1996 | J74: =$G74>0 -> TRUE | K74: =IF($G74=0,"—",IF($AA74=$G74,"read",IF($AA74>0,"reading","unread"))) -> unread | L74: 2 | M74: The peak of the character, and of Miller | O74: 1 | P74: 2 | Q74: TRUE | S74: =IF($V74>0, "blocked", IF($Y74=0, "ready-all", "ready-hard")) -> blocked | T74: =COUNTIFS(Prerequisites[Run ID], $B74, Prerequisites[Type], "hard") -> 1 | U74: =COUNTIFS(Prerequisites[Run ID], $B74, Prerequisites[Type], "hard", Prerequisites[Satisfied], TRUE) -> 0 | V74: =T74-U74 -> 1 | W74: =COUNTIFS(Prerequisites[Run ID], $B74, Prerequisites[Type], "soft") -> 0 | X74: =COUNTIFS(Prerequisites[Run ID], $B74, Prerequisites[Type], "soft", Prerequisites[Satisfied], TRUE) -> 0 | Y74: =W74-X74 -> 0 | Z74: =COUNTIFS(Prerequisites[Prereq Run ID],$B74,Prerequisites[Type], "hard") -> 1 | AA74: =COUNTIFS(Reading_Order[Run ID], $B74, Reading_Order[Completed], TRUE) -> 0 | AB74: =$G74-$AA74 -> 9 | AC74: =AA74/(AB74+AA74) -> 0 | AD74: =IF(T74<1, TRUE, FALSE) -> FALSE
A75: Miller Coda | B75: miller-dd-coda | C75: Daredevil | D75: Frank Miller | F75: Elektra: Assassin #1-8; Daredevil: Love and War | G75: =COUNTIF(Reading_Order[Run ID], B75) -> 14 | H75: 1986 | I75: 1987 | J75: =$G75>0 -> TRUE | K75: =IF($G75=0,"—",IF($AA75=$G75,"read",IF($AA75>0,"reading","unread"))) -> unread | L75: 3 | M75: Miller and Sienkiewicz completely off the leash | O75: 1 | P75: 3 | Q75: FALSE | S75: =IF($V75>0, "blocked", IF($Y75=0, "ready-all", "ready-hard")) -> blocked | T75: =COUNTIFS(Prerequisites[Run ID], $B75, Prerequisites[Type], "hard") -> 1 | U75: =COUNTIFS(Prerequisites[Run ID], $B75, Prerequisites[Type], "hard", Prerequisites[Satisfied], TRUE) -> 0 | V75: =T75-U75 -> 1 | W75: =COUNTIFS(Prerequisites[Run ID], $B75, Prerequisites[Type], "soft") -> 1 | X75: =COUNTIFS(Prerequisites[Run ID], $B75, Prerequisites[Type], "soft", Prerequisites[Satisfied], TRUE) -> 0 | Y75: =W75-X75 -> 1 | Z75: =COUNTIFS(Prerequisites[Prereq Run ID],$B75,Prerequisites[Type], "hard") -> 0 | AA75: =COUNTIFS(Reading_Order[Run ID], $B75, Reading_Order[Completed], TRUE) -> 0 | AB75: =$G75-$AA75 -> 14 | AC75: =AA75/(AB75+AA75) -> 0 | AD75: =IF(T75<1, TRUE, FALSE) -> FALSE
A76: Nocenti's Daredevil | B76: nocenti-daredevil | C76: Daredevil | D76: Ann Nocenti | E76: John Romita Jr. | F76: Daredevil #236-291 | G76: =COUNTIF(Reading_Order[Run ID], B76) -> 57 | H76: 1986 | I76: 1991 | J76: =$G76>0 -> TRUE | K76: =IF($G76=0,"—",IF($AA76=$G76,"read",IF($AA76>0,"reading","unread"))) -> unread | L76: 3 | M76: The bridge from Miller to Bendis; Typhoid Mary is created here | O76: 2 | P76: 1 | Q76: FALSE | S76: =IF($V76>0, "blocked", IF($Y76=0, "ready-all", "ready-hard")) -> ready-hard | T76: =COUNTIFS(Prerequisites[Run ID], $B76, Prerequisites[Type], "hard") -> 0 | U76: =COUNTIFS(Prerequisites[Run ID], $B76, Prerequisites[Type], "hard", Prerequisites[Satisfied], TRUE) -> 0 | V76: =T76-U76 -> 0 | W76: =COUNTIFS(Prerequisites[Run ID], $B76, Prerequisites[Type], "soft") -> 1 | X76: =COUNTIFS(Prerequisites[Run ID], $B76, Prerequisites[Type], "soft", Prerequisites[Satisfied], TRUE) -> 0 | Y76: =W76-X76 -> 1 | Z76: =COUNTIFS(Prerequisites[Prereq Run ID],$B76,Prerequisites[Type], "hard") -> 0 | AA76: =COUNTIFS(Reading_Order[Run ID], $B76, Reading_Order[Completed], TRUE) -> 0 | AB76: =$G76-$AA76 -> 57 | AC76: =AA76/(AB76+AA76) -> 0 | AD76: =IF(T76<1, TRUE, FALSE) -> TRUE
A77: Daredevil - Guardian Devil | B77: smith-dd | C77: Daredevil | D77: Kevin Smith | E77: Joe Quesada | F77: Daredevil (1998) #1-8 | G77: =COUNTIF(Reading_Order[Run ID], B77) -> 8 | H77: 1998 | I77: 1999 | J77: =$G77>0 -> TRUE | K77: =IF($G77=0,"—",IF($AA77=$G77,"read",IF($AA77>0,"reading","unread"))) -> unread | L77: 2 | M77: The Marvel Knights relaunch; required setup for Bendis | O77: 3 | P77: 1 | Q77: TRUE | S77: =IF($V77>0, "blocked", IF($Y77=0, "ready-all", "ready-hard")) -> ready-hard | T77: =COUNTIFS(Prerequisites[Run ID], $B77, Prerequisites[Type], "hard") -> 0 | U77: =COUNTIFS(Prerequisites[Run ID], $B77, Prerequisites[Type], "hard", Prerequisites[Satisfied], TRUE) -> 0 | V77: =T77-U77 -> 0 | W77: =COUNTIFS(Prerequisites[Run ID], $B77, Prerequisites[Type], "soft") -> 2 | X77: =COUNTIFS(Prerequisites[Run ID], $B77, Prerequisites[Type], "soft", Prerequisites[Satisfied], TRUE) -> 0 | Y77: =W77-X77 -> 2 | Z77: =COUNTIFS(Prerequisites[Prereq Run ID],$B77,Prerequisites[Type], "hard") -> 2 | AA77: =COUNTIFS(Reading_Order[Run ID], $B77, Reading_Order[Completed], TRUE) -> 0 | AB77: =$G77-$AA77 -> 8 | AC77: =AA77/(AB77+AA77) -> 0 | AD77: =IF(T77<1, TRUE, FALSE) -> TRUE
A78: Daredevil: Yellow | B78: daredevil-yellow | C78: Daredevil | D78: Jeph Loeb | F78: Daredevil: Yellow #1-6 | G78: =COUNTIF(Reading_Order[Run ID], B78) -> 6 | J78: =$G78>0 -> TRUE | K78: =IF($G78=0,"—",IF($AA78=$G78,"read",IF($AA78>0,"reading","unread"))) -> unread | O78: 3 | P78: 2 | Q78: FALSE | S78: =IF($V78>0, "blocked", IF($Y78=0, "ready-all", "ready-hard")) -> blocked | T78: =COUNTIFS(Prerequisites[Run ID], $B78, Prerequisites[Type], "hard") -> 1 | U78: =COUNTIFS(Prerequisites[Run ID], $B78, Prerequisites[Type], "hard", Prerequisites[Satisfied], TRUE) -> 0 | V78: =T78-U78 -> 1 | W78: =COUNTIFS(Prerequisites[Run ID], $B78, Prerequisites[Type], "soft") -> 0 | X78: =COUNTIFS(Prerequisites[Run ID], $B78, Prerequisites[Type], "soft", Prerequisites[Satisfied], TRUE) -> 0 | Y78: =W78-X78 -> 0 | Z78: =COUNTIFS(Prerequisites[Prereq Run ID],$B78,Prerequisites[Type], "hard") -> 0 | AA78: =COUNTIFS(Reading_Order[Run ID], $B78, Reading_Order[Completed], TRUE) -> 0 | AB78: =$G78-$AA78 -> 6 | AC78: =AA78/(AB78+AA78) -> 0 | AD78: =IF(T78<1, TRUE, FALSE) -> FALSE
A79: Daredevil - Parts of a Hole | B79: mack-dd | C79: Daredevil | D79: David Mack | F79: Daredevil (1998) #9-15 | G79: =COUNTIF(Reading_Order[Run ID], B79) -> 7 | H79: 1999 | I79: 2001 | J79: =$G79>0 -> TRUE | K79: =IF($G79=0,"—",IF($AA79=$G79,"read",IF($AA79>0,"reading","unread"))) -> unread | L79: 2 | M79: Echo's introduction | O79: 3 | P79: 3 | Q79: TRUE | S79: =IF($V79>0, "blocked", IF($Y79=0, "ready-all", "ready-hard")) -> blocked | T79: =COUNTIFS(Prerequisites[Run ID], $B79, Prerequisites[Type], "hard") -> 2 | U79: =COUNTIFS(Prerequisites[Run ID], $B79, Prerequisites[Type], "hard", Prerequisites[Satisfied], TRUE) -> 0 | V79: =T79-U79 -> 2 | W79: =COUNTIFS(Prerequisites[Run ID], $B79, Prerequisites[Type], "soft") -> 0 | X79: =COUNTIFS(Prerequisites[Run ID], $B79, Prerequisites[Type], "soft", Prerequisites[Satisfied], TRUE) -> 0 | Y79: =W79-X79 -> 0 | Z79: =COUNTIFS(Prerequisites[Prereq Run ID],$B79,Prerequisites[Type], "hard") -> 0 | AA79: =COUNTIFS(Reading_Order[Run ID], $B79, Reading_Order[Completed], TRUE) -> 0 | AB79: =$G79-$AA79 -> 7 | AC79: =AA79/(AB79+AA79) -> 0 | AD79: =IF(T79<1, TRUE, FALSE) -> FALSE
A80: Bendis' Daredevil | B80: bendis-daredevil | C80: Daredevil | D80: Brian Michael Bendis | E80: Alex Maleev | F80: Daredevil (1998) #16-81 | G80: =COUNTIF(Reading_Order[Run ID], B80) -> 60 | H80: 2001 | I80: 2006 | J80: =$G80>0 -> TRUE | K80: =IF($G80=0,"—",IF($AA80=$G80,"read",IF($AA80>0,"reading","unread"))) -> unread | L80: 2 | M80: Matt's identity goes public and never recovers | O80: 3 | P80: 4 | Q80: TRUE | S80: =IF($V80>0, "blocked", IF($Y80=0, "ready-all", "ready-hard")) -> ready-hard | T80: =COUNTIFS(Prerequisites[Run ID], $B80, Prerequisites[Type], "hard") -> 0 | U80: =COUNTIFS(Prerequisites[Run ID], $B80, Prerequisites[Type], "hard", Prerequisites[Satisfied], TRUE) -> 0 | V80: =T80-U80 -> 0 | W80: =COUNTIFS(Prerequisites[Run ID], $B80, Prerequisites[Type], "soft") -> 1 | X80: =COUNTIFS(Prerequisites[Run ID], $B80, Prerequisites[Type], "soft", Prerequisites[Satisfied], TRUE) -> 0 | Y80: =W80-X80 -> 1 | Z80: =COUNTIFS(Prerequisites[Prereq Run ID],$B80,Prerequisites[Type], "hard") -> 2 | AA80: =COUNTIFS(Reading_Order[Run ID], $B80, Reading_Order[Completed], TRUE) -> 0 | AB80: =$G80-$AA80 -> 60 | AC80: =AA80/(AB80+AA80) -> 0 | AD80: =IF(T80<1, TRUE, FALSE) -> TRUE
A81: Brubaker's Daredevil | B81: brubaker-daredevil | C81: Daredevil | D81: Ed Brubaker | E81: Michael Lark | F81: Daredevil (1998) #82-119, 500; Daredevil (1998) Annual | G81: =COUNTIF(Reading_Order[Run ID], B81) -> 35 | H81: 2006 | I81: 2009 | J81: =$G81>0 -> TRUE | K81: =IF($G81=0,"—",IF($AA81=$G81,"read",IF($AA81>0,"reading","unread"))) -> unread | L81: 2 | M81: Picks up mid-cliffhanger from Bendis | O81: 3 | P81: 5 | Q81: TRUE | S81: =IF($V81>0, "blocked", IF($Y81=0, "ready-all", "ready-hard")) -> blocked | T81: =COUNTIFS(Prerequisites[Run ID], $B81, Prerequisites[Type], "hard") -> 1 | U81: =COUNTIFS(Prerequisites[Run ID], $B81, Prerequisites[Type], "hard", Prerequisites[Satisfied], TRUE) -> 0 | V81: =T81-U81 -> 1 | W81: =COUNTIFS(Prerequisites[Run ID], $B81, Prerequisites[Type], "soft") -> 0 | X81: =COUNTIFS(Prerequisites[Run ID], $B81, Prerequisites[Type], "soft", Prerequisites[Satisfied], TRUE) -> 0 | Y81: =W81-X81 -> 0 | Z81: =COUNTIFS(Prerequisites[Prereq Run ID],$B81,Prerequisites[Type], "hard") -> 0 | AA81: =COUNTIFS(Reading_Order[Run ID], $B81, Reading_Order[Completed], TRUE) -> 0 | AB81: =$G81-$AA81 -> 35 | AC81: =AA81/(AB81+AA81) -> 0 | AD81: =IF(T81<1, TRUE, FALSE) -> FALSE
A82: Waid's Daredevil | B82: waid-daredevil | C82: Daredevil | D82: Mark Waid | E82: Chris Samnee | F82: Daredevil (2011) #1-36, 10.1; Daredevil (2014) #0.1-18, 1.5, 15.1; Amazing Spider-Man #667; The Punisher (2011) #9; Avenging Spider-Man #6 | G82: =COUNTIF(Reading_Order[Run ID], B82) -> 72 | H82: 2011 | I82: 2015 | J82: =$G82>0 -> TRUE | K82: =IF($G82=0,"—",IF($AA82=$G82,"read",IF($AA82>0,"reading","unread"))) -> unread | L82: 3 | M82: A deliberate clean-slate relaunch that actually works | O82: 4 | P82: 1 | Q82: FALSE | S82: =IF($V82>0, "blocked", IF($Y82=0, "ready-all", "ready-hard")) -> ready-hard | T82: =COUNTIFS(Prerequisites[Run ID], $B82, Prerequisites[Type], "hard") -> 0 | U82: =COUNTIFS(Prerequisites[Run ID], $B82, Prerequisites[Type], "hard", Prerequisites[Satisfied], TRUE) -> 0 | V82: =T82-U82 -> 0 | W82: =COUNTIFS(Prerequisites[Run ID], $B82, Prerequisites[Type], "soft") -> 3 | X82: =COUNTIFS(Prerequisites[Run ID], $B82, Prerequisites[Type], "soft", Prerequisites[Satisfied], TRUE) -> 0 | Y82: =W82-X82 -> 3 | Z82: =COUNTIFS(Prerequisites[Prereq Run ID],$B82,Prerequisites[Type], "hard") -> 1 | AA82: =COUNTIFS(Reading_Order[Run ID], $B82, Reading_Order[Completed], TRUE) -> 0 | AB82: =$G82-$AA82 -> 72 | AC82: =AA82/(AB82+AA82) -> 0 | AD82: =IF(T82<1, TRUE, FALSE) -> TRUE
A83: Soule's Daredevil | B83: soule-daredevil | C83: Daredevil | D83: Charles Soule | F83: Daredevil (2015) #1-28, #595-612; Daredevil (2014) Annual; All-New All Different Point One | G83: =COUNTIF(Reading_Order[Run ID], B83) -> 64 | H83: 2015 | I83: 2018 | J83: =$G83>0 -> TRUE | K83: =IF($G83=0,"—",IF($AA83=$G83,"read",IF($AA83>0,"reading","unread"))) -> unread | L83: 3 | M83: Matt as a prosecutor; the identity genie back in the bottle | O83: 4 | P83: 2 | Q83: FALSE | S83: =IF($V83>0, "blocked", IF($Y83=0, "ready-all", "ready-hard")) -> blocked | T83: =COUNTIFS(Prerequisites[Run ID], $B83, Prerequisites[Type], "hard") -> 1 | U83: =COUNTIFS(Prerequisites[Run ID], $B83, Prerequisites[Type], "hard", Prerequisites[Satisfied], TRUE) -> 0 | V83: =T83-U83 -> 1 | W83: =COUNTIFS(Prerequisites[Run ID], $B83, Prerequisites[Type], "soft") -> 0 | X83: =COUNTIFS(Prerequisites[Run ID], $B83, Prerequisites[Type], "soft", Prerequisites[Satisfied], TRUE) -> 0 | Y83: =W83-X83 -> 0 | Z83: =COUNTIFS(Prerequisites[Prereq Run ID],$B83,Prerequisites[Type], "hard") -> 0 | AA83: =COUNTIFS(Reading_Order[Run ID], $B83, Reading_Order[Completed], TRUE) -> 0 | AB83: =$G83-$AA83 -> 64 | AC83: =AA83/(AB83+AA83) -> 0 | AD83: =IF(T83<1, TRUE, FALSE) -> FALSE
A84: Zdarsky's Daredevil | B84: zdarsky-daredevil | C84: Daredevil | D84: Chip Zdarsky | E84: Marco Checchetto | F84: Daredevil (2019) #1-36; Daredevil (2022) #1-14; Devil's Reign #1-6; Devil's Reign: Omega; Daredevil: Woman Without Fear #1-3; Daredevil Annual (2019) | G84: =COUNTIF(Reading_Order[Run ID], B84) -> 66 | H84: 2019 | I84: 2023 | J84: =$G84>0 -> TRUE | K84: =IF($G84=0,"—",IF($AA84=$G84,"read",IF($AA84>0,"reading","unread"))) -> unread | L84: 3 | M84: Best Daredevil since Bendis, arguably since Miller | O84: 5 | P84: 1 | Q84: TRUE | S84: =IF($V84>0, "blocked", IF($Y84=0, "ready-all", "ready-hard")) -> ready-hard | T84: =COUNTIFS(Prerequisites[Run ID], $B84, Prerequisites[Type], "hard") -> 0 | U84: =COUNTIFS(Prerequisites[Run ID], $B84, Prerequisites[Type], "hard", Prerequisites[Satisfied], TRUE) -> 0 | V84: =T84-U84 -> 0 | W84: =COUNTIFS(Prerequisites[Run ID], $B84, Prerequisites[Type], "soft") -> 3 | X84: =COUNTIFS(Prerequisites[Run ID], $B84, Prerequisites[Type], "soft", Prerequisites[Satisfied], TRUE) -> 0 | Y84: =W84-X84 -> 3 | Z84: =COUNTIFS(Prerequisites[Prereq Run ID],$B84,Prerequisites[Type], "hard") -> 0 | AA84: =COUNTIFS(Reading_Order[Run ID], $B84, Reading_Order[Completed], TRUE) -> 0 | AB84: =$G84-$AA84 -> 66 | AC84: =AA84/(AB84+AA84) -> 0 | AD84: =IF(T84<1, TRUE, FALSE) -> TRUE
A85: Deadpool Origin | B85: deadpool-origin | C85: Deadpool | D85: Fabian Nicieza | F85: New Mutants #98; X-Force (1991) #2 | G85: =COUNTIF(Reading_Order[Run ID], B85) -> 17 | H85: 1991 | I85: 1991 | J85: =$G85>0 -> TRUE | K85: =IF($G85=0,"—",IF($AA85=$G85,"read",IF($AA85>0,"reading","unread"))) -> unread | L85: 4 | M85: Wade's debut and the Weapon X ties | O85: 1 | P85: 1 | Q85: FALSE | S85: =IF($V85>0, "blocked", IF($Y85=0, "ready-all", "ready-hard")) -> ready-all | T85: =COUNTIFS(Prerequisites[Run ID], $B85, Prerequisites[Type], "hard") -> 0 | U85: =COUNTIFS(Prerequisites[Run ID], $B85, Prerequisites[Type], "hard", Prerequisites[Satisfied], TRUE) -> 0 | V85: =T85-U85 -> 0 | W85: =COUNTIFS(Prerequisites[Run ID], $B85, Prerequisites[Type], "soft") -> 0 | X85: =COUNTIFS(Prerequisites[Run ID], $B85, Prerequisites[Type], "soft", Prerequisites[Satisfied], TRUE) -> 0 | Y85: =W85-X85 -> 0 | Z85: =COUNTIFS(Prerequisites[Prereq Run ID],$B85,Prerequisites[Type], "hard") -> 1 | AA85: =COUNTIFS(Reading_Order[Run ID], $B85, Reading_Order[Completed], TRUE) -> 0 | AB85: =$G85-$AA85 -> 17 | AC85: =AA85/(AB85+AA85) -> 0 | AD85: =IF(T85<1, TRUE, FALSE) -> TRUE
A86: Kelly's Deadpool | B86: kelly-deadpool | C86: Deadpool | D86: Joe Kelly | F86: Deadpool (1997) #1-33 | G86: =COUNTIF(Reading_Order[Run ID], B86) -> 40 | H86: 1997 | I86: 1999 | J86: =$G86>0 -> TRUE | K86: =IF($G86=0,"—",IF($AA86=$G86,"read",IF($AA86>0,"reading","unread"))) -> unread | L86: 4 | M86: Invented the modern Deadpool | O86: 1 | P86: 2 | Q86: TRUE | S86: =IF($V86>0, "blocked", IF($Y86=0, "ready-all", "ready-hard")) -> blocked | T86: =COUNTIFS(Prerequisites[Run ID], $B86, Prerequisites[Type], "hard") -> 1 | U86: =COUNTIFS(Prerequisites[Run ID], $B86, Prerequisites[Type], "hard", Prerequisites[Satisfied], TRUE) -> 0 | V86: =T86-U86 -> 1 | W86: =COUNTIFS(Prerequisites[Run ID], $B86, Prerequisites[Type], "soft") -> 0 | X86: =COUNTIFS(Prerequisites[Run ID], $B86, Prerequisites[Type], "soft", Prerequisites[Satisfied], TRUE) -> 0 | Y86: =W86-X86 -> 0 | Z86: =COUNTIFS(Prerequisites[Prereq Run ID],$B86,Prerequisites[Type], "hard") -> 0 | AA86: =COUNTIFS(Reading_Order[Run ID], $B86, Reading_Order[Completed], TRUE) -> 0 | AB86: =$G86-$AA86 -> 40 | AC86: =AA86/(AB86+AA86) -> 0 | AD86: =IF(T86<1, TRUE, FALSE) -> FALSE
A87: Englehart & Gerber's Defenders | B87: classic-defenders | C87: Defenders | D87: Steve Englehart, Steve Gerber | E87: Sal Buscema | F87: Defenders (1972) #1-16, #20-41 | G87: =COUNTIF(Reading_Order[Run ID], B87) -> 62 | H87: 1972 | I87: 1976 | J87: =$G87>0 -> TRUE | K87: =IF($G87=0,"—",IF($AA87=$G87,"read",IF($AA87>0,"reading","unread"))) -> unread | L87: 4 | M87: The Non-Team, the Headmen, the Elf with a Gun | O87: 1 | P87: 1 | Q87: TRUE | S87: =IF($V87>0, "blocked", IF($Y87=0, "ready-all", "ready-hard")) -> ready-all | T87: =COUNTIFS(Prerequisites[Run ID], $B87, Prerequisites[Type], "hard") -> 0 | U87: =COUNTIFS(Prerequisites[Run ID], $B87, Prerequisites[Type], "hard", Prerequisites[Satisfied], TRUE) -> 0 | V87: =T87-U87 -> 0 | W87: =COUNTIFS(Prerequisites[Run ID], $B87, Prerequisites[Type], "soft") -> 0 | X87: =COUNTIFS(Prerequisites[Run ID], $B87, Prerequisites[Type], "soft", Prerequisites[Satisfied], TRUE) -> 0 | Y87: =W87-X87 -> 0 | Z87: =COUNTIFS(Prerequisites[Prereq Run ID],$B87,Prerequisites[Type], "hard") -> 0 | AA87: =COUNTIFS(Reading_Order[Run ID], $B87, Reading_Order[Completed], TRUE) -> 0 | AB87: =$G87-$AA87 -> 62 | AC87: =AA87/(AB87+AA87) -> 0 | AD87: =IF(T87<1, TRUE, FALSE) -> TRUE
A88: Doctor Doom: Origins | B88: doom-origin | C88: Doctor Doom | D88: Stan Lee | F88: Fantastic Four #5-6, 10, 16-17, 23, 39-40, 57-60, 84-87, Annual #2 | G88: =COUNTIF(Reading_Order[Run ID], B88) -> 30 | H88: 1962 | I88: 1969 | J88: =$G88>0 -> TRUE | K88: =IF($G88=0,"—",IF($AA88=$G88,"read",IF($AA88>0,"reading","unread"))) -> unread | L88: 4 | M88: Doom across sixty years of other people's books | O88: 1 | P88: 1 | Q88: FALSE | S88: =IF($V88>0, "blocked", IF($Y88=0, "ready-all", "ready-hard")) -> ready-hard | T88: =COUNTIFS(Prerequisites[Run ID], $B88, Prerequisites[Type], "hard") -> 0 | U88: =COUNTIFS(Prerequisites[Run ID], $B88, Prerequisites[Type], "hard", Prerequisites[Satisfied], TRUE) -> 0 | V88: =T88-U88 -> 0 | W88: =COUNTIFS(Prerequisites[Run ID], $B88, Prerequisites[Type], "soft") -> 1 | X88: =COUNTIFS(Prerequisites[Run ID], $B88, Prerequisites[Type], "soft", Prerequisites[Satisfied], TRUE) -> 0 | Y88: =W88-X88 -> 1 | Z88: =COUNTIFS(Prerequisites[Prereq Run ID],$B88,Prerequisites[Type], "hard") -> 1 | AA88: =COUNTIFS(Reading_Order[Run ID], $B88, Reading_Order[Completed], TRUE) -> 0 | AB88: =$G88-$AA88 -> 30 | AC88: =AA88/(AB88+AA88) -> 0 | AD88: =IF(T88<1, TRUE, FALSE) -> TRUE
A89: Doctor Doom: Modern | B89: doom-modern | C89: Doctor Doom | D89: John Byrne, David Michelinie | F89: Iron Man #149-150; Fantastic Four #236, 246-247, 258-260; Fantastic Four Special 2005; Fantastic Four (1998) #67-70, 500 | G89: =COUNTIF(Reading_Order[Run ID], B89) -> 34 | H89: 1981 | I89: 1983 | J89: =$G89>0 -> TRUE | K89: =IF($G89=0,"—",IF($AA89=$G89,"read",IF($AA89>0,"reading","unread"))) -> unread | L89: 4 | M89: Doom at his most fully realised | O89: 1 | P89: 2 | Q89: FALSE | S89: =IF($V89>0, "blocked", IF($Y89=0, "ready-all", "ready-hard")) -> blocked | T89: =COUNTIFS(Prerequisites[Run ID], $B89, Prerequisites[Type], "hard") -> 1 | U89: =COUNTIFS(Prerequisites[Run ID], $B89, Prerequisites[Type], "hard", Prerequisites[Satisfied], TRUE) -> 0 | V89: =T89-U89 -> 1 | W89: =COUNTIFS(Prerequisites[Run ID], $B89, Prerequisites[Type], "soft") -> 1 | X89: =COUNTIFS(Prerequisites[Run ID], $B89, Prerequisites[Type], "soft", Prerequisites[Satisfied], TRUE) -> 0 | Y89: =W89-X89 -> 1 | Z89: =COUNTIFS(Prerequisites[Prereq Run ID],$B89,Prerequisites[Type], "hard") -> 0 | AA89: =COUNTIFS(Reading_Order[Run ID], $B89, Reading_Order[Completed], TRUE) -> 0 | AB89: =$G89-$AA89 -> 34 | AC89: =AA89/(AB89+AA89) -> 0 | AD89: =IF(T89<1, TRUE, FALSE) -> FALSE
A90: Emperor Doom | B90: emperor-doom | C90: Doctor Doom | D90: David Michelinie, Mark Gruenwald, Jim Shooter | F90: Marvel Graphic Novel #27: Emperor Doom | G90: =COUNTIF(Reading_Order[Run ID], B90) -> 1 | H90: 1987 | I90: 1987 | J90: =$G90>0 -> TRUE | K90: =IF($G90=0,"—",IF($AA90=$G90,"read",IF($AA90>0,"reading","unread"))) -> unread | L90: 4 | M90: Doom actually winning | O90: 2 | P90: 1 | Q90: FALSE | S90: =IF($V90>0, "blocked", IF($Y90=0, "ready-all", "ready-hard")) -> ready-hard | T90: =COUNTIFS(Prerequisites[Run ID], $B90, Prerequisites[Type], "hard") -> 0 | U90: =COUNTIFS(Prerequisites[Run ID], $B90, Prerequisites[Type], "hard", Prerequisites[Satisfied], TRUE) -> 0 | V90: =T90-U90 -> 0 | W90: =COUNTIFS(Prerequisites[Run ID], $B90, Prerequisites[Type], "soft") -> 1 | X90: =COUNTIFS(Prerequisites[Run ID], $B90, Prerequisites[Type], "soft", Prerequisites[Satisfied], TRUE) -> 0 | Y90: =W90-X90 -> 1 | Z90: =COUNTIFS(Prerequisites[Prereq Run ID],$B90,Prerequisites[Type], "hard") -> 0 | AA90: =COUNTIFS(Reading_Order[Run ID], $B90, Reading_Order[Completed], TRUE) -> 0 | AB90: =$G90-$AA90 -> 1 | AC90: =AA90/(AB90+AA90) -> 0 | AD90: =IF(T90<1, TRUE, FALSE) -> TRUE
A91: Doctor Strange & Doctor Doom: Triumph and Torment | B91: triumph-and-torment | C91: Doctor Doom | D91: Roger Stern | F91: Marvel Graphic Novel #49: Doctor Strange & Doctor Doom: Triumph and Torment | G91: =COUNTIF(Reading_Order[Run ID], B91) -> 1 | H91: 1989 | I91: 1989 | J91: =$G91>0 -> TRUE | K91: =IF($G91=0,"—",IF($AA91=$G91,"read",IF($AA91>0,"reading","unread"))) -> unread | L91: 4 | M91: The best Doom story, and the best Strange team-up | O91: 3 | P91: 1 | Q91: TRUE | S91: =IF($V91>0, "blocked", IF($Y91=0, "ready-all", "ready-hard")) -> ready-hard | T91: =COUNTIFS(Prerequisites[Run ID], $B91, Prerequisites[Type], "hard") -> 0 | U91: =COUNTIFS(Prerequisites[Run ID], $B91, Prerequisites[Type], "hard", Prerequisites[Satisfied], TRUE) -> 0 | V91: =T91-U91 -> 0 | W91: =COUNTIFS(Prerequisites[Run ID], $B91, Prerequisites[Type], "soft") -> 2 | X91: =COUNTIFS(Prerequisites[Run ID], $B91, Prerequisites[Type], "soft", Prerequisites[Satisfied], TRUE) -> 0 | Y91: =W91-X91 -> 2 | Z91: =COUNTIFS(Prerequisites[Prereq Run ID],$B91,Prerequisites[Type], "hard") -> 1 | AA91: =COUNTIFS(Reading_Order[Run ID], $B91, Reading_Order[Completed], TRUE) -> 0 | AB91: =$G91-$AA91 -> 1 | AC91: =AA91/(AB91+AA91) -> 0 | AD91: =IF(T91<1, TRUE, FALSE) -> TRUE
A92: Dixon's Doom | B92: dixon-doom | C92: Doctor Doom | D92: Chuck Dixon | F92: Doom: The Emperor Returns #1-3 | G92: =COUNTIF(Reading_Order[Run ID], B92) -> 6 | H92: 2001 | I92: 2001 | J92: =$G92>0 -> TRUE | K92: =IF($G92=0,"—",IF($AA92=$G92,"read",IF($AA92>0,"reading","unread"))) -> unread | L92: 4 | M92: Doom reclaiming Latveria | O92: 4 | P92: 1 | Q92: FALSE | S92: =IF($V92>0, "blocked", IF($Y92=0, "ready-all", "ready-hard")) -> ready-hard | T92: =COUNTIFS(Prerequisites[Run ID], $B92, Prerequisites[Type], "hard") -> 0 | U92: =COUNTIFS(Prerequisites[Run ID], $B92, Prerequisites[Type], "hard", Prerequisites[Satisfied], TRUE) -> 0 | V92: =T92-U92 -> 0 | W92: =COUNTIFS(Prerequisites[Run ID], $B92, Prerequisites[Type], "soft") -> 1 | X92: =COUNTIFS(Prerequisites[Run ID], $B92, Prerequisites[Type], "soft", Prerequisites[Satisfied], TRUE) -> 0 | Y92: =W92-X92 -> 1 | Z92: =COUNTIFS(Prerequisites[Prereq Run ID],$B92,Prerequisites[Type], "hard") -> 0 | AA92: =COUNTIFS(Reading_Order[Run ID], $B92, Reading_Order[Completed], TRUE) -> 0 | AB92: =$G92-$AA92 -> 6 | AC92: =AA92/(AB92+AA92) -> 0 | AD92: =IF(T92<1, TRUE, FALSE) -> TRUE
A93: Books of Doom | B93: books-of-doom | C93: Doctor Doom | D93: Ed Brubaker | F93: Books of Doom #1-6 | G93: =COUNTIF(Reading_Order[Run ID], B93) -> 6 | H93: 2005 | I93: 2006 | J93: =$G93>0 -> TRUE | K93: =IF($G93=0,"—",IF($AA93=$G93,"read",IF($AA93>0,"reading","unread"))) -> unread | L93: 4 | M93: The origin retold properly | O93: 5 | P93: 1 | Q93: TRUE | S93: =IF($V93>0, "blocked", IF($Y93=0, "ready-all", "ready-hard")) -> ready-all | T93: =COUNTIFS(Prerequisites[Run ID], $B93, Prerequisites[Type], "hard") -> 0 | U93: =COUNTIFS(Prerequisites[Run ID], $B93, Prerequisites[Type], "hard", Prerequisites[Satisfied], TRUE) -> 0 | V93: =T93-U93 -> 0 | W93: =COUNTIFS(Prerequisites[Run ID], $B93, Prerequisites[Type], "soft") -> 0 | X93: =COUNTIFS(Prerequisites[Run ID], $B93, Prerequisites[Type], "soft", Prerequisites[Satisfied], TRUE) -> 0 | Y93: =W93-X93 -> 0 | Z93: =COUNTIFS(Prerequisites[Prereq Run ID],$B93,Prerequisites[Type], "hard") -> 0 | AA93: =COUNTIFS(Reading_Order[Run ID], $B93, Reading_Order[Completed], TRUE) -> 0 | AB93: =$G93-$AA93 -> 6 | AC93: =AA93/(AB93+AA93) -> 0 | AD93: =IF(T93<1, TRUE, FALSE) -> TRUE
A94: Doomwar | B94: doomwar | C94: Doctor Doom | D94: Jonathan Maberry | F94: Doomwar #1-6 | G94: =COUNTIF(Reading_Order[Run ID], B94) -> 6 | H94: 2010 | I94: 2010 | J94: =$G94>0 -> TRUE | K94: =IF($G94=0,"—",IF($AA94=$G94,"read",IF($AA94>0,"reading","unread"))) -> unread | L94: 4 | M94: Spins directly out of Hudlin's Black Panther | O94: 6 | P94: 1 | Q94: FALSE | S94: =IF($V94>0, "blocked", IF($Y94=0, "ready-all", "ready-hard")) -> blocked | T94: =COUNTIFS(Prerequisites[Run ID], $B94, Prerequisites[Type], "hard") -> 1 | U94: =COUNTIFS(Prerequisites[Run ID], $B94, Prerequisites[Type], "hard", Prerequisites[Satisfied], TRUE) -> 0 | V94: =T94-U94 -> 1 | W94: =COUNTIFS(Prerequisites[Run ID], $B94, Prerequisites[Type], "soft") -> 0 | X94: =COUNTIFS(Prerequisites[Run ID], $B94, Prerequisites[Type], "soft", Prerequisites[Satisfied], TRUE) -> 0 | Y94: =W94-X94 -> 0 | Z94: =COUNTIFS(Prerequisites[Prereq Run ID],$B94,Prerequisites[Type], "hard") -> 0 | AA94: =COUNTIFS(Reading_Order[Run ID], $B94, Reading_Order[Completed], TRUE) -> 0 | AB94: =$G94-$AA94 -> 6 | AC94: =AA94/(AB94+AA94) -> 0 | AD94: =IF(T94<1, TRUE, FALSE) -> FALSE
A95: Infamous Iron Man | B95: infamous-iron-man | C95: Doctor Doom | D95: Brian Michael Bendis | F95: Infamous Iron Man #1-12 | G95: =COUNTIF(Reading_Order[Run ID], B95) -> 12 | H95: 2016 | I95: 2017 | J95: =$G95>0 -> TRUE | K95: =IF($G95=0,"—",IF($AA95=$G95,"read",IF($AA95>0,"reading","unread"))) -> unread | L95: 4 | M95: Doom as Iron Man; Bendis' best late-period idea | O95: 7 | P95: 1 | Q95: FALSE | S95: =IF($V95>0, "blocked", IF($Y95=0, "ready-all", "ready-hard")) -> blocked | T95: =COUNTIFS(Prerequisites[Run ID], $B95, Prerequisites[Type], "hard") -> 2 | U95: =COUNTIFS(Prerequisites[Run ID], $B95, Prerequisites[Type], "hard", Prerequisites[Satisfied], TRUE) -> 0 | V95: =T95-U95 -> 2 | W95: =COUNTIFS(Prerequisites[Run ID], $B95, Prerequisites[Type], "soft") -> 3 | X95: =COUNTIFS(Prerequisites[Run ID], $B95, Prerequisites[Type], "soft", Prerequisites[Satisfied], TRUE) -> 0 | Y95: =W95-X95 -> 3 | Z95: =COUNTIFS(Prerequisites[Prereq Run ID],$B95,Prerequisites[Type], "hard") -> 0 | AA95: =COUNTIFS(Reading_Order[Run ID], $B95, Reading_Order[Completed], TRUE) -> 0 | AB95: =$G95-$AA95 -> 12 | AC95: =AA95/(AB95+AA95) -> 0 | AD95: =IF(T95<1, TRUE, FALSE) -> FALSE
A96: Cantwell's Doctor Doom | B96: cantwell-doom | C96: Doctor Doom | D96: Christopher Cantwell | E96: Salvador Larroca | F96: Doctor Doom (2019) #1-10 | G96: =COUNTIF(Reading_Order[Run ID], B96) -> 10 | H96: 2019 | I96: 2020 | J96: =$G96>0 -> TRUE | K96: =IF($G96=0,"—",IF($AA96=$G96,"read",IF($AA96>0,"reading","unread"))) -> unread | L96: 4 | M96: Ten issues, and the best modern Doom | O96: 8 | P96: 1 | Q96: TRUE | S96: =IF($V96>0, "blocked", IF($Y96=0, "ready-all", "ready-hard")) -> ready-hard | T96: =COUNTIFS(Prerequisites[Run ID], $B96, Prerequisites[Type], "hard") -> 0 | U96: =COUNTIFS(Prerequisites[Run ID], $B96, Prerequisites[Type], "hard", Prerequisites[Satisfied], TRUE) -> 0 | V96: =T96-U96 -> 0 | W96: =COUNTIFS(Prerequisites[Run ID], $B96, Prerequisites[Type], "soft") -> 1 | X96: =COUNTIFS(Prerequisites[Run ID], $B96, Prerequisites[Type], "soft", Prerequisites[Satisfied], TRUE) -> 0 | Y96: =W96-X96 -> 1 | Z96: =COUNTIFS(Prerequisites[Prereq Run ID],$B96,Prerequisites[Type], "hard") -> 0 | AA96: =COUNTIFS(Reading_Order[Run ID], $B96, Reading_Order[Completed], TRUE) -> 0 | AB96: =$G96-$AA96 -> 10 | AC96: =AA96/(AB96+AA96) -> 0 | AD96: =IF(T96<1, TRUE, FALSE) -> TRUE
A97: Lee & Ditko's Doctor Strange | B97: leeditko-strange | C97: Dr. Strange | D97: Stan Lee | E97: Steve Ditko | F97: Strange Tales (1951) #110-111, #114-168; Amazing Spider-Man Annual (1964) #2 (1965) | G97: =COUNTIF(Reading_Order[Run ID], B97) -> 36 | H97: 1963 | I97: 1966 | J97: =$G97>0 -> TRUE | K97: =IF($G97=0,"—",IF($AA97=$G97,"read",IF($AA97>0,"reading","unread"))) -> unread | L97: 4 | M97: The one Silver Age run that rewards completeness — #130-146 unbroken | O97: 1 | P97: 1 | Q97: TRUE | S97: =IF($V97>0, "blocked", IF($Y97=0, "ready-all", "ready-hard")) -> ready-all | T97: =COUNTIFS(Prerequisites[Run ID], $B97, Prerequisites[Type], "hard") -> 0 | U97: =COUNTIFS(Prerequisites[Run ID], $B97, Prerequisites[Type], "hard", Prerequisites[Satisfied], TRUE) -> 0 | V97: =T97-U97 -> 0 | W97: =COUNTIFS(Prerequisites[Run ID], $B97, Prerequisites[Type], "soft") -> 0 | X97: =COUNTIFS(Prerequisites[Run ID], $B97, Prerequisites[Type], "soft", Prerequisites[Satisfied], TRUE) -> 0 | Y97: =W97-X97 -> 0 | Z97: =COUNTIFS(Prerequisites[Prereq Run ID],$B97,Prerequisites[Type], "hard") -> 1 | AA97: =COUNTIFS(Reading_Order[Run ID], $B97, Reading_Order[Completed], TRUE) -> 0 | AB97: =$G97-$AA97 -> 36 | AC97: =AA97/(AB97+AA97) -> 0 | AD97: =IF(T97<1, TRUE, FALSE) -> TRUE
A98: Englehart & Brunner's Doctor Strange | B98: englehart-brunner-strange | C98: Dr. Strange | D98: Steve Englehart | E98: Frank Brunner | F98: Marvel Premiere (1972) #9-14; Doctor Strange (1974) #1-19 | G98: =COUNTIF(Reading_Order[Run ID], B98) -> 31 | H98: 1973 | I98: 1976 | J98: =$G98>0 -> TRUE | K98: =IF($G98=0,"—",IF($AA98=$G98,"read",IF($AA98>0,"reading","unread"))) -> unread | L98: 4 | M98: THE Doctor Strange run | O98: 1 | P98: 2 | Q98: TRUE | S98: =IF($V98>0, "blocked", IF($Y98=0, "ready-all", "ready-hard")) -> blocked | T98: =COUNTIFS(Prerequisites[Run ID], $B98, Prerequisites[Type], "hard") -> 1 | U98: =COUNTIFS(Prerequisites[Run ID], $B98, Prerequisites[Type], "hard", Prerequisites[Satisfied], TRUE) -> 0 | V98: =T98-U98 -> 1 | W98: =COUNTIFS(Prerequisites[Run ID], $B98, Prerequisites[Type], "soft") -> 0 | X98: =COUNTIFS(Prerequisites[Run ID], $B98, Prerequisites[Type], "soft", Prerequisites[Satisfied], TRUE) -> 0 | Y98: =W98-X98 -> 0 | Z98: =COUNTIFS(Prerequisites[Prereq Run ID],$B98,Prerequisites[Type], "hard") -> 1 | AA98: =COUNTIFS(Reading_Order[Run ID], $B98, Reading_Order[Completed], TRUE) -> 0 | AB98: =$G98-$AA98 -> 31 | AC98: =AA98/(AB98+AA98) -> 0 | AD98: =IF(T98<1, TRUE, FALSE) -> FALSE
A99: Stern's Doctor Strange | B99: stern-strange | C99: Dr. Strange | D99: Roger Stern | E99: Marshall Rogers | F99: Doctor Strange (1974) #14, #27-30, #32-33, #35-37, #47-62, #65-73, #75; Tomb of Dracula (1972) #44; Doctor Strange and Doctor Doom: Triumph and Torment | G99: =COUNTIF(Reading_Order[Run ID], B99) -> 36 | H99: 1979 | I99: 1985 | J99: =$G99>0 -> TRUE | K99: =IF($G99=0,"—",IF($AA99=$G99,"read",IF($AA99>0,"reading","unread"))) -> unread | L99: 4 | M99: Triumph and Torment is the standout | O99: 1 | P99: 3 | Q99: FALSE | S99: =IF($V99>0, "blocked", IF($Y99=0, "ready-all", "ready-hard")) -> blocked | T99: =COUNTIFS(Prerequisites[Run ID], $B99, Prerequisites[Type], "hard") -> 1 | U99: =COUNTIFS(Prerequisites[Run ID], $B99, Prerequisites[Type], "hard", Prerequisites[Satisfied], TRUE) -> 0 | V99: =T99-U99 -> 1 | W99: =COUNTIFS(Prerequisites[Run ID], $B99, Prerequisites[Type], "soft") -> 0 | X99: =COUNTIFS(Prerequisites[Run ID], $B99, Prerequisites[Type], "soft", Prerequisites[Satisfied], TRUE) -> 0 | Y99: =W99-X99 -> 0 | Z99: =COUNTIFS(Prerequisites[Prereq Run ID],$B99,Prerequisites[Type], "hard") -> 0 | AA99: =COUNTIFS(Reading_Order[Run ID], $B99, Reading_Order[Completed], TRUE) -> 0 | AB99: =$G99-$AA99 -> 36 | AC99: =AA99/(AB99+AA99) -> 0 | AD99: =IF(T99<1, TRUE, FALSE) -> FALSE
A100: Doctor Strange: The Oath | B100: the-oath | C100: Dr. Strange | D100: Brian K. Vaughan | E100: Marcos Martin | F100: Doctor Strange: The Oath | G100: =COUNTIF(Reading_Order[Run ID], B100) -> 5 | H100: 2006 | I100: 2007 | J100: =$G100>0 -> TRUE | K100: =IF($G100=0,"—",IF($AA100=$G100,"read",IF($AA100>0,"reading","unread"))) -> unread | L100: 4 | M100: Five issues, no homework, the best modern Strange story | O100: 2 | P100: 1 | Q100: TRUE | S100: =IF($V100>0, "blocked", IF($Y100=0, "ready-all", "ready-hard")) -> ready-all | T100: =COUNTIFS(Prerequisites[Run ID], $B100, Prerequisites[Type], "hard") -> 0 | U100: =COUNTIFS(Prerequisites[Run ID], $B100, Prerequisites[Type], "hard", Prerequisites[Satisfied], TRUE) -> 0 | V100: =T100-U100 -> 0 | W100: =COUNTIFS(Prerequisites[Run ID], $B100, Prerequisites[Type], "soft") -> 0 | X100: =COUNTIFS(Prerequisites[Run ID], $B100, Prerequisites[Type], "soft", Prerequisites[Satisfied], TRUE) -> 0 | Y100: =W100-X100 -> 0 | Z100: =COUNTIFS(Prerequisites[Prereq Run ID],$B100,Prerequisites[Type], "hard") -> 0 | AA100: =COUNTIFS(Reading_Order[Run ID], $B100, Reading_Order[Completed], TRUE) -> 0 | AB100: =$G100-$AA100 -> 5 | AC100: =AA100/(AB100+AA100) -> 0 | AD100: =IF(T100<1, TRUE, FALSE) -> TRUE
A101: Aaron's Doctor Strange | B101: aaron-strange | C101: Dr. Strange | D101: Jason Aaron | F101: Doctor Strange (2015) #1-20; Doctor Strange: The Last Days of Magic; Doctor Strange Annual (2016) | G101: =COUNTIF(Reading_Order[Run ID], B101) -> 22 | H101: 2015 | I101: 2017 | J101: =$G101>0 -> TRUE | K101: =IF($G101=0,"—",IF($AA101=$G101,"read",IF($AA101>0,"reading","unread"))) -> unread | L101: 4 | M101: Magic has a price, paid in body horror | O101: 3 | P101: 1 | Q101: TRUE | S101: =IF($V101>0, "blocked", IF($Y101=0, "ready-all", "ready-hard")) -> ready-hard | T101: =COUNTIFS(Prerequisites[Run ID], $B101, Prerequisites[Type], "hard") -> 0 | U101: =COUNTIFS(Prerequisites[Run ID], $B101, Prerequisites[Type], "hard", Prerequisites[Satisfied], TRUE) -> 0 | V101: =T101-U101 -> 0 | W101: =COUNTIFS(Prerequisites[Run ID], $B101, Prerequisites[Type], "soft") -> 1 | X101: =COUNTIFS(Prerequisites[Run ID], $B101, Prerequisites[Type], "soft", Prerequisites[Satisfied], TRUE) -> 0 | Y101: =W101-X101 -> 1 | Z101: =COUNTIFS(Prerequisites[Prereq Run ID],$B101,Prerequisites[Type], "hard") -> 1 | AA101: =COUNTIFS(Reading_Order[Run ID], $B101, Reading_Order[Completed], TRUE) -> 0 | AB101: =$G101-$AA101 -> 22 | AC101: =AA101/(AB101+AA101) -> 0 | AD101: =IF(T101<1, TRUE, FALSE) -> TRUE
A102: Cates' Dr. Strange | B102: cates-strange | C102: Dr. Strange | D102: Donny Cates | F102: Doctor Strange,(2015) #381-390; Doctor Strange: Damnation #1-4 | G102: =COUNTIF(Reading_Order[Run ID], B102) -> 14 | H102: 2017 | I102: 2018 | J102: =$G102>0 -> TRUE | K102: =IF($G102=0,"—",IF($AA102=$G102,"read",IF($AA102>0,"reading","unread"))) -> unread | L102: 4 | M102: Damnation — also sits in your Midnight Sons material | O102: 3 | P102: 2 | Q102: TRUE | S102: =IF($V102>0, "blocked", IF($Y102=0, "ready-all", "ready-hard")) -> blocked | T102: =COUNTIFS(Prerequisites[Run ID], $B102, Prerequisites[Type], "hard") -> 1 | U102: =COUNTIFS(Prerequisites[Run ID], $B102, Prerequisites[Type], "hard", Prerequisites[Satisfied], TRUE) -> 0 | V102: =T102-U102 -> 1 | W102: =COUNTIFS(Prerequisites[Run ID], $B102, Prerequisites[Type], "soft") -> 1 | X102: =COUNTIFS(Prerequisites[Run ID], $B102, Prerequisites[Type], "soft", Prerequisites[Satisfied], TRUE) -> 0 | Y102: =W102-X102 -> 1 | Z102: =COUNTIFS(Prerequisites[Prereq Run ID],$B102,Prerequisites[Type], "hard") -> 1 | AA102: =COUNTIFS(Reading_Order[Run ID], $B102, Reading_Order[Completed], TRUE) -> 0 | AB102: =$G102-$AA102 -> 14 | AC102: =AA102/(AB102+AA102) -> 0 | AD102: =IF(T102<1, TRUE, FALSE) -> FALSE
A103: Waid's Doctor Strange | B103: waid-strange | C103: Dr. Strange | D103: Mark Waid | F103: Doctor Strange (2018) #1-20; Doctor Strange Annual (2019) | G103: =COUNTIF(Reading_Order[Run ID], B103) -> 27 | H103: 2018 | I103: 2019 | J103: =$G103>0 -> TRUE | K103: =IF($G103=0,"—",IF($AA103=$G103,"read",IF($AA103>0,"reading","unread"))) -> unread | L103: 4 | M103: Strange in space; a palate cleanser after Aaron | O103: 3 | P103: 3 | Q103: FALSE | S103: =IF($V103>0, "blocked", IF($Y103=0, "ready-all", "ready-hard")) -> blocked | T103: =COUNTIFS(Prerequisites[Run ID], $B103, Prerequisites[Type], "hard") -> 1 | U103: =COUNTIFS(Prerequisites[Run ID], $B103, Prerequisites[Type], "hard", Prerequisites[Satisfied], TRUE) -> 0 | V103: =T103-U103 -> 1 | W103: =COUNTIFS(Prerequisites[Run ID], $B103, Prerequisites[Type], "soft") -> 0 | X103: =COUNTIFS(Prerequisites[Run ID], $B103, Prerequisites[Type], "soft", Prerequisites[Satisfied], TRUE) -> 0 | Y103: =W103-X103 -> 0 | Z103: =COUNTIFS(Prerequisites[Prereq Run ID],$B103,Prerequisites[Type], "hard") -> 1 | AA103: =COUNTIFS(Reading_Order[Run ID], $B103, Reading_Order[Completed], TRUE) -> 0 | AB103: =$G103-$AA103 -> 27 | AC103: =AA103/(AB103+AA103) -> 0 | AD103: =IF(T103<1, TRUE, FALSE) -> FALSE
A104: MacKay's Doctor Strange | B104: mackay-strange | C104: Dr. Strange | D104: Jed MacKay | F104: Doctor Strange: Sorcerer Supreme #48-51; Death of Doctor Strange #1-5; Death of Doctor Strange: Avengers; Strange Academy Presents: Death of Doctor Strange; Death of Doctor Strange: Spider-Man; Death of Doctor Strange: White Fox; Death of Doctor Strange: Blade; Death of Doctor Strange: Bloodstone; Death of Doctor Strange: X-Men/Black Knight; Strange (2022) #1-10; Doctor Strange (2023) #1-18; Blood Hunt #1-5 | G104: =COUNTIF(Reading_Order[Run ID], B104) -> 49 | H104: 2021 | I104: 2024 | J104: =$G104>0 -> TRUE | K104: =IF($G104=0,"—",IF($AA104=$G104,"read",IF($AA104>0,"reading","unread"))) -> unread | L104: 4 | M104: Clea as Sorcerer Supreme, which is the good idea here | O104: 3 | P104: 4 | Q104: TRUE | S104: =IF($V104>0, "blocked", IF($Y104=0, "ready-all", "ready-hard")) -> blocked | T104: =COUNTIFS(Prerequisites[Run ID], $B104, Prerequisites[Type], "hard") -> 1 | U104: =COUNTIFS(Prerequisites[Run ID], $B104, Prerequisites[Type], "hard", Prerequisites[Satisfied], TRUE) -> 0 | V104: =T104-U104 -> 1 | W104: =COUNTIFS(Prerequisites[Run ID], $B104, Prerequisites[Type], "soft") -> 1 | X104: =COUNTIFS(Prerequisites[Run ID], $B104, Prerequisites[Type], "soft", Prerequisites[Satisfied], TRUE) -> 0 | Y104: =W104-X104 -> 1 | Z104: =COUNTIFS(Prerequisites[Prereq Run ID],$B104,Prerequisites[Type], "hard") -> 0 | AA104: =COUNTIFS(Reading_Order[Run ID], $B104, Reading_Order[Completed], TRUE) -> 0 | AB104: =$G104-$AA104 -> 49 | AC104: =AA104/(AB104+AA104) -> 0 | AD104: =IF(T104<1, TRUE, FALSE) -> FALSE
A105: Kirby's Eternals | B105: kirby-eternals | C105: Eternals | D105: Jack Kirby | F105: Eternals (1976) #1-19 | G105: =COUNTIF(Reading_Order[Run ID], B105) -> 20 | H105: 1976 | I105: 1978 | J105: =$G105>0 -> TRUE | K105: =IF($G105=0,"—",IF($AA105=$G105,"read",IF($AA105>0,"reading","unread"))) -> unread | L105: 4 | M105: Kirby unsupervised. Take that as you like | O105: 1 | P105: 1 | Q105: TRUE | S105: =IF($V105>0, "blocked", IF($Y105=0, "ready-all", "ready-hard")) -> ready-all | T105: =COUNTIFS(Prerequisites[Run ID], $B105, Prerequisites[Type], "hard") -> 0 | U105: =COUNTIFS(Prerequisites[Run ID], $B105, Prerequisites[Type], "hard", Prerequisites[Satisfied], TRUE) -> 0 | V105: =T105-U105 -> 0 | W105: =COUNTIFS(Prerequisites[Run ID], $B105, Prerequisites[Type], "soft") -> 0 | X105: =COUNTIFS(Prerequisites[Run ID], $B105, Prerequisites[Type], "soft", Prerequisites[Satisfied], TRUE) -> 0 | Y105: =W105-X105 -> 0 | Z105: =COUNTIFS(Prerequisites[Prereq Run ID],$B105,Prerequisites[Type], "hard") -> 1 | AA105: =COUNTIFS(Reading_Order[Run ID], $B105, Reading_Order[Completed], TRUE) -> 0 | AB105: =$G105-$AA105 -> 20 | AC105: =AA105/(AB105+AA105) -> 0 | AD105: =IF(T105<1, TRUE, FALSE) -> TRUE
A106: Eternals (1985) | B106: gillis-eternals | C106: Eternals | D106: Peter B. Gillis | E106: Sal Buscema | F106: Eternals (1985) #1-12 | G106: =COUNTIF(Reading_Order[Run ID], B106) -> 36 | H106: 1985 | I106: 1986 | J106: =$G106>0 -> TRUE | K106: =IF($G106=0,"—",IF($AA106=$G106,"read",IF($AA106>0,"reading","unread"))) -> unread | L106: 4 | M106: The first attempt to fold the Eternals into the Marvel Universe | O106: 1 | P106: 2 | Q106: FALSE | S106: =IF($V106>0, "blocked", IF($Y106=0, "ready-all", "ready-hard")) -> blocked | T106: =COUNTIFS(Prerequisites[Run ID], $B106, Prerequisites[Type], "hard") -> 3 | U106: =COUNTIFS(Prerequisites[Run ID], $B106, Prerequisites[Type], "hard", Prerequisites[Satisfied], TRUE) -> 0 | V106: =T106-U106 -> 3 | W106: =COUNTIFS(Prerequisites[Run ID], $B106, Prerequisites[Type], "soft") -> 1 | X106: =COUNTIFS(Prerequisites[Run ID], $B106, Prerequisites[Type], "soft", Prerequisites[Satisfied], TRUE) -> 0 | Y106: =W106-X106 -> 1 | Z106: =COUNTIFS(Prerequisites[Prereq Run ID],$B106,Prerequisites[Type], "hard") -> 0 | AA106: =COUNTIFS(Reading_Order[Run ID], $B106, Reading_Order[Completed], TRUE) -> 0 | AB106: =$G106-$AA106 -> 36 | AC106: =AA106/(AB106+AA106) -> 0 | AD106: =IF(T106<1, TRUE, FALSE) -> FALSE
A107: Gaiman's Eternals | B107: gaiman-eternals | C107: Eternals | D107: Neil Gaiman | E107: John Romita Jr. | F107: Eternals (2006) #1-7 | G107: =COUNTIF(Reading_Order[Run ID], B107) -> 7 | H107: 2006 | I107: 2007 | J107: =$G107>0 -> TRUE | K107: =IF($G107=0,"—",IF($AA107=$G107,"read",IF($AA107>0,"reading","unread"))) -> unread | L107: 4 | M107: The Eternals as amnesiacs; a clean modern reintroduction | O107: 1 | P107: 3 | Q107: FALSE | S107: =IF($V107>0, "blocked", IF($Y107=0, "ready-all", "ready-hard")) -> ready-hard | T107: =COUNTIFS(Prerequisites[Run ID], $B107, Prerequisites[Type], "hard") -> 0 | U107: =COUNTIFS(Prerequisites[Run ID], $B107, Prerequisites[Type], "hard", Prerequisites[Satisfied], TRUE) -> 0 | V107: =T107-U107 -> 0 | W107: =COUNTIFS(Prerequisites[Run ID], $B107, Prerequisites[Type], "soft") -> 1 | X107: =COUNTIFS(Prerequisites[Run ID], $B107, Prerequisites[Type], "soft", Prerequisites[Satisfied], TRUE) -> 0 | Y107: =W107-X107 -> 1 | Z107: =COUNTIFS(Prerequisites[Prereq Run ID],$B107,Prerequisites[Type], "hard") -> 2 | AA107: =COUNTIFS(Reading_Order[Run ID], $B107, Reading_Order[Completed], TRUE) -> 0 | AB107: =$G107-$AA107 -> 7 | AC107: =AA107/(AB107+AA107) -> 0 | AD107: =IF(T107<1, TRUE, FALSE) -> TRUE
A108: Gillen's Eternals | B108: gillen-eternals | C108: Eternals | D108: Kieron Gillen | E108: Esad Ribic | F108: Eternals (2021) #1-13; Eternals: Thanos Rises; Eternals: Celestia; Eternals: The Heretic; A.X.E.: Judgement Day | G108: =COUNTIF(Reading_Order[Run ID], B108) -> 34 | H108: 2021 | I108: 2022 | J108: =$G108>0 -> TRUE | K108: =IF($G108=0,"—",IF($AA108=$G108,"read",IF($AA108>0,"reading","unread"))) -> unread | L108: 4 | M108: Recontextualises the Celestials in a way that plays off Hickman | O108: 1 | P108: 4 | Q108: TRUE | S108: =IF($V108>0, "blocked", IF($Y108=0, "ready-all", "ready-hard")) -> blocked | T108: =COUNTIFS(Prerequisites[Run ID], $B108, Prerequisites[Type], "hard") -> 1 | U108: =COUNTIFS(Prerequisites[Run ID], $B108, Prerequisites[Type], "hard", Prerequisites[Satisfied], TRUE) -> 0 | V108: =T108-U108 -> 1 | W108: =COUNTIFS(Prerequisites[Run ID], $B108, Prerequisites[Type], "soft") -> 1 | X108: =COUNTIFS(Prerequisites[Run ID], $B108, Prerequisites[Type], "soft", Prerequisites[Satisfied], TRUE) -> 0 | Y108: =W108-X108 -> 1 | Z108: =COUNTIFS(Prerequisites[Prereq Run ID],$B108,Prerequisites[Type], "hard") -> 0 | AA108: =COUNTIFS(Reading_Order[Run ID], $B108, Reading_Order[Completed], TRUE) -> 0 | AB108: =$G108-$AA108 -> 34 | AC108: =AA108/(AB108+AA108) -> 0 | AD108: =IF(T108<1, TRUE, FALSE) -> FALSE
...

Sheet Reading Orders
A1: Track | B1: Run ID | C1: Run Title | D1: Issue | E1: Completed | F1: Sequence | G1: Type | H1: Notes | I1: Column 1
A2: {=IFERROR(_xlfn.XLOOKUP(B2, Runs[Run ID], Runs[Track]), "— pick a run —")} -> Hickman Saga | B2: hickman-secret-warriors | C2: {=IFERROR(_xlfn.XLOOKUP(B2, Runs[Run ID], Runs[Title]), "— pick a run —")} -> Secret Warriors | D2: Dark Reign: New Nation | E2: TRUE | F2: =IF($B2="","",IF($B2=$B1,F1+1,1)) -> 1 | G2: Core | H2: The Secret Warriors #0 story lives in this anthology.
A3: {=IFERROR(_xlfn.XLOOKUP(B3, Runs[Run ID], Runs[Track]), "— pick a run —")} -> Hickman Saga | B3: hickman-secret-warriors | C3: {=IFERROR(_xlfn.XLOOKUP(B3, Runs[Run ID], Runs[Title]), "— pick a run —")} -> Secret Warriors | D3: Secret Warriors #1 | E3: TRUE | F3: =IF($B3="","",IF($B3=$B2,F2+1,1)) -> 2 | G3: Core | H3: Co-plotted with Bendis; Hickman scripts.
A4: {=IFERROR(_xlfn.XLOOKUP(B4, Runs[Run ID], Runs[Track]), "— pick a run —")} -> Hickman Saga | B4: hickman-secret-warriors | C4: {=IFERROR(_xlfn.XLOOKUP(B4, Runs[Run ID], Runs[Title]), "— pick a run —")} -> Secret Warriors | D4: Secret Warriors #2 | E4: TRUE | F4: =IF($B4="","",IF($B4=$B3,F3+1,1)) -> 3 | G4: Core
A5: {=IFERROR(_xlfn.XLOOKUP(B5, Runs[Run ID], Runs[Track]), "— pick a run —")} -> Hickman Saga | B5: hickman-secret-warriors | C5: {=IFERROR(_xlfn.XLOOKUP(B5, Runs[Run ID], Runs[Title]), "— pick a run —")} -> Secret Warriors | D5: Secret Warriors #3 | E5: TRUE | F5: =IF($B5="","",IF($B5=$B4,F4+1,1)) -> 4 | G5: Core
A6: {=IFERROR(_xlfn.XLOOKUP(B6, Runs[Run ID], Runs[Track]), "— pick a run —")} -> Hickman Saga | B6: hickman-secret-warriors | C6: {=IFERROR(_xlfn.XLOOKUP(B6, Runs[Run ID], Runs[Title]), "— pick a run —")} -> Secret Warriors | D6: Secret Warriors #4 | E6: TRUE | F6: =IF($B6="","",IF($B6=$B5,F5+1,1)) -> 5 | G6: Core
A7: {=IFERROR(_xlfn.XLOOKUP(B7, Runs[Run ID], Runs[Track]), "— pick a run —")} -> Hickman Saga | B7: hickman-secret-warriors | C7: {=IFERROR(_xlfn.XLOOKUP(B7, Runs[Run ID], Runs[Title]), "— pick a run —")} -> Secret Warriors | D7: Secret Warriors #5 | E7: TRUE | F7: =IF($B7="","",IF($B7=$B6,F6+1,1)) -> 6 | G7: Core
A8: {=IFERROR(_xlfn.XLOOKUP(B8, Runs[Run ID], Runs[Track]), "— pick a run —")} -> Hickman Saga | B8: hickman-secret-warriors | C8: {=IFERROR(_xlfn.XLOOKUP(B8, Runs[Run ID], Runs[Title]), "— pick a run —")} -> Secret Warriors | D8: Secret Warriors #6 | E8: TRUE | F8: =IF($B8="","",IF($B8=$B7,F7+1,1)) -> 7 | G8: Core
A9: {=IFERROR(_xlfn.XLOOKUP(B9, Runs[Run ID], Runs[Track]), "— pick a run —")} -> Hickman Saga | B9: hickman-secret-warriors | C9: {=IFERROR(_xlfn.XLOOKUP(B9, Runs[Run ID], Runs[Title]), "— pick a run —")} -> Secret Warriors | D9: Secret Warriors #7 | E9: TRUE | F9: =IF($B9="","",IF($B9=$B8,F8+1,1)) -> 8 | G9: Core
A10: {=IFERROR(_xlfn.XLOOKUP(B10, Runs[Run ID], Runs[Track]), "— pick a run —")} -> Hickman Saga | B10: hickman-secret-warriors | C10: {=IFERROR(_xlfn.XLOOKUP(B10, Runs[Run ID], Runs[Title]), "— pick a run —")} -> Secret Warriors | D10: Secret Warriors #8 | E10: TRUE | F10: =IF($B10="","",IF($B10=$B9,F9+1,1)) -> 9 | G10: Core
A11: {=IFERROR(_xlfn.XLOOKUP(B11, Runs[Run ID], Runs[Track]), "— pick a run —")} -> Hickman Saga | B11: hickman-secret-warriors | C11: {=IFERROR(_xlfn.XLOOKUP(B11, Runs[Run ID], Runs[Title]), "— pick a run —")} -> Secret Warriors | D11: Secret Warriors #9 | E11: TRUE | F11: =IF($B11="","",IF($B11=$B10,F10+1,1)) -> 10 | G11: Core
A12: {=IFERROR(_xlfn.XLOOKUP(B12, Runs[Run ID], Runs[Track]), "— pick a run —")} -> Hickman Saga | B12: hickman-secret-warriors | C12: {=IFERROR(_xlfn.XLOOKUP(B12, Runs[Run ID], Runs[Title]), "— pick a run —")} -> Secret Warriors | D12: Dark Reign: The List - Secret Warriors | E12: TRUE | F12: =IF($B12="","",IF($B12=$B11,F11+1,1)) -> 11 | G12: Core
A13: {=IFERROR(_xlfn.XLOOKUP(B13, Runs[Run ID], Runs[Track]), "— pick a run —")} -> Hickman Saga | B13: hickman-secret-warriors | C13: {=IFERROR(_xlfn.XLOOKUP(B13, Runs[Run ID], Runs[Title]), "— pick a run —")} -> Secret Warriors | D13: Secret Warriors #10 | E13: TRUE | F13: =IF($B13="","",IF($B13=$B12,F12+1,1)) -> 12 | G13: Core
A14: {=IFERROR(_xlfn.XLOOKUP(B14, Runs[Run ID], Runs[Track]), "— pick a run —")} -> Hickman Saga | B14: hickman-secret-warriors | C14: {=IFERROR(_xlfn.XLOOKUP(B14, Runs[Run ID], Runs[Title]), "— pick a run —")} -> Secret Warriors | D14: Secret Warriors #11 | E14: TRUE | F14: =IF($B14="","",IF($B14=$B13,F13+1,1)) -> 13 | G14: Core
A15: {=IFERROR(_xlfn.XLOOKUP(B15, Runs[Run ID], Runs[Track]), "— pick a run —")} -> Hickman Saga | B15: hickman-secret-warriors | C15: {=IFERROR(_xlfn.XLOOKUP(B15, Runs[Run ID], Runs[Title]), "— pick a run —")} -> Secret Warriors | D15: Secret Warriors #12 | E15: TRUE | F15: =IF($B15="","",IF($B15=$B14,F14+1,1)) -> 14 | G15: Core
... A32: {=IFERROR(_xlfn.XLOOKUP(B32, Runs[Run ID], Runs[Track]), "— pick a run —")} -> Hickman Saga | B32: hickman-secret-warriors | C32: {=IFERROR(_xlfn.XLOOKUP(B32, Runs[Run ID], Runs[Title]), "— pick a run —")} -> Secret Warriors | D32: Secret Warriors #28 | E32: TRUE | F32: =IF($B32="","",IF($B32=$B31,F31+1,1)) -> 31 | G32: Core
A33: {=IFERROR(_xlfn.XLOOKUP(B33, Runs[Run ID], Runs[Track]), "— pick a run —")} -> Hickman Saga | B33: hickman-ff | C33: {=IFERROR(_xlfn.XLOOKUP(B33, Runs[Run ID], Runs[Title]), "— pick a run —")} -> Hickman's Fantastic Four / FF | D33: Dark Reign: Fantastic Four #1 | E33: TRUE | F33: =IF($B33="","",IF($B33=$B32,F32+1,1)) -> 1 | G33: Core | H33: Hickman's audition. Introduces the multiversal-Reed idea.
A34: {=IFERROR(_xlfn.XLOOKUP(B34, Runs[Run ID], Runs[Track]), "— pick a run —")} -> Hickman Saga | B34: hickman-ff | C34: {=IFERROR(_xlfn.XLOOKUP(B34, Runs[Run ID], Runs[Title]), "— pick a run —")} -> Hickman's Fantastic Four / FF | D34: Dark Reign: Fantastic Four #2 | E34: TRUE | F34: =IF($B34="","",IF($B34=$B33,F33+1,1)) -> 2 | G34: Core
A35: {=IFERROR(_xlfn.XLOOKUP(B35, Runs[Run ID], Runs[Track]), "— pick a run —")} -> Hickman Saga | B35: hickman-ff | C35: {=IFERROR(_xlfn.XLOOKUP(B35, Runs[Run ID], Runs[Title]), "— pick a run —")} -> Hickman's Fantastic Four / FF | D35: Dark Reign: Fantastic Four #3 | E35: TRUE | F35: =IF($B35="","",IF($B35=$B34,F34+1,1)) -> 3 | G35: Core
A36: {=IFERROR(_xlfn.XLOOKUP(B36, Runs[Run ID], Runs[Track]), "— pick a run —")} -> Hickman Saga | B36: hickman-ff | C36: {=IFERROR(_xlfn.XLOOKUP(B36, Runs[Run ID], Runs[Title]), "— pick a run —")} -> Hickman's Fantastic Four / FF | D36: Dark Reign: Fantastic Four #4 | E36: TRUE | F36: =IF($B36="","",IF($B36=$B35,F35+1,1)) -> 4 | G36: Core
A37: {=IFERROR(_xlfn.XLOOKUP(B37, Runs[Run ID], Runs[Track]), "— pick a run —")} -> Hickman Saga | B37: hickman-ff | C37: {=IFERROR(_xlfn.XLOOKUP(B37, Runs[Run ID], Runs[Title]), "— pick a run —")} -> Hickman's Fantastic Four / FF | D37: Dark Reign: Fantastic Four #5 | E37: TRUE | F37: =IF($B37="","",IF($B37=$B36,F36+1,1)) -> 5 | G37: Core
A38: {=IFERROR(_xlfn.XLOOKUP(B38, Runs[Run ID], Runs[Track]), "— pick a run —")} -> Hickman Saga | B38: hickman-ff | C38: {=IFERROR(_xlfn.XLOOKUP(B38, Runs[Run ID], Runs[Title]), "— pick a run —")} -> Hickman's Fantastic Four / FF | D38: Dark Reign: The Cabal | E38: TRUE | F38: =IF($B38="","",IF($B38=$B37,F37+1,1)) -> 6 | G38: Core | H38: Hickman writes the FF segment.
A39: {=IFERROR(_xlfn.XLOOKUP(B39, Runs[Run ID], Runs[Track]), "— pick a run —")} -> Hickman Saga | B39: hickman-ff | C39: {=IFERROR(_xlfn.XLOOKUP(B39, Runs[Run ID], Runs[Title]), "— pick a run —")} -> Hickman's Fantastic Four / FF | D39: Fantastic Four (1998) #570 | E39: TRUE | F39: =IF($B39="","",IF($B39=$B38,F38+1,1)) -> 7 | G39: Core | H39: "Solve Everything" through the silent issue.
A40: {=IFERROR(_xlfn.XLOOKUP(B40, Runs[Run ID], Runs[Track]), "— pick a run —")} -> Hickman Saga | B40: hickman-ff | C40: {=IFERROR(_xlfn.XLOOKUP(B40, Runs[Run ID], Runs[Title]), "— pick a run —")} -> Hickman's Fantastic Four / FF | D40: Fantastic Four (1998) #571 | E40: TRUE | F40: =IF($B40="","",IF($B40=$B39,F39+1,1)) -> 8 | G40: Core
A41: {=IFERROR(_xlfn.XLOOKUP(B41, Runs[Run ID], Runs[Track]), "— pick a run —")} -> Hickman Saga | B41: hickman-ff | C41: {=IFERROR(_xlfn.XLOOKUP(B41, Runs[Run ID], Runs[Title]), "— pick a run —")} -> Hickman's Fantastic Four / FF | D41: Fantastic Four (1998) #572 | E41: TRUE | F41: =IF($B41="","",IF($B41=$B40,F40+1,1)) -> 9 | G41: Core
A42: {=IFERROR(_xlfn.XLOOKUP(B42, Runs[Run ID], Runs[Track]), "— pick a run —")} -> Hickman Saga | B42: hickman-ff | C42: {=IFERROR(_xlfn.XLOOKUP(B42, Runs[Run ID], Runs[Title]), "— pick a run —")} -> Hickman's Fantastic Four / FF | D42: Fantastic Four (1998) #573 | E42: TRUE | F42: =IF($B42="","",IF($B42=$B41,F41+1,1)) -> 10 | G42: Core
A43: {=IFERROR(_xlfn.XLOOKUP(B43, Runs[Run ID], Runs[Track]), "— pick a run —")} -> Hickman Saga | B43: hickman-ff | C43: {=IFERROR(_xlfn.XLOOKUP(B43, Runs[Run ID], Runs[Title]), "— pick a run —")} -> Hickman's Fantastic Four / FF | D43: Fantastic Four (1998) #574 | E43: TRUE | F43: =IF($B43="","",IF($B43=$B42,F42+1,1)) -> 11 | G43: Core
A44: {=IFERROR(_xlfn.XLOOKUP(B44, Runs[Run ID], Runs[Track]), "— pick a run —")} -> Hickman Saga | B44: hickman-ff | C44: {=IFERROR(_xlfn.XLOOKUP(B44, Runs[Run ID], Runs[Title]), "— pick a run —")} -> Hickman's Fantastic Four / FF | D44: Fantastic Four (1998) #575 | E44: TRUE | F44: =IF($B44="","",IF($B44=$B43,F43+1,1)) -> 12 | G44: Core
A45: {=IFERROR(_xlfn.XLOOKUP(B45, Runs[Run ID], Runs[Track]), "— pick a run —")} -> Hickman Saga | B45: hickman-ff | C45: {=IFERROR(_xlfn.XLOOKUP(B45, Runs[Run ID], Runs[Title]), "— pick a run —")} -> Hickman's Fantastic Four / FF | D45: Fantastic Four (1998) #576 | E45: TRUE | F45: =IF($B45="","",IF($B45=$B44,F44+1,1)) -> 13 | G45: Core
A46: {=IFERROR(_xlfn.XLOOKUP(B46, Runs[Run ID], Runs[Track]), "— pick a run —")} -> Hickman Saga | B46: hickman-ff | C46: {=IFERROR(_xlfn.XLOOKUP(B46, Runs[Run ID], Runs[Title]), "— pick a run —")} -> Hickman's Fantastic Four / FF | D46: Fantastic Four (1998) #577 | E46: TRUE | F46: =IF($B46="","",IF($B46=$B45,F45+1,1)) -> 14 | G46: Core
A47: {=IFERROR(_xlfn.XLOOKUP(B47, Runs[Run ID], Runs[Track]), "— pick a run —")} -> Hickman Saga | B47: hickman-ff | C47: {=IFERROR(_xlfn.XLOOKUP(B47, Runs[Run ID], Runs[Title]), "— pick a run —")} -> Hickman's Fantastic Four / FF | D47: Fantastic Four (1998) #578 | E47: TRUE | F47: =IF($B47="","",IF($B47=$B46,F46+1,1)) -> 15 | G47: Core
A48: {=IFERROR(_xlfn.XLOOKUP(B48, Runs[Run ID], Runs[Track]), "— pick a run —")} -> Hickman Saga | B48: hickman-ff | C48: {=IFERROR(_xlfn.XLOOKUP(B48, Runs[Run ID], Runs[Title]), "— pick a run —")} -> Hickman's Fantastic Four / FF | D48: Fantastic Four (1998) #579 | E48: TRUE | F48: =IF($B48="","",IF($B48=$B47,F47+1,1)) -> 16 | G48: Core
A49: {=IFERROR(_xlfn.XLOOKUP(B49, Runs[Run ID], Runs[Track]), "— pick a run —")} -> Hickman Saga | B49: hickman-ff | C49: {=IFERROR(_xlfn.XLOOKUP(B49, Runs[Run ID], Runs[Title]), "— pick a run —")} -> Hickman's Fantastic Four / FF | D49: Fantastic Four (1998) #580 | E49: TRUE | F49: =IF($B49="","",IF($B49=$B48,F48+1,1)) -> 17 | G49: Core
A50: {=IFERROR(_xlfn.XLOOKUP(B50, Runs[Run ID], Runs[Track]), "— pick a run —")} -> Hickman Saga | B50: hickman-ff | C50: {=IFERROR(_xlfn.XLOOKUP(B50, Runs[Run ID], Runs[Title]), "— pick a run —")} -> Hickman's Fantastic Four / FF | D50: Fantastic Four (1998) #581 | E50: TRUE | F50: =IF($B50="","",IF($B50=$B49,F49+1,1)) -> 18 | G50: Core
A51: {=IFERROR(_xlfn.XLOOKUP(B51, Runs[Run ID], Runs[Track]), "— pick a run —")} -> Hickman Saga | B51: hickman-ff | C51: {=IFERROR(_xlfn.XLOOKUP(B51, Runs[Run ID], Runs[Title]), "— pick a run —")} -> Hickman's Fantastic Four / FF | D51: Fantastic Four (1998) #582 | E51: TRUE | F51: =IF($B51="","",IF($B51=$B50,F50+1,1)) -> 19 | G51: Core
... A78: {=IFERROR(_xlfn.XLOOKUP(B78, Runs[Run ID], Runs[Track]), "— pick a run —")} -> Hickman Saga | B78: hickman-ff | C78: {=IFERROR(_xlfn.XLOOKUP(B78, Runs[Run ID], Runs[Title]), "— pick a run —")} -> Hickman's Fantastic Four / FF | D78: FF (2011) #16 | E78: FALSE | F78: =IF($B78="","",IF($B78=$B77,F77+1,1)) -> 46 | G78: Core
A79: {=IFERROR(_xlfn.XLOOKUP(B79, Runs[Run ID], Runs[Track]), "— pick a run —")} -> Hickman Saga | B79: hickman-ff | C79: {=IFERROR(_xlfn.XLOOKUP(B79, Runs[Run ID], Runs[Title]), "— pick a run —")} -> Hickman's Fantastic Four / FF | D79: Fantastic Four (2012) #605 | E79: FALSE | F79: =IF($B79="","",IF($B79=$B78,F78+1,1)) -> 47 | G79: Core | H79: The "Reed and Sue grow old" done-in-one. Best single issue of the run.
A80: {=IFERROR(_xlfn.XLOOKUP(B80, Runs[Run ID], Runs[Track]), "— pick a run —")} -> Hickman Saga | B80: hickman-ff | C80: {=IFERROR(_xlfn.XLOOKUP(B80, Runs[Run ID], Runs[Title]), "— pick a run —")} -> Hickman's Fantastic Four / FF | D80: Fantastic Four (2012) #605.1 | E80: FALSE | F80: =IF($B80="","",IF($B80=$B79,F79+1,1)) -> 48 | G80: Core
A81: {=IFERROR(_xlfn.XLOOKUP(B81, Runs[Run ID], Runs[Track]), "— pick a run —")} -> Hickman Saga | B81: hickman-ff | C81: {=IFERROR(_xlfn.XLOOKUP(B81, Runs[Run ID], Runs[Title]), "— pick a run —")} -> Hickman's Fantastic Four / FF | D81: Fantastic Four (2012) #606 | E81: FALSE | F81: =IF($B81="","",IF($B81=$B80,F80+1,1)) -> 49 | G81: Core
A82: {=IFERROR(_xlfn.XLOOKUP(B82, Runs[Run ID], Runs[Track]), "— pick a run —")} -> Hickman Saga | B82: hickman-ff | C82: {=IFERROR(_xlfn.XLOOKUP(B82, Runs[Run ID], Runs[Title]), "— pick a run —")} -> Hickman's Fantastic Four / FF | D82: FF (2011) #17 | E82: FALSE | F82: =IF($B82="","",IF($B82=$B81,F81+1,1)) -> 50 | G82: Core
A83: {=IFERROR(_xlfn.XLOOKUP(B83, Runs[Run ID], Runs[Track]), "— pick a run —")} -> Hickman Saga | B83: hickman-ff | C83: {=IFERROR(_xlfn.XLOOKUP(B83, Runs[Run ID], Runs[Title]), "— pick a run —")} -> Hickman's Fantastic Four / FF | D83: FF (2011) #18 | E83: FALSE | F83: =IF($B83="","",IF($B83=$B82,F82+1,1)) -> 51 | G83: Core
A84: {=IFERROR(_xlfn.XLOOKUP(B84, Runs[Run ID], Runs[Track]), "— pick a run —")} -> Hickman Saga | B84: hickman-ff | C84: {=IFERROR(_xlfn.XLOOKUP(B84, Runs[Run ID], Runs[Title]), "— pick a run —")} -> Hickman's Fantastic Four / FF | D84: Fantastic Four (2012) #607 | E84: FALSE | F84: =IF($B84="","",IF($B84=$B83,F83+1,1)) -> 52 | G84: Core
A85: {=IFERROR(_xlfn.XLOOKUP(B85, Runs[Run ID], Runs[Track]), "— pick a run —")} -> Hickman Saga | B85: hickman-ff | C85: {=IFERROR(_xlfn.XLOOKUP(B85, Runs[Run ID], Runs[Title]), "— pick a run —")} -> Hickman's Fantastic Four / FF | D85: Fantastic Four (2012) #608 | E85: FALSE | F85: =IF($B85="","",IF($B85=$B84,F84+1,1)) -> 53 | G85: Core
A86: {=IFERROR(_xlfn.XLOOKUP(B86, Runs[Run ID], Runs[Track]), "— pick a run —")} -> Hickman Saga | B86: hickman-ff | C86: {=IFERROR(_xlfn.XLOOKUP(B86, Runs[Run ID], Runs[Title]), "— pick a run —")} -> Hickman's Fantastic Four / FF | D86: FF (2011) #19 | E86: FALSE | F86: =IF($B86="","",IF($B86=$B85,F85+1,1)) -> 54 | G86: Core
A87: {=IFERROR(_xlfn.XLOOKUP(B87, Runs[Run ID], Runs[Track]), "— pick a run —")} -> Hickman Saga | B87: hickman-ff | C87: {=IFERROR(_xlfn.XLOOKUP(B87, Runs[Run ID], Runs[Title]), "— pick a run —")} -> Hickman's Fantastic Four / FF | D87: FF (2011) #20 | E87: FALSE | F87: =IF($B87="","",IF($B87=$B86,F86+1,1)) -> 55 | G87: Core
A88: {=IFERROR(_xlfn.XLOOKUP(B88, Runs[Run ID], Runs[Track]), "— pick a run —")} -> Hickman Saga | B88: hickman-ff | C88: {=IFERROR(_xlfn.XLOOKUP(B88, Runs[Run ID], Runs[Title]), "— pick a run —")} -> Hickman's Fantastic Four / FF | D88: FF (2011) #21 | E88: FALSE | F88: =IF($B88="","",IF($B88=$B87,F87+1,1)) -> 56 | G88: Core
A89: {=IFERROR(_xlfn.XLOOKUP(B89, Runs[Run ID], Runs[Track]), "— pick a run —")} -> Hickman Saga | B89: hickman-ff | C89: {=IFERROR(_xlfn.XLOOKUP(B89, Runs[Run ID], Runs[Title]), "— pick a run —")} -> Hickman's Fantastic Four / FF | D89: Fantastic Four (2012) #609 | E89: FALSE | F89: =IF($B89="","",IF($B89=$B88,F88+1,1)) -> 57 | G89: Core
A90: {=IFERROR(_xlfn.XLOOKUP(B90, Runs[Run ID], Runs[Track]), "— pick a run —")} -> Hickman Saga | B90: hickman-ff | C90: {=IFERROR(_xlfn.XLOOKUP(B90, Runs[Run ID], Runs[Title]), "— pick a run —")} -> Hickman's Fantastic Four / FF | D90: Fantastic Four (2012) #610 | E90: FALSE | F90: =IF($B90="","",IF($B90=$B89,F89+1,1)) -> 58 | G90: Core
A91: {=IFERROR(_xlfn.XLOOKUP(B91, Runs[Run ID], Runs[Track]), "— pick a run —")} -> Hickman Saga | B91: hickman-ff | C91: {=IFERROR(_xlfn.XLOOKUP(B91, Runs[Run ID], Runs[Title]), "— pick a run —")} -> Hickman's Fantastic Four / FF | D91: FF (2011) #22 | E91: FALSE | F91: =IF($B91="","",IF($B91=$B90,F90+1,1)) -> 59 | G91: Core
... A124: {=IFERROR(_xlfn.XLOOKUP(B124, Runs[Run ID], Runs[Track]), "— pick a run —")} -> Hickman Saga | B124: bendis-doomsday | C124: {=IFERROR(_xlfn.XLOOKUP(B124, Runs[Run ID], Runs[Title]), "— pick a run —")} -> Ultimate Doomsday | D124: Ultimate Doom #4 | E124: FALSE | F124: =IF($B124="","",IF($B124=$B123,F123+1,1)) -> 12 | G124: Core
A125: {=IFERROR(_xlfn.XLOOKUP(B125, Runs[Run ID], Runs[Track]), "— pick a run —")} -> Hickman Saga | B125: hickman-ultimates | C125: {=IFERROR(_xlfn.XLOOKUP(B125, Runs[Run ID], Runs[Title]), "— pick a run —")} -> Ultimate Comics: Ultimates | D125: Ultimate Thor (2010) #1 | E125: FALSE | F125: =IF($B125="","",IF($B125=$B124,F124+1,1)) -> 1 | G125: Core | H125: Hickman, with Carlos Pacheco. Sets up the Asgard material he then uses in The Ultimates.
A126: {=IFERROR(_xlfn.XLOOKUP(B126, Runs[Run ID], Runs[Track]), "— pick a run —")} -> Hickman Saga | B126: hickman-ultimates | C126: {=IFERROR(_xlfn.XLOOKUP(B126, Runs[Run ID], Runs[Title]), "— pick a run —")} -> Ultimate Comics: Ultimates | D126: Ultimate Thor (2010) #2 | E126: FALSE | F126: =IF($B126="","",IF($B126=$B125,F125+1,1)) -> 2 | G126: Core
A127: {=IFERROR(_xlfn.XLOOKUP(B127, Runs[Run ID], Runs[Track]), "— pick a run —")} -> Hickman Saga | B127: hickman-ultimates | C127: {=IFERROR(_xlfn.XLOOKUP(B127, Runs[Run ID], Runs[Title]), "— pick a run —")} -> Ultimate Comics: Ultimates | D127: Ultimate Thor (2010) #3 | E127: FALSE | F127: =IF($B127="","",IF($B127=$B126,F126+1,1)) -> 3 | G127: Core
A128: {=IFERROR(_xlfn.XLOOKUP(B128, Runs[Run ID], Runs[Track]), "— pick a run —")} -> Hickman Saga | B128: hickman-ultimates | C128: {=IFERROR(_xlfn.XLOOKUP(B128, Runs[Run ID], Runs[Title]), "— pick a run —")} -> Ultimate Comics: Ultimates | D128: Ultimate Thor (2010) #4 | E128: FALSE | F128: =IF($B128="","",IF($B128=$B127,F127+1,1)) -> 4 | G128: Core
A129: {=IFERROR(_xlfn.XLOOKUP(B129, Runs[Run ID], Runs[Track]), "— pick a run —")} -> Hickman Saga | B129: hickman-ultimates | C129: {=IFERROR(_xlfn.XLOOKUP(B129, Runs[Run ID], Runs[Title]), "— pick a run —")} -> Ultimate Comics: Ultimates | D129: Ultimate Fallout #1 | E129: FALSE | F129: =IF($B129="","",IF($B129=$B128,F128+1,1)) -> 5 | G129: Recommended | H129: Post–Death of Spider-Man. Miles Morales debuts in #4.
A130: {=IFERROR(_xlfn.XLOOKUP(B130, Runs[Run ID], Runs[Track]), "— pick a run —")} -> Hickman Saga | B130: hickman-ultimates | C130: {=IFERROR(_xlfn.XLOOKUP(B130, Runs[Run ID], Runs[Title]), "— pick a run —")} -> Ultimate Comics: Ultimates | D130: Ultimate Fallout #2 | E130: FALSE | F130: =IF($B130="","",IF($B130=$B129,F129+1,1)) -> 6 | G130: Recommended
A131: {=IFERROR(_xlfn.XLOOKUP(B131, Runs[Run ID], Runs[Track]), "— pick a run —")} -> Hickman Saga | B131: hickman-ultimates | C131: {=IFERROR(_xlfn.XLOOKUP(B131, Runs[Run ID], Runs[Title]), "— pick a run —")} -> Ultimate Comics: Ultimates | D131: Ultimate Fallout #3 | E131: FALSE | F131: =IF($B131="","",IF($B131=$B130,F130+1,1)) -> 7 | G131: Recommended
A132: {=IFERROR(_xlfn.XLOOKUP(B132, Runs[Run ID], Runs[Track]), "— pick a run —")} -> Hickman Saga | B132: hickman-ultimates | C132: {=IFERROR(_xlfn.XLOOKUP(B132, Runs[Run ID], Runs[Title]), "— pick a run —")} -> Ultimate Comics: Ultimates | D132: Ultimate Fallout #4 | E132: FALSE | F132: =IF($B132="","",IF($B132=$B131,F131+1,1)) -> 8 | G132: Recommended
A133: {=IFERROR(_xlfn.XLOOKUP(B133, Runs[Run ID], Runs[Track]), "— pick a run —")} -> Hickman Saga | B133: hickman-ultimates | C133: {=IFERROR(_xlfn.XLOOKUP(B133, Runs[Run ID], Runs[Title]), "— pick a run —")} -> Ultimate Comics: Ultimates | D133: Ultimate Fallout #5 | E133: FALSE | F133: =IF($B133="","",IF($B133=$B132,F132+1,1)) -> 9 | G133: Recommended
A134: {=IFERROR(_xlfn.XLOOKUP(B134, Runs[Run ID], Runs[Track]), "— pick a run —")} -> Hickman Saga | B134: hickman-ultimates | C134: {=IFERROR(_xlfn.XLOOKUP(B134, Runs[Run ID], Runs[Title]), "— pick a run —")} -> Ultimate Comics: Ultimates | D134: Ultimate Fallout #6 | E134: FALSE | F134: =IF($B134="","",IF($B134=$B133,F133+1,1)) -> 10 | G134: Recommended
A135: {=IFERROR(_xlfn.XLOOKUP(B135, Runs[Run ID], Runs[Track]), "— pick a run —")} -> Hickman Saga | B135: hickman-ultimates | C135: {=IFERROR(_xlfn.XLOOKUP(B135, Runs[Run ID], Runs[Title]), "— pick a run —")} -> Ultimate Comics: Ultimates | D135: Ultimate Comics: The Ultimates #1 | E135: FALSE | F135: =IF($B135="","",IF($B135=$B134,F134+1,1)) -> 11 | G135: Core
A136: {=IFERROR(_xlfn.XLOOKUP(B136, Runs[Run ID], Runs[Track]), "— pick a run —")} -> Hickman Saga | B136: hickman-ultimates | C136: {=IFERROR(_xlfn.XLOOKUP(B136, Runs[Run ID], Runs[Title]), "— pick a run —")} -> Ultimate Comics: Ultimates | D136: Ultimate Comics: The Ultimates #2 | E136: FALSE | F136: =IF($B136="","",IF($B136=$B135,F135+1,1)) -> 12 | G136: Core
A137: {=IFERROR(_xlfn.XLOOKUP(B137, Runs[Run ID], Runs[Track]), "— pick a run —")} -> Hickman Saga | B137: hickman-ultimates | C137: {=IFERROR(_xlfn.XLOOKUP(B137, Runs[Run ID], Runs[Title]), "— pick a run —")} -> Ultimate Comics: Ultimates | D137: Ultimate Comics: The Ultimates #3 | E137: FALSE | F137: =IF($B137="","",IF($B137=$B136,F136+1,1)) -> 13 | G137: Core
A138: {=IFERROR(_xlfn.XLOOKUP(B138, Runs[Run ID], Runs[Track]), "— pick a run —")} -> Hickman Saga | B138: hickman-ultimates | C138: {=IFERROR(_xlfn.XLOOKUP(B138, Runs[Run ID], Runs[Title]), "— pick a run —")} -> Ultimate Comics: Ultimates | D138: Ultimate Comics: The Ultimates #4 | E138: FALSE | F138: =IF($B138="","",IF($B138=$B137,F137+1,1)) -> 14 | G138: Core
A139: {=IFERROR(_xlfn.XLOOKUP(B139, Runs[Run ID], Runs[Track]), "— pick a run —")} -> Hickman Saga | B139: hickman-ultimates | C139: {=IFERROR(_xlfn.XLOOKUP(B139, Runs[Run ID], Runs[Title]), "— pick a run —")} -> Ultimate Comics: Ultimates | D139: Ultimate Hawkeye (2011) #1 | E139: FALSE | F139: =IF($B139="","",IF($B139=$B138,F138+1,1)) -> 15 | G139: Core
A140: {=IFERROR(_xlfn.XLOOKUP(B140, Runs[Run ID], Runs[Track]), "— pick a run —")} -> Hickman Saga | B140: hickman-ultimates | C140: {=IFERROR(_xlfn.XLOOKUP(B140, Runs[Run ID], Runs[Title]), "— pick a run —")} -> Ultimate Comics: Ultimates | D140: Ultimate Hawkeye (2011) #2 | E140: FALSE | F140: =IF($B140="","",IF($B140=$B139,F139+1,1)) -> 16 | G140: Core
A141: {=IFERROR(_xlfn.XLOOKUP(B141, Runs[Run ID], Runs[Track]), "— pick a run —")} -> Hickman Saga | B141: hickman-ultimates | C141: {=IFERROR(_xlfn.XLOOKUP(B141, Runs[Run ID], Runs[Title]), "— pick a run —")} -> Ultimate Comics: Ultimates | D141: Ultimate Hawkeye (2011) #3 | E141: FALSE | F141: =IF($B141="","",IF($B141=$B140,F140+1,1)) -> 17 | G141: Core
A142: {=IFERROR(_xlfn.XLOOKUP(B142, Runs[Run ID], Runs[Track]), "— pick a run —")} -> Hickman Saga | B142: hickman-ultimates | C142: {=IFERROR(_xlfn.XLOOKUP(B142, Runs[Run ID], Runs[Title]), "— pick a run —")} -> Ultimate Comics: Ultimates | D142: Ultimate Hawkeye (2011) #4 | E142: FALSE | F142: =IF($B142="","",IF($B142=$B141,F141+1,1)) -> 18 | G142: Core
A143: {=IFERROR(_xlfn.XLOOKUP(B143, Runs[Run ID], Runs[Track]), "— pick a run —")} -> Hickman Saga | B143: hickman-ultimates | C143: {=IFERROR(_xlfn.XLOOKUP(B143, Runs[Run ID], Runs[Title]), "— pick a run —")} -> Ultimate Comics: Ultimates | D143: Ultimate Comics: The Ultimates #5 | E143: FALSE | F143: =IF($B143="","",IF($B143=$B142,F142+1,1)) -> 19 | G143: Core | H143: Note: Sam Humphries starts co-writing at #10, and takes over solo at #13 — so #12 is a clean stopping point and you have it right.
A144: {=IFERROR(_xlfn.XLOOKUP(B144, Runs[Run ID], Runs[Track]), "— pick a run —")} -> Hickman Saga | B144: hickman-ultimates | C144: {=IFERROR(_xlfn.XLOOKUP(B144, Runs[Run ID], Runs[Title]), "— pick a run —")} -> Ultimate Comics: Ultimates | D144: Ultimate Comics: The Ultimates #6 | E144: FALSE | F144: =IF($B144="","",IF($B144=$B143,F143+1,1)) -> 20 | G144: Core
A145: {=IFERROR(_xlfn.XLOOKUP(B145, Runs[Run ID], Runs[Track]), "— pick a run —")} -> Hickman Saga | B145: hickman-ultimates | C145: {=IFERROR(_xlfn.XLOOKUP(B145, Runs[Run ID], Runs[Title]), "— pick a run —")} -> Ultimate Comics: Ultimates | D145: Ultimate Comics: The Ultimates #7 | E145: FALSE | F145: =IF($B145="","",IF($B145=$B144,F144+1,1)) -> 21 | G145: Core
A146: {=IFERROR(_xlfn.XLOOKUP(B146, Runs[Run ID], Runs[Track]), "— pick a run —")} -> Hickman Saga | B146: hickman-ultimates | C146: {=IFERROR(_xlfn.XLOOKUP(B146, Runs[Run ID], Runs[Title]), "— pick a run —")} -> Ultimate Comics: Ultimates | D146: Ultimate Comics: The Ultimates #8 | E146: FALSE | F146: =IF($B146="","",IF($B146=$B145,F145+1,1)) -> 22 | G146: Core
A147: {=IFERROR(_xlfn.XLOOKUP(B147, Runs[Run ID], Runs[Track]), "— pick a run —")} -> Hickman Saga | B147: hickman-ultimates | C147: {=IFERROR(_xlfn.XLOOKUP(B147, Runs[Run ID], Runs[Title]), "— pick a run —")} -> Ultimate Comics: Ultimates | D147: Ultimate Comics: The Ultimates #9 | E147: FALSE | F147: =IF($B147="","",IF($B147=$B146,F146+1,1)) -> 23 | G147: Core
A148: {=IFERROR(_xlfn.XLOOKUP(B148, Runs[Run ID], Runs[Track]), "— pick a run —")} -> Hickman Saga | B148: hickman-ultimates | C148: {=IFERROR(_xlfn.XLOOKUP(B148, Runs[Run ID], Runs[Title]), "— pick a run —")} -> Ultimate Comics: Ultimates | D148: Ultimate Comics: The Ultimates #10 | E148: FALSE | F148: =IF($B148="","",IF($B148=$B147,F147+1,1)) -> 24 | G148: Core
A149: {=IFERROR(_xlfn.XLOOKUP(B149, Runs[Run ID], Runs[Track]), "— pick a run —")} -> Hickman Saga | B149: hickman-ultimates | C149: {=IFERROR(_xlfn.XLOOKUP(B149, Runs[Run ID], Runs[Title]), "— pick a run —")} -> Ultimate Comics: Ultimates | D149: Ultimate Comics: The Ultimates #11 | E149: FALSE | F149: =IF($B149="","",IF($B149=$B148,F148+1,1)) -> 25 | G149: Core
A150: {=IFERROR(_xlfn.XLOOKUP(B150, Runs[Run ID], Runs[Track]), "— pick a run —")} -> Hickman Saga | B150: hickman-ultimates | C150: {=IFERROR(_xlfn.XLOOKUP(B150, Runs[Run ID], Runs[Title]), "— pick a run —")} -> Ultimate Comics: Ultimates | D150: Ultimate Comics: The Ultimates #12 | E150: FALSE | F150: =IF($B150="","",IF($B150=$B149,F149+1,1)) -> 26 | G150: Core
A151: {=IFERROR(_xlfn.XLOOKUP(B151, Runs[Run ID], Runs[Track]), "— pick a run —")} -> Hickman Saga | B151: hickman-avengers-world | C151: {=IFERROR(_xlfn.XLOOKUP(B151, Runs[Run ID], Runs[Title]), "— pick a run —")} -> Hickman's Avengers World | D151: Astonishing Tales (2009) #1 | E151: FALSE | F151: =IF($B151="","",IF($B151=$B150,F150+1,1)) -> 1 | G151: Optional | H151: Hickman + Nick Pitarra, starring Cannonball and Sunspot. Pure trivia — it's here because he clearly loved those two before he made them the heart of Avengers. Collected in the Avengers by Hickman omnibus, which is why it shows up on these lists.
A152: {=IFERROR(_xlfn.XLOOKUP(B152, Runs[Run ID], Runs[Track]), "— pick a run —")} -> Hickman Saga | B152: hickman-avengers-world | C152: {=IFERROR(_xlfn.XLOOKUP(B152, Runs[Run ID], Runs[Title]), "— pick a run —")} -> Hickman's Avengers World | D152: Astonishing Tales (2009) #2 | E152: FALSE | F152: =IF($B152="","",IF($B152=$B151,F151+1,1)) -> 2 | G152: Optional
A153: {=IFERROR(_xlfn.XLOOKUP(B153, Runs[Run ID], Runs[Track]), "— pick a run —")} -> Hickman Saga | B153: hickman-avengers-world | C153: {=IFERROR(_xlfn.XLOOKUP(B153, Runs[Run ID], Runs[Title]), "— pick a run —")} -> Hickman's Avengers World | D153: Astonishing Tales (2009) #3 | E153: FALSE | F153: =IF($B153="","",IF($B153=$B152,F152+1,1)) -> 3 | G153: Optional
A154: {=IFERROR(_xlfn.XLOOKUP(B154, Runs[Run ID], Runs[Track]), "— pick a run —")} -> Hickman Saga | B154: hickman-avengers-world | C154: {=IFERROR(_xlfn.XLOOKUP(B154, Runs[Run ID], Runs[Title]), "— pick a run —")} -> Hickman's Avengers World | D154: Astonishing Tales (2009) #4 | E154: FALSE | F154: =IF($B154="","",IF($B154=$B153,F153+1,1)) -> 4 | G154: Optional
A155: {=IFERROR(_xlfn.XLOOKUP(B155, Runs[Run ID], Runs[Track]), "— pick a run —")} -> Hickman Saga | B155: hickman-avengers-world | C155: {=IFERROR(_xlfn.XLOOKUP(B155, Runs[Run ID], Runs[Title]), "— pick a run —")} -> Hickman's Avengers World | D155: Astonishing Tales (2009) #5 | E155: FALSE | F155: =IF($B155="","",IF($B155=$B154,F154+1,1)) -> 5 | G155: Optional
A156: {=IFERROR(_xlfn.XLOOKUP(B156, Runs[Run ID], Runs[Track]), "— pick a run —")} -> Hickman Saga | B156: hickman-avengers-world | C156: {=IFERROR(_xlfn.XLOOKUP(B156, Runs[Run ID], Runs[Title]), "— pick a run —")} -> Hickman's Avengers World | D156: Astonishing Tales (2009) #6 | E156: FALSE | F156: =IF($B156="","",IF($B156=$B155,F155+1,1)) -> 6 | G156: Optional
A157: {=IFERROR(_xlfn.XLOOKUP(B157, Runs[Run ID], Runs[Track]), "— pick a run —")} -> Hickman Saga | B157: hickman-avengers-world | C157: {=IFERROR(_xlfn.XLOOKUP(B157, Runs[Run ID], Runs[Title]), "— pick a run —")} -> Hickman's Avengers World | D157: Shang-Chi: Master of Kung Fu | E157: FALSE | F157: =IF($B157="","",IF($B157=$B156,F156+1,1)) -> 7 | G157: Optional | H157: A comedic Deadpool/Shang-Chi race. Same deal: it's in the collection, it's not part of the saga.
A158: {=IFERROR(_xlfn.XLOOKUP(B158, Runs[Run ID], Runs[Track]), "— pick a run —")} -> Hickman Saga | B158: hickman-avengers-world | C158: {=IFERROR(_xlfn.XLOOKUP(B158, Runs[Run ID], Runs[Title]), "— pick a run —")} -> Hickman's Avengers World | D158: New Avengers (2013) #1 | E158: FALSE | F158: =IF($B158="","",IF($B158=$B157,F157+1,1)) -> 8 | G158: Core
A159: {=IFERROR(_xlfn.XLOOKUP(B159, Runs[Run ID], Runs[Track]), "— pick a run —")} -> Hickman Saga | B159: hickman-avengers-world | C159: {=IFERROR(_xlfn.XLOOKUP(B159, Runs[Run ID], Runs[Title]), "— pick a run —")} -> Hickman's Avengers World | D159: New Avengers (2013) #2 | E159: FALSE | F159: =IF($B159="","",IF($B159=$B158,F158+1,1)) -> 9 | G159: Core
A160: {=IFERROR(_xlfn.XLOOKUP(B160, Runs[Run ID], Runs[Track]), "— pick a run —")} -> Hickman Saga | B160: hickman-avengers-world | C160: {=IFERROR(_xlfn.XLOOKUP(B160, Runs[Run ID], Runs[Title]), "— pick a run —")} -> Hickman's Avengers World | D160: New Avengers (2013) #3 | E160: FALSE | F160: =IF($B160="","",IF($B160=$B159,F159+1,1)) -> 10 | G160: Core
A161: {=IFERROR(_xlfn.XLOOKUP(B161, Runs[Run ID], Runs[Track]), "— pick a run —")} -> Hickman Saga | B161: hickman-avengers-world | C161: {=IFERROR(_xlfn.XLOOKUP(B161, Runs[Run ID], Runs[Title]), "— pick a run —")} -> Hickman's Avengers World | D161: Avengers (2013) #1 | E161: FALSE | F161: =IF($B161="","",IF($B161=$B160,F160+1,1)) -> 11 | G161: Core
A162: {=IFERROR(_xlfn.XLOOKUP(B162, Runs[Run ID], Runs[Track]), "— pick a run —")} -> Hickman Saga | B162: hickman-avengers-world | C162: {=IFERROR(_xlfn.XLOOKUP(B162, Runs[Run ID], Runs[Title]), "— pick a run —")} -> Hickman's Avengers World | D162: Avengers (2013) #2 | E162: FALSE | F162: =IF($B162="","",IF($B162=$B161,F161+1,1)) -> 12 | G162: Core
A163: {=IFERROR(_xlfn.XLOOKUP(B163, Runs[Run ID], Runs[Track]), "— pick a run —")} -> Hickman Saga | B163: hickman-avengers-world | C163: {=IFERROR(_xlfn.XLOOKUP(B163, Runs[Run ID], Runs[Title]), "— pick a run —")} -> Hickman's Avengers World | D163: Avengers (2013) #3 | E163: FALSE | F163: =IF($B163="","",IF($B163=$B162,F162+1,1)) -> 13 | G163: Core
A164: {=IFERROR(_xlfn.XLOOKUP(B164, Runs[Run ID], Runs[Track]), "— pick a run —")} -> Hickman Saga | B164: hickman-avengers-world | C164: {=IFERROR(_xlfn.XLOOKUP(B164, Runs[Run ID], Runs[Title]), "— pick a run —")} -> Hickman's Avengers World | D164: Avengers (2013) #4 | E164: FALSE | F164: =IF($B164="","",IF($B164=$B163,F163+1,1)) -> 14 | G164: Core
A165: {=IFERROR(_xlfn.XLOOKUP(B165, Runs[Run ID], Runs[Track]), "— pick a run —")} -> Hickman Saga | B165: hickman-avengers-world | C165: {=IFERROR(_xlfn.XLOOKUP(B165, Runs[Run ID], Runs[Title]), "— pick a run —")} -> Hickman's Avengers World | D165: New Avengers (2013) #4 | E165: FALSE | F165: =IF($B165="","",IF($B165=$B164,F164+1,1)) -> 15 | G165: Core
A166: {=IFERROR(_xlfn.XLOOKUP(B166, Runs[Run ID], Runs[Track]), "— pick a run —")} -> Hickman Saga | B166: hickman-avengers-world | C166: {=IFERROR(_xlfn.XLOOKUP(B166, Runs[Run ID], Runs[Title]), "— pick a run —")} -> Hickman's Avengers World | D166: Avengers (2013) #5 | E166: FALSE | F166: =IF($B166="","",IF($B166=$B165,F165+1,1)) -> 16 | G166: Core
A167: {=IFERROR(_xlfn.XLOOKUP(B167, Runs[Run ID], Runs[Track]), "— pick a run —")} -> Hickman Saga | B167: hickman-avengers-world | C167: {=IFERROR(_xlfn.XLOOKUP(B167, Runs[Run ID], Runs[Title]), "— pick a run —")} -> Hickman's Avengers World | D167: New Avengers (2013) #5 | E167: FALSE | F167: =IF($B167="","",IF($B167=$B166,F166+1,1)) -> 17 | G167: Core
A168: {=IFERROR(_xlfn.XLOOKUP(B168, Runs[Run ID], Runs[Track]), "— pick a run —")} -> Hickman Saga | B168: hickman-avengers-world | C168: {=IFERROR(_xlfn.XLOOKUP(B168, Runs[Run ID], Runs[Title]), "— pick a run —")} -> Hickman's Avengers World | D168: New Avengers (2013) #6 | E168: FALSE | F168: =IF($B168="","",IF($B168=$B167,F167+1,1)) -> 18 | G168: Core
A169: {=IFERROR(_xlfn.XLOOKUP(B169, Runs[Run ID], Runs[Track]), "— pick a run —")} -> Hickman Saga | B169: hickman-avengers-world | C169: {=IFERROR(_xlfn.XLOOKUP(B169, Runs[Run ID], Runs[Title]), "— pick a run —")} -> Hickman's Avengers World | D169: Avengers (2013) #6 | E169: FALSE | F169: =IF($B169="","",IF($B169=$B168,F168+1,1)) -> 19 | G169: Core
... A201: {=IFERROR(_xlfn.XLOOKUP(B201, Runs[Run ID], Runs[Track]), "— pick a run —")} -> Hickman Saga | B201: hickman-avengers | C201: {=IFERROR(_xlfn.XLOOKUP(B201, Runs[Run ID], Runs[Title]), "— pick a run —")} -> Hickman's Avengers / New Avengers | D201: New Avengers #15 | E201: FALSE | F201: =IF($B201="","",IF($B201=$B200,F200+1,1)) -> 2 | G201: Core
A202: {=IFERROR(_xlfn.XLOOKUP(B202, Runs[Run ID], Runs[Track]), "— pick a run —")} -> Hickman Saga | B202: hickman-avengers | C202: {=IFERROR(_xlfn.XLOOKUP(B202, Runs[Run ID], Runs[Title]), "— pick a run —")} -> Hickman's Avengers / New Avengers | D202: Avengers World #1 | E202: FALSE | F202: =IF($B202="","",IF($B202=$B201,F201+1,1)) -> 3 | G202: Optional | H202: Hickman co-writes with Spencer. Read it if you want more of the world-building — global threats, Avengers outposts — rather than the Illuminati plot. It connects to nothing downstream.
A203: {=IFERROR(_xlfn.XLOOKUP(B203, Runs[Run ID], Runs[Track]), "— pick a run —")} -> Hickman Saga | B203: hickman-avengers | C203: {=IFERROR(_xlfn.XLOOKUP(B203, Runs[Run ID], Runs[Title]), "— pick a run —")} -> Hickman's Avengers / New Avengers | D203: Avengers World #2 | E203: FALSE | F203: =IF($B203="","",IF($B203=$B202,F202+1,1)) -> 4 | G203: Optional
A204: {=IFERROR(_xlfn.XLOOKUP(B204, Runs[Run ID], Runs[Track]), "— pick a run —")} -> Hickman Saga | B204: hickman-avengers | C204: {=IFERROR(_xlfn.XLOOKUP(B204, Runs[Run ID], Runs[Title]), "— pick a run —")} -> Hickman's Avengers / New Avengers | D204: Avengers World #3 | E204: FALSE | F204: =IF($B204="","",IF($B204=$B203,F203+1,1)) -> 5 | G204: Optional
A205: {=IFERROR(_xlfn.XLOOKUP(B205, Runs[Run ID], Runs[Track]), "— pick a run —")} -> Hickman Saga | B205: hickman-avengers | C205: {=IFERROR(_xlfn.XLOOKUP(B205, Runs[Run ID], Runs[Title]), "— pick a run —")} -> Hickman's Avengers / New Avengers | D205: Avengers World #4 | E205: FALSE | F205: =IF($B205="","",IF($B205=$B204,F204+1,1)) -> 6 | G205: Optional
...

Sheet PREREQS
A1: Run ID | B1: Prereq Run ID | C1: Type | D1: Prerequisite Title | E1: Prerequisite Status | F1: Satisfied
A2: kree-skrull-war | B2: avengers-origin | C2: hard | D2: {=_xlfn.XLOOKUP($B2, Runs[Run ID], Runs[Title])} -> Avengers Origin | E2: {=_xlfn.XLOOKUP($B2, Runs[Run ID], Runs[Status])} -> unread | F2: =IF($E2="read",TRUE,FALSE) -> FALSE
A3: stern-avengers | B3: byrne-ff | C3: soft | D3: {=_xlfn.XLOOKUP($B3, Runs[Run ID], Runs[Title])} -> Byrne's Fantastic Four | E3: {=_xlfn.XLOOKUP($B3, Runs[Run ID], Runs[Status])} -> unread | F3: =IF($E3="read",TRUE,FALSE) -> FALSE
A4: stern-avengers | B4: hercules-prince-of-power | C4: soft | D4: {=_xlfn.XLOOKUP($B4, Runs[Run ID], Runs[Title])} -> Hercules: Prince of Power | E4: {=_xlfn.XLOOKUP($B4, Runs[Run ID], Runs[Status])} -> unread | F4: =IF($E4="read",TRUE,FALSE) -> FALSE
A5: stern-avengers | B5: kree-skrull-war | C5: hard | D5: {=_xlfn.XLOOKUP($B5, Runs[Run ID], Runs[Title])} -> The Kree-Skrull War | E5: {=_xlfn.XLOOKUP($B5, Runs[Run ID], Runs[Status])} -> unread | F5: =IF($E5="read",TRUE,FALSE) -> FALSE
A6: stern-avengers | B6: secret-wars-1984 | C6: soft | D6: {=_xlfn.XLOOKUP($B6, Runs[Run ID], Runs[Title])} -> Secret Wars (1984) | E6: {=_xlfn.XLOOKUP($B6, Runs[Run ID], Runs[Status])} -> unread | F6: =IF($E6="read",TRUE,FALSE) -> FALSE
A7: busiek-avengers | B7: busiek-iron-man | C7: soft | D7: {=_xlfn.XLOOKUP($B7, Runs[Run ID], Runs[Title])} -> Busiek's Iron Man | E7: {=_xlfn.XLOOKUP($B7, Runs[Run ID], Runs[Status])} -> unread | F7: =IF($E7="read",TRUE,FALSE) -> FALSE
A8: busiek-avengers | B8: mantlo-hulk | C8: soft | D8: {=_xlfn.XLOOKUP($B8, Runs[Run ID], Runs[Title])} -> Mantlo's Incredible Hulk | E8: {=_xlfn.XLOOKUP($B8, Runs[Run ID], Runs[Status])} -> unread | F8: =IF($E8="read",TRUE,FALSE) -> FALSE
A9: bendis-disassembled | B9: busiek-avengers | C9: hard | D9: {=_xlfn.XLOOKUP($B9, Runs[Run ID], Runs[Title])} -> Busiek's Avengers + Thunderbolts | E9: {=_xlfn.XLOOKUP($B9, Runs[Run ID], Runs[Status])} -> unread | F9: =IF($E9="read",TRUE,FALSE) -> FALSE
A10: bendis-breakout | B10: bendis-disassembled | C10: hard | D10: {=_xlfn.XLOOKUP($B10, Runs[Run ID], Runs[Title])} -> Avengers: Disassembled | E10: {=_xlfn.XLOOKUP($B10, Runs[Run ID], Runs[Status])} -> unread | F10: =IF($E10="read",TRUE,FALSE) -> FALSE
A11: bendis-house-of-m | B11: bendis-breakout | C11: hard | D11: {=_xlfn.XLOOKUP($B11, Runs[Run ID], Runs[Title])} -> New Avengers Breakout | E11: {=_xlfn.XLOOKUP($B11, Runs[Run ID], Runs[Status])} -> unread | F11: =IF($E11="read",TRUE,FALSE) -> FALSE
A12: bendis-civil-war | B12: brubaker-daredevil | C12: soft | D12: {=_xlfn.XLOOKUP($B12, Runs[Run ID], Runs[Title])} -> Brubaker's Daredevil | E12: {=_xlfn.XLOOKUP($B12, Runs[Run ID], Runs[Status])} -> unread | F12: =IF($E12="read",TRUE,FALSE) -> FALSE
A13: bendis-initiative | B13: bendis-civil-war | C13: hard | D13: {=_xlfn.XLOOKUP($B13, Runs[Run ID], Runs[Title])} -> Civil War | E13: {=_xlfn.XLOOKUP($B13, Runs[Run ID], Runs[Status])} -> unread | F13: =IF($E13="read",TRUE,FALSE) -> FALSE
... A437: gillen-young-avengers | B437: childrens-crusade | C437: hard | D437: {=_xlfn.XLOOKUP($B437, Runs[Run ID], Runs[Title])} -> childrens-crusade | E437: {=_xlfn.XLOOKUP($B437, Runs[Run ID], Runs[Status])} -> unread | F437: =IF($E437="read",TRUE,FALSE) -> FALSE

Sheet TRACKS
A1: Track | B1: Total Runs | C1: Runs Read | D1: Spine Progress | E1: Issues Read | F1: Total Issues | G1: Percent Read | H1: Ready Now
A2: TOTAL | B2: =SUM(B3:B35) -> 222 | C2: =SUM(C3:C35) -> 1 | E2: =SUM(E3:E35) -> 31 | F2: =SUM(F3:F35) -> 8703 | G2: =AVERAGE(G3:G35) -> 0.0034663983 | H2: =SUM(H3:H35) -> 34
A3: =IFERROR(__xludf.DUMMYFUNCTION("SORT(UNIQUE(TRANSPOSE(TRIM(SPLIT(TEXTJOIN("","", TRUE, RUNS!$C$2:$C1000), "","")))))"),"Avengers") -> Avengers | B3: =SUMPRODUCT(--ISNUMBER(SEARCH(","&$A3&",", ","&SUBSTITUTE(RUNS!$C$2:$C$308,", ",",")&","))) -> 27 | C3: =SUMPRODUCT(--ISNUMBER(SEARCH(","&$A3&",", ","&SUBSTITUTE(RUNS!$C$2:$C$308,", ",",")&",")), --(RUNS!$K$2:$K$308="read")) -> 0 | E3: =SUMPRODUCT(--ISNUMBER(SEARCH(","&$A3&",", ","&SUBSTITUTE(RUNS!$C$2:$C$308,", ",",")&",")), --(RUNS!$K$2:$K$308="read"), N(RUNS!$G$2:$G$308)) -> 0 | F3: =SUMPRODUCT(--ISNUMBER(SEARCH(","&$A3&",", ","&SUBSTITUTE(RUNS!$C$2:$C$308,", ",",")&",")), N(RUNS!$G$2:$G$308)) -> 1296 | G3: =IF($F3=0,0,$E3/$F3) -> 0 | H3: =SUMPRODUCT(--ISNUMBER(SEARCH(","&$A3&",", ","&SUBSTITUTE(RUNS!$C$2:$C$308,", ",",")&",")), --(RUNS!$S$2:$S$308="READY-ALL"), --(RUNS!$K$2:$K$308="unread")) -> 1
A4: =IFERROR(__xludf.DUMMYFUNCTION("""COMPUTED_VALUE"""),"Black Panther") -> Black Panther | B4: =SUMPRODUCT(--ISNUMBER(SEARCH(","&$A4&",", ","&SUBSTITUTE(RUNS!$C$2:$C$308,", ",",")&","))) -> 7 | C4: =SUMPRODUCT(--ISNUMBER(SEARCH(","&$A4&",", ","&SUBSTITUTE(RUNS!$C$2:$C$308,", ",",")&",")), --(RUNS!$K$2:$K$308="read")) -> 0 | E4: =SUMPRODUCT(--ISNUMBER(SEARCH(","&$A4&",", ","&SUBSTITUTE(RUNS!$C$2:$C$308,", ",",")&",")), --(RUNS!$K$2:$K$308="read"), N(RUNS!$G$2:$G$308)) -> 0 | F4: =SUMPRODUCT(--ISNUMBER(SEARCH(","&$A4&",", ","&SUBSTITUTE(RUNS!$C$2:$C$308,", ",",")&",")), N(RUNS!$G$2:$G$308)) -> 328 | G4: =IF($F4=0,0,$E4/$F4) -> 0 | H4: =SUMPRODUCT(--ISNUMBER(SEARCH(","&$A4&",", ","&SUBSTITUTE(RUNS!$C$2:$C$308,", ",",")&",")), --(RUNS!$S$2:$S$308="READY-ALL"), --(RUNS!$K$2:$K$308="unread")) -> 0
A5: =IFERROR(__xludf.DUMMYFUNCTION("""COMPUTED_VALUE"""),"Black Widow") -> Black Widow | B5: =SUMPRODUCT(--ISNUMBER(SEARCH(","&$A5&",", ","&SUBSTITUTE(RUNS!$C$2:$C$308,", ",",")&","))) -> 2 | C5: =SUMPRODUCT(--ISNUMBER(SEARCH(","&$A5&",", ","&SUBSTITUTE(RUNS!$C$2:$C$308,", ",",")&",")), --(RUNS!$K$2:$K$308="read")) -> 0 | E5: =SUMPRODUCT(--ISNUMBER(SEARCH(","&$A5&",", ","&SUBSTITUTE(RUNS!$C$2:$C$308,", ",",")&",")), --(RUNS!$K$2:$K$308="read"), N(RUNS!$G$2:$G$308)) -> 0 | F5: =SUMPRODUCT(--ISNUMBER(SEARCH(","&$A5&",", ","&SUBSTITUTE(RUNS!$C$2:$C$308,", ",",")&",")), N(RUNS!$G$2:$G$308)) -> 74 | G5: =IF($F5=0,0,$E5/$F5) -> 0 | H5: =SUMPRODUCT(--ISNUMBER(SEARCH(","&$A5&",", ","&SUBSTITUTE(RUNS!$C$2:$C$308,", ",",")&",")), --(RUNS!$S$2:$S$308="READY-ALL"), --(RUNS!$K$2:$K$308="unread")) -> 1
A6: =IFERROR(__xludf.DUMMYFUNCTION("""COMPUTED_VALUE"""),"Captain America") -> Captain America | B6: =SUMPRODUCT(--ISNUMBER(SEARCH(","&$A6&",", ","&SUBSTITUTE(RUNS!$C$2:$C$308,", ",",")&","))) -> 12 | C6: =SUMPRODUCT(--ISNUMBER(SEARCH(","&$A6&",", ","&SUBSTITUTE(RUNS!$C$2:$C$308,", ",",")&",")), --(RUNS!$K$2:$K$308="read")) -> 0 | E6: =SUMPRODUCT(--ISNUMBER(SEARCH(","&$A6&",", ","&SUBSTITUTE(RUNS!$C$2:$C$308,", ",",")&",")), --(RUNS!$K$2:$K$308="read"), N(RUNS!$G$2:$G$308)) -> 0 | F6: =SUMPRODUCT(--ISNUMBER(SEARCH(","&$A6&",", ","&SUBSTITUTE(RUNS!$C$2:$C$308,", ",",")&",")), N(RUNS!$G$2:$G$308)) -> 554 | G6: =IF($F6=0,0,$E6/$F6) -> 0 | H6: =SUMPRODUCT(--ISNUMBER(SEARCH(","&$A6&",", ","&SUBSTITUTE(RUNS!$C$2:$C$308,", ",",")&",")), --(RUNS!$S$2:$S$308="READY-ALL"), --(RUNS!$K$2:$K$308="unread")) -> 1
A7: =IFERROR(__xludf.DUMMYFUNCTION("""COMPUTED_VALUE"""),"Captain Marvel") -> Captain Marvel | B7: =SUMPRODUCT(--ISNUMBER(SEARCH(","&$A7&",", ","&SUBSTITUTE(RUNS!$C$2:$C$308,", ",",")&","))) -> 3 | C7: =SUMPRODUCT(--ISNUMBER(SEARCH(","&$A7&",", ","&SUBSTITUTE(RUNS!$C$2:$C$308,", ",",")&",")), --(RUNS!$K$2:$K$308="read")) -> 0 | E7: =SUMPRODUCT(--ISNUMBER(SEARCH(","&$A7&",", ","&SUBSTITUTE(RUNS!$C$2:$C$308,", ",",")&",")), --(RUNS!$K$2:$K$308="read"), N(RUNS!$G$2:$G$308)) -> 0 | F7: =SUMPRODUCT(--ISNUMBER(SEARCH(","&$A7&",", ","&SUBSTITUTE(RUNS!$C$2:$C$308,", ",",")&",")), N(RUNS!$G$2:$G$308)) -> 219 | G7: =IF($F7=0,0,$E7/$F7) -> 0 | H7: =SUMPRODUCT(--ISNUMBER(SEARCH(","&$A7&",", ","&SUBSTITUTE(RUNS!$C$2:$C$308,", ",",")&",")), --(RUNS!$S$2:$S$308="READY-ALL"), --(RUNS!$K$2:$K$308="unread")) -> 1
A8: =IFERROR(__xludf.DUMMYFUNCTION("""COMPUTED_VALUE"""),"Cosmic") -> Cosmic | B8: =SUMPRODUCT(--ISNUMBER(SEARCH(","&$A8&",", ","&SUBSTITUTE(RUNS!$C$2:$C$308,", ",",")&","))) -> 18 | C8: =SUMPRODUCT(--ISNUMBER(SEARCH(","&$A8&",", ","&SUBSTITUTE(RUNS!$C$2:$C$308,", ",",")&",")), --(RUNS!$K$2:$K$308="read")) -> 0 | E8: =SUMPRODUCT(--ISNUMBER(SEARCH(","&$A8&",", ","&SUBSTITUTE(RUNS!$C$2:$C$308,", ",",")&",")), --(RUNS!$K$2:$K$308="read"), N(RUNS!$G$2:$G$308)) -> 0 | F8: =SUMPRODUCT(--ISNUMBER(SEARCH(","&$A8&",", ","&SUBSTITUTE(RUNS!$C$2:$C$308,", ",",")&",")), N(RUNS!$G$2:$G$308)) -> 513 | G8: =IF($F8=0,0,$E8/$F8) -> 0 | H8: =SUMPRODUCT(--ISNUMBER(SEARCH(","&$A8&",", ","&SUBSTITUTE(RUNS!$C$2:$C$308,", ",",")&",")), --(RUNS!$S$2:$S$308="READY-ALL"), --(RUNS!$K$2:$K$308="unread")) -> 0
A9: =IFERROR(__xludf.DUMMYFUNCTION("""COMPUTED_VALUE"""),"Daredevil") -> Daredevil | B9: =SUMPRODUCT(--ISNUMBER(SEARCH(","&$A9&",", ","&SUBSTITUTE(RUNS!$C$2:$C$308,", ",",")&","))) -> 12 | C9: =SUMPRODUCT(--ISNUMBER(SEARCH(","&$A9&",", ","&SUBSTITUTE(RUNS!$C$2:$C$308,", ",",")&",")), --(RUNS!$K$2:$K$308="read")) -> 0 | E9: =SUMPRODUCT(--ISNUMBER(SEARCH(","&$A9&",", ","&SUBSTITUTE(RUNS!$C$2:$C$308,", ",",")&",")), --(RUNS!$K$2:$K$308="read"), N(RUNS!$G$2:$G$308)) -> 0 | F9: =SUMPRODUCT(--ISNUMBER(SEARCH(","&$A9&",", ","&SUBSTITUTE(RUNS!$C$2:$C$308,", ",",")&",")), N(RUNS!$G$2:$G$308)) -> 442 | G9: =IF($F9=0,0,$E9/$F9) -> 0 | H9: =SUMPRODUCT(--ISNUMBER(SEARCH(","&$A9&",", ","&SUBSTITUTE(RUNS!$C$2:$C$308,", ",",")&",")), --(RUNS!$S$2:$S$308="READY-ALL"), --(RUNS!$K$2:$K$308="unread")) -> 1
A10: =IFERROR(__xludf.DUMMYFUNCTION("""COMPUTED_VALUE"""),"Deadpool") -> Deadpool | B10: =SUMPRODUCT(--ISNUMBER(SEARCH(","&$A10&",", ","&SUBSTITUTE(RUNS!$C$2:$C$308,", ",",")&","))) -> 2 | C10: =SUMPRODUCT(--ISNUMBER(SEARCH(","&$A10&",", ","&SUBSTITUTE(RUNS!$C$2:$C$308,", ",",")&",")), --(RUNS!$K$2:$K$308="read")) -> 0 | E10: =SUMPRODUCT(--ISNUMBER(SEARCH(","&$A10&",", ","&SUBSTITUTE(RUNS!$C$2:$C$308,", ",",")&",")), --(RUNS!$K$2:$K$308="read"), N(RUNS!$G$2:$G$308)) -> 0 | F10: =SUMPRODUCT(--ISNUMBER(SEARCH(","&$A10&",", ","&SUBSTITUTE(RUNS!$C$2:$C$308,", ",",")&",")), N(RUNS!$G$2:$G$308)) -> 57 | G10: =IF($F10=0,0,$E10/$F10) -> 0 | H10: =SUMPRODUCT(--ISNUMBER(SEARCH(","&$A10&",", ","&SUBSTITUTE(RUNS!$C$2:$C$308,", ",",")&",")), --(RUNS!$S$2:$S$308="READY-ALL"), --(RUNS!$K$2:$K$308="unread")) -> 1
A11: =IFERROR(__xludf.DUMMYFUNCTION("""COMPUTED_VALUE"""),"Defenders") -> Defenders | B11: =SUMPRODUCT(--ISNUMBER(SEARCH(","&$A11&",", ","&SUBSTITUTE(RUNS!$C$2:$C$308,", ",",")&","))) -> 1 | C11: =SUMPRODUCT(--ISNUMBER(SEARCH(","&$A11&",", ","&SUBSTITUTE(RUNS!$C$2:$C$308,", ",",")&",")), --(RUNS!$K$2:$K$308="read")) -> 0 | E11: =SUMPRODUCT(--ISNUMBER(SEARCH(","&$A11&",", ","&SUBSTITUTE(RUNS!$C$2:$C$308,", ",",")&",")), --(RUNS!$K$2:$K$308="read"), N(RUNS!$G$2:$G$308)) -> 0 | F11: =SUMPRODUCT(--ISNUMBER(SEARCH(","&$A11&",", ","&SUBSTITUTE(RUNS!$C$2:$C$308,", ",",")&",")), N(RUNS!$G$2:$G$308)) -> 62 | G11: =IF($F11=0,0,$E11/$F11) -> 0 | H11: =SUMPRODUCT(--ISNUMBER(SEARCH(","&$A11&",", ","&SUBSTITUTE(RUNS!$C$2:$C$308,", ",",")&",")), --(RUNS!$S$2:$S$308="READY-ALL"), --(RUNS!$K$2:$K$308="unread")) -> 1
